Workbook

Sheet 대시보드 Dashboard
B1: API 연동 개발 트래커 — 대시보드 · API Integration Tracker — Dashboard
B2: ="오늘 Today "&TEXT(TODAY(),"yyyy-mm-dd")&" · 카테고리 시트에서 자동 집계 · auto-counted from the category sheets · 데이터 Data: SharePoint API Dev Tracker (19 Oct) + OMH-CRM (18 Oct)" -> 오늘 Today 2026-10-30 · 카테고리 시트에서 자동 집계 · auto-counted from the category sheets · 데이터 Data: SharePoint API Dev Tracker (19 Oct) + OMH-CRM (18 Oct)
B4: 전체 Total | D4: 라이브 Live | F4: 개발·테스트 Dev / Test | H4: 계약·NDA NDA / Contract | J4: 파이프라인 Pipeline | L4: 60일+ 정체 Stalled 60d+ | N4: 체이스 지연·필요 Chase overdue / needed
B5: =COUNTA('스위칭 업체 Switch vendors'!$G$5:$G$400)+COUNTA('스위칭 연동 Switching'!$G$5:$G$400)+COUNTA('서드파티 연동 3rd Party'!$G$5:$G$399)+COUNTA('우리가 공급사 OMH Supply'!$G$5:$G$399)+COUNTA('상호연동 Two-way'!$G$5:$G$400) -> 142 | D5: =COUNTIF('스위칭 업체 Switch vendors'!$B$5:$B$400,"Live")+COUNTIF('스위칭 업체 Switch vendors'!$B$5:$B$400,"Partially Live")+COUNTIF('스위칭 연동 Switching'!$B$5:$B$400,"Live")+COUNTIF('스위칭 연동 Switching'!$B$5:$B$400,"Partially Live")+COUNTIF('서드파티 연동 3rd Party'!$B$5:$B$399,"Live")+COUNTIF('서드파티 연동 3rd Party'!$B$5:$B$399,"Partially Live")+COUNTIF('우리가 공급사 OMH Supply'!$B$5:$B$399,"Live")+COUNTIF('우리가 공급사 OMH Supply'!$B$5:$B$399,"Partially Live")+COUNTIF('상호연동 Two-way'!$B$5:$B$400,"Live")+COUNTIF('상호연동 Two-way'!$B$5:$B$400,"Partially Live") -> 35 | F5: =COUNTIF('스위칭 업체 Switch vendors'!$B$5:$B$400,"In Development")+COUNTIF('스위칭 업체 Switch vendors'!$B$5:$B$400,"Testing")+COUNTIF('스위칭 업체 Switch vendors'!$B$5:$B$400,"Pending Live")+COUNTIF('스위칭 연동 Switching'!$B$5:$B$400,"In Development")+COUNTIF('스위칭 연동 Switching'!$B$5:$B$400,"Testing")+COUNTIF('스위칭 연동 Switching'!$B$5:$B$400,"Pending Live")+COUNTIF('서드파티 연동 3rd Party'!$B$5:$B$399,"In Development")+COUNTIF('서드파티 연동 3rd Party'!$B$5:$B$399,"Testing")+COUNTIF('서드파티 연동 3rd Party'!$B$5:$B$399,"Pending Live")+COUNTIF('우리가 공급사 OMH Supply'!$B$5:$B$399,"In Development")+COUNTIF('우리가 공급사 OMH Supply'!$B$5:$B$399,"Testing")+COUNTIF('우리가 공급사 OMH Supply'!$B$5:$B$399,"Pending Live")+COUNTIF('상호연동 Two-way'!$B$5:$B$400,"In Development")+COUNTIF('상호연동 Two-way'!$B$5:$B$400,"Testing")+COUNTIF('상호연동 Two-way'!$B$5:$B$400,"Pending Live") -> 14 | H5: =COUNTIF('스위칭 업체 Switch vendors'!$B$5:$B$400,"NDA/Contract")+COUNTIF('스위칭 연동 Switching'!$B$5:$B$400,"NDA/Contract")+COUNTIF('서드파티 연동 3rd Party'!$B$5:$B$399,"NDA/Contract")+COUNTIF('우리가 공급사 OMH Supply'!$B$5:$B$399,"NDA/Contract")+COUNTIF('상호연동 Two-way'!$B$5:$B$400,"NDA/Contract") -> 16 | J5: =COUNTIF('스위칭 업체 Switch vendors'!$B$5:$B$400,"Pipeline")+COUNTIF('스위칭 업체 Switch vendors'!$B$5:$B$400,"Contact")+COUNTIF('스위칭 연동 Switching'!$B$5:$B$400,"Pipeline")+COUNTIF('스위칭 연동 Switching'!$B$5:$B$400,"Contact")+COUNTIF('서드파티 연동 3rd Party'!$B$5:$B$399,"Pipeline")+COUNTIF('서드파티 연동 3rd Party'!$B$5:$B$399,"Contact")+COUNTIF('우리가 공급사 OMH Supply'!$B$5:$B$399,"Pipeline")+COUNTIF('우리가 공급사 OMH Supply'!$B$5:$B$399,"Contact")+COUNTIF('상호연동 Two-way'!$B$5:$B$400,"Pipeline")+COUNTIF('상호연동 Two-way'!$B$5:$B$400,"Contact") -> 77 | L5: =COUNTIF('스위칭 업체 Switch vendors'!$V$5:$V$400,"Stalled 60d+")+COUNTIF('스위칭 업체 Switch vendors'!$V$5:$V$400,"Stalled 90d+")+COUNTIF('스위칭 연동 Switching'!$S$5:$S$400,"Stalled 60d+")+COUNTIF('스위칭 연동 Switching'!$S$5:$S$400,"Stalled 90d+")+COUNTIF('서드파티 연동 3rd Party'!$S$5:$S$399,"Stalled 60d+")+COUNTIF('서드파티 연동 3rd Party'!$S$5:$S$399,"Stalled 90d+")+COUNTIF('우리가 공급사 OMH Supply'!$S$5:$S$399,"Stalled 60d+")+COUNTIF('우리가 공급사 OMH Supply'!$S$5:$S$399,"Stalled 90d+")+COUNTIF('상호연동 Two-way'!$V$5:$V$400,"Stalled 60d+")+COUNTIF('상호연동 Two-way'!$V$5:$V$400,"Stalled 90d+") -> 14 | N5: =COUNTIF('스위칭 업체 Switch vendors'!$AC$5:$AC$400,"Chase Overdue")+COUNTIF('스위칭 업체 Switch vendors'!$AC$5:$AC$400,"Chase Needed")+COUNTIF('스위칭 연동 Switching'!$Z$5:$Z$400,"Chase Overdue")+COUNTIF('스위칭 연동 Switching'!$Z$5:$Z$400,"Chase Needed")+COUNTIF('서드파티 연동 3rd Party'!$Z$5:$Z$399,"Chase Overdue")+COUNTIF('서드파티 연동 3rd Party'!$Z$5:$Z$399,"Chase Needed")+COUNTIF('우리가 공급사 OMH Supply'!$Z$5:$Z$399,"Chase Overdue")+COUNTIF('우리가 공급사 OMH Supply'!$Z$5:$Z$399,"Chase Needed")+COUNTIF('상호연동 Two-way'!$AC$5:$AC$400,"Chase Overdue")+COUNTIF('상호연동 Two-way'!$AC$5:$AC$400,"Chase Needed") -> 45
B8: 카테고리 × 개발 상태 · Category × status | O8: 지역 × 카테고리 (진행 중) · Region × category (open items)
B9: 카테고리 · Category | C9: Live | D9: Partially Live | E9: Pending Live | F9: Testing | G9: In Development | H9: NDA/Contract | I9: Pipeline | J9: Contact | K9: 보류/드롭 Hold/Drop | L9: 합계 Total | O9: 지역 · Region | P9: 스위칭 업체 Switch vendors | Q9: 스위칭 연동 Switching | R9: 서드파티 연동 3rd Party | S9: 우리가 공급사 OMH Supply | T9: 상호연동 Two-way | U9: 합계 Total
B10: 스위칭 업체 Switch vendors | C10: =COUNTIF('스위칭 업체 Switch vendors'!$B$5:$B$400,"Live") -> 0 | D10: =COUNTIF('스위칭 업체 Switch vendors'!$B$5:$B$400,"Partially Live") -> 0 | E10: =COUNTIF('스위칭 업체 Switch vendors'!$B$5:$B$400,"Pending Live") -> 0 | F10: =COUNTIF('스위칭 업체 Switch vendors'!$B$5:$B$400,"Testing") -> 1 | G10: =COUNTIF('스위칭 업체 Switch vendors'!$B$5:$B$400,"In Development") -> 1 | H10: =COUNTIF('스위칭 업체 Switch vendors'!$B$5:$B$400,"NDA/Contract") -> 0 | I10: =COUNTIF('스위칭 업체 Switch vendors'!$B$5:$B$400,"Pipeline") -> 0 | J10: =COUNTIF('스위칭 업체 Switch vendors'!$B$5:$B$400,"Contact") -> 6 | K10: =COUNTA('스위칭 업체 Switch vendors'!$D$5:$D$400) -> 5 | L10: =COUNTA('스위칭 업체 Switch vendors'!$G$5:$G$400) -> 8 | O10: 한국 · Korea | P10: =COUNTIFS('스위칭 업체 Switch vendors'!$E$5:$E$400,"한국 · Korea",'스위칭 업체 Switch vendors'!$B$5:$B$400,"<>Live",'스위칭 업체 Switch vendors'!$D$5:$D$400,"") -> 0 | Q10: =COUNTIFS('스위칭 연동 Switching'!$E$5:$E$400,"한국 · Korea",'스위칭 연동 Switching'!$B$5:$B$400,"<>Live",'스위칭 연동 Switching'!$D$5:$D$400,"") -> 0 | R10: =COUNTIFS('서드파티 연동 3rd Party'!$E$5:$E$399,"한국 · Korea",'서드파티 연동 3rd Party'!$B$5:$B$399,"<>Live",'서드파티 연동 3rd Party'!$D$5:$D$399,"") -> 0 | S10: =COUNTIFS('우리가 공급사 OMH Supply'!$E$5:$E$399,"한국 · Korea",'우리가 공급사 OMH Supply'!$B$5:$B$399,"<>Live",'우리가 공급사 OMH Supply'!$D$5:$D$399,"") -> 8 | T10: =COUNTIFS('상호연동 Two-way'!$E$5:$E$400,"한국 · Korea",'상호연동 Two-way'!$B$5:$B$400,"<>Live",'상호연동 Two-way'!$D$5:$D$400,"") -> 0 | U10: =SUM(P10:T10) -> 8
B11: 스위칭 연동 Switching | C11: =COUNTIF('스위칭 연동 Switching'!$B$5:$B$400,"Live") -> 0 | D11: =COUNTIF('스위칭 연동 Switching'!$B$5:$B$400,"Partially Live") -> 0 | E11: =COUNTIF('스위칭 연동 Switching'!$B$5:$B$400,"Pending Live") -> 0 | F11: =COUNTIF('스위칭 연동 Switching'!$B$5:$B$400,"Testing") -> 0 | G11: =COUNTIF('스위칭 연동 Switching'!$B$5:$B$400,"In Development") -> 0 | H11: =COUNTIF('스위칭 연동 Switching'!$B$5:$B$400,"NDA/Contract") -> 3 | I11: =COUNTIF('스위칭 연동 Switching'!$B$5:$B$400,"Pipeline") -> 0 | J11: =COUNTIF('스위칭 연동 Switching'!$B$5:$B$400,"Contact") -> 13 | K11: =COUNTA('스위칭 연동 Switching'!$D$5:$D$400) -> 0 | L11: =COUNTA('스위칭 연동 Switching'!$G$5:$G$400) -> 16 | O11: 일본 · Japan | P11: =COUNTIFS('스위칭 업체 Switch vendors'!$E$5:$E$400,"일본 · Japan",'스위칭 업체 Switch vendors'!$B$5:$B$400,"<>Live",'스위칭 업체 Switch vendors'!$D$5:$D$400,"") -> 0 | Q11: =COUNTIFS('스위칭 연동 Switching'!$E$5:$E$400,"일본 · Japan",'스위칭 연동 Switching'!$B$5:$B$400,"<>Live",'스위칭 연동 Switching'!$D$5:$D$400,"") -> 1 | R11: =COUNTIFS('서드파티 연동 3rd Party'!$E$5:$E$399,"일본 · Japan",'서드파티 연동 3rd Party'!$B$5:$B$399,"<>Live",'서드파티 연동 3rd Party'!$D$5:$D$399,"") -> 3 | S11: =COUNTIFS('우리가 공급사 OMH Supply'!$E$5:$E$399,"일본 · Japan",'우리가 공급사 OMH Supply'!$B$5:$B$399,"<>Live",'우리가 공급사 OMH Supply'!$D$5:$D$399,"") -> 2 | T11: =COUNTIFS('상호연동 Two-way'!$E$5:$E$400,"일본 · Japan",'상호연동 Two-way'!$B$5:$B$400,"<>Live",'상호연동 Two-way'!$D$5:$D$400,"") -> 0 | U11: =SUM(P11:T11) -> 6
B12: 서드파티 연동 3rd Party | C12: =COUNTIF('서드파티 연동 3rd Party'!$B$5:$B$399,"Live") -> 0 | D12: =COUNTIF('서드파티 연동 3rd Party'!$B$5:$B$399,"Partially Live") -> 0 | E12: =COUNTIF('서드파티 연동 3rd Party'!$B$5:$B$399,"Pending Live") -> 0 | F12: =COUNTIF('서드파티 연동 3rd Party'!$B$5:$B$399,"Testing") -> 0 | G12: =COUNTIF('서드파티 연동 3rd Party'!$B$5:$B$399,"In Development") -> 0 | H12: =COUNTIF('서드파티 연동 3rd Party'!$B$5:$B$399,"NDA/Contract") -> 0 | I12: =COUNTIF('서드파티 연동 3rd Party'!$B$5:$B$399,"Pipeline") -> 0 | J12: =COUNTIF('서드파티 연동 3rd Party'!$B$5:$B$399,"Contact") -> 4 | K12: =COUNTA('서드파티 연동 3rd Party'!$D$5:$D$399) -> 0 | L12: =COUNTA('서드파티 연동 3rd Party'!$G$5:$G$399) -> 4 | O12: 중화권 · Greater China | P12: =COUNTIFS('스위칭 업체 Switch vendors'!$E$5:$E$400,"중화권 · Greater China",'스위칭 업체 Switch vendors'!$B$5:$B$400,"<>Live",'스위칭 업체 Switch vendors'!$D$5:$D$400,"") -> 1 | Q12: =COUNTIFS('스위칭 연동 Switching'!$E$5:$E$400,"중화권 · Greater China",'스위칭 연동 Switching'!$B$5:$B$400,"<>Live",'스위칭 연동 Switching'!$D$5:$D$400,"") -> 1 | R12: =COUNTIFS('서드파티 연동 3rd Party'!$E$5:$E$399,"중화권 · Greater China",'서드파티 연동 3rd Party'!$B$5:$B$399,"<>Live",'서드파티 연동 3rd Party'!$D$5:$D$399,"") -> 1 | S12: =COUNTIFS('우리가 공급사 OMH Supply'!$E$5:$E$399,"중화권 · Greater China",'우리가 공급사 OMH Supply'!$B$5:$B$399,"<>Live",'우리가 공급사 OMH Supply'!$D$5:$D$399,"") -> 22 | T12: =COUNTIFS('상호연동 Two-way'!$E$5:$E$400,"중화권 · Greater China",'상호연동 Two-way'!$B$5:$B$400,"<>Live",'상호연동 Two-way'!$D$5:$D$400,"") -> 1 | U12: =SUM(P12:T12) -> 26
B13: 우리가 공급사 OMH Supply | C13: =COUNTIF('우리가 공급사 OMH Supply'!$B$5:$B$399,"Live") -> 31 | D13: =COUNTIF('우리가 공급사 OMH Supply'!$B$5:$B$399,"Partially Live") -> 0 | E13: =COUNTIF('우리가 공급사 OMH Supply'!$B$5:$B$399,"Pending Live") -> 1 | F13: =COUNTIF('우리가 공급사 OMH Supply'!$B$5:$B$399,"Testing") -> 2 | G13: =COUNTIF('우리가 공급사 OMH Supply'!$B$5:$B$399,"In Development") -> 7 | H13: =COUNTIF('우리가 공급사 OMH Supply'!$B$5:$B$399,"NDA/Contract") -> 5 | I13: =COUNTIF('우리가 공급사 OMH Supply'!$B$5:$B$399,"Pipeline") -> 2 | J13: =COUNTIF('우리가 공급사 OMH Supply'!$B$5:$B$399,"Contact") -> 46 | K13: =COUNTA('우리가 공급사 OMH Supply'!$D$5:$D$399) -> 1 | L13: =COUNTA('우리가 공급사 OMH Supply'!$G$5:$G$399) -> 94 | O13: 동남아 · SE Asia | P13: =COUNTIFS('스위칭 업체 Switch vendors'!$E$5:$E$400,"동남아 · SE Asia",'스위칭 업체 Switch vendors'!$B$5:$B$400,"<>Live",'스위칭 업체 Switch vendors'!$D$5:$D$400,"") -> 0 | Q13: =COUNTIFS('스위칭 연동 Switching'!$E$5:$E$400,"동남아 · SE Asia",'스위칭 연동 Switching'!$B$5:$B$400,"<>Live",'스위칭 연동 Switching'!$D$5:$D$400,"") -> 3 | R13: =COUNTIFS('서드파티 연동 3rd Party'!$E$5:$E$399,"동남아 · SE Asia",'서드파티 연동 3rd Party'!$B$5:$B$399,"<>Live",'서드파티 연동 3rd Party'!$D$5:$D$399,"") -> 0 | S13: =COUNTIFS('우리가 공급사 OMH Supply'!$E$5:$E$399,"동남아 · SE Asia",'우리가 공급사 OMH Supply'!$B$5:$B$399,"<>Live",'우리가 공급사 OMH Supply'!$D$5:$D$399,"") -> 17 | T13: =COUNTIFS('상호연동 Two-way'!$E$5:$E$400,"동남아 · SE Asia",'상호연동 Two-way'!$B$5:$B$400,"<>Live",'상호연동 Two-way'!$D$5:$D$400,"") -> 7 | U13: =SUM(P13:T13) -> 27
B14: 상호연동 Two-way | C14: =COUNTIF('상호연동 Two-way'!$B$5:$B$400,"Live") -> 4 | D14: =COUNTIF('상호연동 Two-way'!$B$5:$B$400,"Partially Live") -> 0 | E14: =COUNTIF('상호연동 Two-way'!$B$5:$B$400,"Pending Live") -> 0 | F14: =COUNTIF('상호연동 Two-way'!$B$5:$B$400,"Testing") -> 0 | G14: =COUNTIF('상호연동 Two-way'!$B$5:$B$400,"In Development") -> 2 | H14: =COUNTIF('상호연동 Two-way'!$B$5:$B$400,"NDA/Contract") -> 8 | I14: =COUNTIF('상호연동 Two-way'!$B$5:$B$400,"Pipeline") -> 0 | J14: =COUNTIF('상호연동 Two-way'!$B$5:$B$400,"Contact") -> 6 | K14: =COUNTA('상호연동 Two-way'!$D$5:$D$400) -> 0 | L14: =COUNTA('상호연동 Two-way'!$G$5:$G$400) -> 20 | O14: 인도 · India | P14: =COUNTIFS('스위칭 업체 Switch vendors'!$E$5:$E$400,"인도 · India",'스위칭 업체 Switch vendors'!$B$5:$B$400,"<>Live",'스위칭 업체 Switch vendors'!$D$5:$D$400,"") -> 1 | Q14: =COUNTIFS('스위칭 연동 Switching'!$E$5:$E$400,"인도 · India",'스위칭 연동 Switching'!$B$5:$B$400,"<>Live",'스위칭 연동 Switching'!$D$5:$D$400,"") -> 4 | R14: =COUNTIFS('서드파티 연동 3rd Party'!$E$5:$E$399,"인도 · India",'서드파티 연동 3rd Party'!$B$5:$B$399,"<>Live",'서드파티 연동 3rd Party'!$D$5:$D$399,"") -> 0 | S14: =COUNTIFS('우리가 공급사 OMH Supply'!$E$5:$E$399,"인도 · India",'우리가 공급사 OMH Supply'!$B$5:$B$399,"<>Live",'우리가 공급사 OMH Supply'!$D$5:$D$399,"") -> 9 | T14: =COUNTIFS('상호연동 Two-way'!$E$5:$E$400,"인도 · India",'상호연동 Two-way'!$B$5:$B$400,"<>Live",'상호연동 Two-way'!$D$5:$D$400,"") -> 1 | U14: =SUM(P14:T14) -> 15
B15: 합계 · Total | C15: =SUM(C10:C14) -> 35 | D15: =SUM(D10:D14) -> 0 | E15: =SUM(E10:E14) -> 1 | F15: =SUM(F10:F14) -> 3 | G15: =SUM(G10:G14) -> 10 | H15: =SUM(H10:H14) -> 16 | I15: =SUM(I10:I14) -> 2 | J15: =SUM(J10:J14) -> 75 | ... L15: =SUM(L10:L14) -> 142 | O15: 중동·러시아 · ME & Russia | P15: =COUNTIFS('스위칭 업체 Switch vendors'!$E$5:$E$400,"중동·러시아 · ME & Russia",'스위칭 업체 Switch vendors'!$B$5:$B$400,"<>Live",'스위칭 업체 Switch vendors'!$D$5:$D$400,"") -> 0 | Q15: =COUNTIFS('스위칭 연동 Switching'!$E$5:$E$400,"중동·러시아 · ME & Russia",'스위칭 연동 Switching'!$B$5:$B$400,"<>Live",'스위칭 연동 Switching'!$D$5:$D$400,"") -> 2 | R15: =COUNTIFS('서드파티 연동 3rd Party'!$E$5:$E$399,"중동·러시아 · ME & Russia",'서드파티 연동 3rd Party'!$B$5:$B$399,"<>Live",'서드파티 연동 3rd Party'!$D$5:$D$399,"") -> 0 | S15: =COUNTIFS('우리가 공급사 OMH Supply'!$E$5:$E$399,"중동·러시아 · ME & Russia",'우리가 공급사 OMH Supply'!$B$5:$B$399,"<>Live",'우리가 공급사 OMH Supply'!$D$5:$D$399,"") -> 3 | T15: =COUNTIFS('상호연동 Two-way'!$E$5:$E$400,"중동·러시아 · ME & Russia",'상호연동 Two-way'!$B$5:$B$400,"<>Live",'상호연동 Two-way'!$D$5:$D$400,"") -> 4 | U15: =SUM(P15:T15) -> 9
O16: 유럽·미주 · Europe & Americas | P16: =COUNTIFS('스위칭 업체 Switch vendors'!$E$5:$E$400,"유럽·미주 · Europe & Americas",'스위칭 업체 Switch vendors'!$B$5:$B$400,"<>Live",'스위칭 업체 Switch vendors'!$D$5:$D$400,"") -> 1 | Q16: =COUNTIFS('스위칭 연동 Switching'!$E$5:$E$400,"유럽·미주 · Europe & Americas",'스위칭 연동 Switching'!$B$5:$B$400,"<>Live",'스위칭 연동 Switching'!$D$5:$D$400,"") -> 5 | R16: =COUNTIFS('서드파티 연동 3rd Party'!$E$5:$E$399,"유럽·미주 · Europe & Americas",'서드파티 연동 3rd Party'!$B$5:$B$399,"<>Live",'서드파티 연동 3rd Party'!$D$5:$D$399,"") -> 0 | S16: =COUNTIFS('우리가 공급사 OMH Supply'!$E$5:$E$399,"유럽·미주 · Europe & Americas",'우리가 공급사 OMH Supply'!$B$5:$B$399,"<>Live",'우리가 공급사 OMH Supply'!$D$5:$D$399,"") -> 0 | T16: =COUNTIFS('상호연동 Two-way'!$E$5:$E$400,"유럽·미주 · Europe & Americas",'상호연동 Two-way'!$B$5:$B$400,"<>Live",'상호연동 Two-way'!$D$5:$D$400,"") -> 3 | U16: =SUM(P16:T16) -> 9
O17: 글로벌 · Global | P17: =COUNTIFS('스위칭 업체 Switch vendors'!$E$5:$E$400,"글로벌 · Global",'스위칭 업체 Switch vendors'!$B$5:$B$400,"<>Live",'스위칭 업체 Switch vendors'!$D$5:$D$400,"") -> 0 | Q17: =COUNTIFS('스위칭 연동 Switching'!$E$5:$E$400,"글로벌 · Global",'스위칭 연동 Switching'!$B$5:$B$400,"<>Live",'스위칭 연동 Switching'!$D$5:$D$400,"") -> 0 | R17: =COUNTIFS('서드파티 연동 3rd Party'!$E$5:$E$399,"글로벌 · Global",'서드파티 연동 3rd Party'!$B$5:$B$399,"<>Live",'서드파티 연동 3rd Party'!$D$5:$D$399,"") -> 0 | S17: =COUNTIFS('우리가 공급사 OMH Supply'!$E$5:$E$399,"글로벌 · Global",'우리가 공급사 OMH Supply'!$B$5:$B$399,"<>Live",'우리가 공급사 OMH Supply'!$D$5:$D$399,"") -> 1 | T17: =COUNTIFS('상호연동 Two-way'!$E$5:$E$400,"글로벌 · Global",'상호연동 Two-way'!$B$5:$B$400,"<>Live",'상호연동 Two-way'!$D$5:$D$400,"") -> 0 | U17: =SUM(P17:T17) -> 1
O18: 합계 · Total | P18: =SUM(P10:P17) -> 3 | Q18: =SUM(Q10:Q17) -> 16 | R18: =SUM(R10:R17) -> 4 | S18: =SUM(S10:S17) -> 62 | T18: =SUM(T10:T17) -> 16 | U18: =SUM(U10:U17) -> 101
O20: 담당별 진행 중 건수 · Open items by owner
O21: 담당 · Owner | P21: 스위칭 업체 Switch vendors | Q21: 스위칭 연동 Switching | R21: 서드파티 연동 3rd Party | S21: 우리가 공급사 OMH Supply | T21: 상호연동 Two-way | U21: 합계 Total | V21: 60일+ 정체 Stalled 60d+ | W21: 체이스 지연·필요 Chase overdue/needed
O22: Grace | P22: =COUNTIFS('스위칭 업체 Switch vendors'!$P$5:$P$400,$O22,'스위칭 업체 Switch vendors'!$B$5:$B$400,"<>Live",'스위칭 업체 Switch vendors'!$D$5:$D$400,"") -> 0 | Q22: =COUNTIFS('스위칭 연동 Switching'!$M$5:$M$400,$O22,'스위칭 연동 Switching'!$B$5:$B$400,"<>Live",'스위칭 연동 Switching'!$D$5:$D$400,"") -> 1 | R22: =COUNTIFS('서드파티 연동 3rd Party'!$M$5:$M$399,$O22,'서드파티 연동 3rd Party'!$B$5:$B$399,"<>Live",'서드파티 연동 3rd Party'!$D$5:$D$399,"") -> 0 | S22: =COUNTIFS('우리가 공급사 OMH Supply'!$M$5:$M$399,$O22,'우리가 공급사 OMH Supply'!$B$5:$B$399,"<>Live",'우리가 공급사 OMH Supply'!$D$5:$D$399,"") -> 22 | T22: =COUNTIFS('상호연동 Two-way'!$P$5:$P$400,$O22,'상호연동 Two-way'!$B$5:$B$400,"<>Live",'상호연동 Two-way'!$D$5:$D$400,"") -> 1 | U22: =SUM(P22:T22) -> 24 | V22: =COUNTIFS('스위칭 업체 Switch vendors'!$P$5:$P$400,$O22,'스위칭 업체 Switch vendors'!$V$5:$V$400,"Stalled 60d+")+COUNTIFS('스위칭 업체 Switch vendors'!$P$5:$P$400,$O22,'스위칭 업체 Switch vendors'!$V$5:$V$400,"Stalled 90d+")+COUNTIFS('스위칭 연동 Switching'!$M$5:$M$400,$O22,'스위칭 연동 Switching'!$S$5:$S$400,"Stalled 60d+")+COUNTIFS('스위칭 연동 Switching'!$M$5:$M$400,$O22,'스위칭 연동 Switching'!$S$5:$S$400,"Stalled 90d+")+COUNTIFS('서드파티 연동 3rd Party'!$M$5:$M$399,$O22,'서드파티 연동 3rd Party'!$S$5:$S$399,"Stalled 60d+")+COUNTIFS('서드파티 연동 3rd Party'!$M$5:$M$399,$O22,'서드파티 연동 3rd Party'!$S$5:$S$399,"Stalled 90d+")+COUNTIFS('우리가 공급사 OMH Supply'!$M$5:$M$399,$O22,'우리가 공급사 OMH Supply'!$S$5:$S$399,"Stalled 60d+")+COUNTIFS('우리가 공급사 OMH Supply'!$M$5:$M$399,$O22,'우리가 공급사 OMH Supply'!$S$5:$S$399,"Stalled 90d+")+COUNTIFS('상호연동 Two-way'!$P$5:$P$400,$O22,'상호연동 Two-way'!$V$5:$V$400,"Stalled 60d+")+COUNTIFS('상호연동 Two-way'!$P$5:$P$400,$O22,'상호연동 Two-way'!$V$5:$V$400,"Stalled 90d+") -> 7 | W22: =COUNTIFS('스위칭 업체 Switch vendors'!$P$5:$P$400,$O22,'스위칭 업체 Switch vendors'!$AC$5:$AC$400,"Chase Overdue")+COUNTIFS('스위칭 업체 Switch vendors'!$P$5:$P$400,$O22,'스위칭 업체 Switch vendors'!$AC$5:$AC$400,"Chase Needed")+COUNTIFS('스위칭 연동 Switching'!$M$5:$M$400,$O22,'스위칭 연동 Switching'!$Z$5:$Z$400,"Chase Overdue")+COUNTIFS('스위칭 연동 Switching'!$M$5:$M$400,$O22,'스위칭 연동 Switching'!$Z$5:$Z$400,"Chase Needed")+COUNTIFS('서드파티 연동 3rd Party'!$M$5:$M$399,$O22,'서드파티 연동 3rd Party'!$Z$5:$Z$399,"Chase Overdue")+COUNTIFS('서드파티 연동 3rd Party'!$M$5:$M$399,$O22,'서드파티 연동 3rd Party'!$Z$5:$Z$399,"Chase Needed")+COUNTIFS('우리가 공급사 OMH Supply'!$M$5:$M$399,$O22,'우리가 공급사 OMH Supply'!$Z$5:$Z$399,"Chase Overdue")+COUNTIFS('우리가 공급사 OMH Supply'!$M$5:$M$399,$O22,'우리가 공급사 OMH Supply'!$Z$5:$Z$399,"Chase Needed")+COUNTIFS('상호연동 Two-way'!$P$5:$P$400,$O22,'상호연동 Two-way'!$AC$5:$AC$400,"Chase Overdue")+COUNTIFS('상호연동 Two-way'!$P$5:$P$400,$O22,'상호연동 Two-way'!$AC$5:$AC$400,"Chase Needed") -> 11
O23: Aiden (지역 공백 · interim) | P23: =COUNTIFS('스위칭 업체 Switch vendors'!$P$5:$P$400,$O23,'스위칭 업체 Switch vendors'!$B$5:$B$400,"<>Live",'스위칭 업체 Switch vendors'!$D$5:$D$400,"") -> 0 | Q23: =COUNTIFS('스위칭 연동 Switching'!$M$5:$M$400,$O23,'스위칭 연동 Switching'!$B$5:$B$400,"<>Live",'스위칭 연동 Switching'!$D$5:$D$400,"") -> 4 | R23: =COUNTIFS('서드파티 연동 3rd Party'!$M$5:$M$399,$O23,'서드파티 연동 3rd Party'!$B$5:$B$399,"<>Live",'서드파티 연동 3rd Party'!$D$5:$D$399,"") -> 0 | S23: =COUNTIFS('우리가 공급사 OMH Supply'!$M$5:$M$399,$O23,'우리가 공급사 OMH Supply'!$B$5:$B$399,"<>Live",'우리가 공급사 OMH Supply'!$D$5:$D$399,"") -> 30 | T23: =COUNTIFS('상호연동 Two-way'!$P$5:$P$400,$O23,'상호연동 Two-way'!$B$5:$B$400,"<>Live",'상호연동 Two-way'!$D$5:$D$400,"") -> 7 | U23: =SUM(P23:T23) -> 41 | V23: =COUNTIFS('스위칭 업체 Switch vendors'!$P$5:$P$400,$O23,'스위칭 업체 Switch vendors'!$V$5:$V$400,"Stalled 60d+")+COUNTIFS('스위칭 업체 Switch vendors'!$P$5:$P$400,$O23,'스위칭 업체 Switch vendors'!$V$5:$V$400,"Stalled 90d+")+COUNTIFS('스위칭 연동 Switching'!$M$5:$M$400,$O23,'스위칭 연동 Switching'!$S$5:$S$400,"Stalled 60d+")+COUNTIFS('스위칭 연동 Switching'!$M$5:$M$400,$O23,'스위칭 연동 Switching'!$S$5:$S$400,"Stalled 90d+")+COUNTIFS('서드파티 연동 3rd Party'!$M$5:$M$399,$O23,'서드파티 연동 3rd Party'!$S$5:$S$399,"Stalled 60d+")+COUNTIFS('서드파티 연동 3rd Party'!$M$5:$M$399,$O23,'서드파티 연동 3rd Party'!$S$5:$S$399,"Stalled 90d+")+COUNTIFS('우리가 공급사 OMH Supply'!$M$5:$M$399,$O23,'우리가 공급사 OMH Supply'!$S$5:$S$399,"Stalled 60d+")+COUNTIFS('우리가 공급사 OMH Supply'!$M$5:$M$399,$O23,'우리가 공급사 OMH Supply'!$S$5:$S$399,"Stalled 90d+")+COUNTIFS('상호연동 Two-way'!$P$5:$P$400,$O23,'상호연동 Two-way'!$V$5:$V$400,"Stalled 60d+")+COUNTIFS('상호연동 Two-way'!$P$5:$P$400,$O23,'상호연동 Two-way'!$V$5:$V$400,"Stalled 90d+") -> 5 | W23: =COUNTIFS('스위칭 업체 Switch vendors'!$P$5:$P$400,$O23,'스위칭 업체 Switch vendors'!$AC$5:$AC$400,"Chase Overdue")+COUNTIFS('스위칭 업체 Switch vendors'!$P$5:$P$400,$O23,'스위칭 업체 Switch vendors'!$AC$5:$AC$400,"Chase Needed")+COUNTIFS('스위칭 연동 Switching'!$M$5:$M$400,$O23,'스위칭 연동 Switching'!$Z$5:$Z$400,"Chase Overdue")+COUNTIFS('스위칭 연동 Switching'!$M$5:$M$400,$O23,'스위칭 연동 Switching'!$Z$5:$Z$400,"Chase Needed")+COUNTIFS('서드파티 연동 3rd Party'!$M$5:$M$399,$O23,'서드파티 연동 3rd Party'!$Z$5:$Z$399,"Chase Overdue")+COUNTIFS('서드파티 연동 3rd Party'!$M$5:$M$399,$O23,'서드파티 연동 3rd Party'!$Z$5:$Z$399,"Chase Needed")+COUNTIFS('우리가 공급사 OMH Supply'!$M$5:$M$399,$O23,'우리가 공급사 OMH Supply'!$Z$5:$Z$399,"Chase Overdue")+COUNTIFS('우리가 공급사 OMH Supply'!$M$5:$M$399,$O23,'우리가 공급사 OMH Supply'!$Z$5:$Z$399,"Chase Needed")+COUNTIFS('상호연동 Two-way'!$P$5:$P$400,$O23,'상호연동 Two-way'!$AC$5:$AC$400,"Chase Overdue")+COUNTIFS('상호연동 Two-way'!$P$5:$P$400,$O23,'상호연동 Two-way'!$AC$5:$AC$400,"Chase Needed") -> 23
O24: GSM: Aiden → Jane (Dec~) | P24: =COUNTIFS('스위칭 업체 Switch vendors'!$P$5:$P$400,$O24,'스위칭 업체 Switch vendors'!$B$5:$B$400,"<>Live",'스위칭 업체 Switch vendors'!$D$5:$D$400,"") -> 3 | Q24: =COUNTIFS('스위칭 연동 Switching'!$M$5:$M$400,$O24,'스위칭 연동 Switching'!$B$5:$B$400,"<>Live",'스위칭 연동 Switching'!$D$5:$D$400,"") -> 10 | R24: =COUNTIFS('서드파티 연동 3rd Party'!$M$5:$M$399,$O24,'서드파티 연동 3rd Party'!$B$5:$B$399,"<>Live",'서드파티 연동 3rd Party'!$D$5:$D$399,"") -> 0 | S24: =COUNTIFS('우리가 공급사 OMH Supply'!$M$5:$M$399,$O24,'우리가 공급사 OMH Supply'!$B$5:$B$399,"<>Live",'우리가 공급사 OMH Supply'!$D$5:$D$399,"") -> 0 | T24: =COUNTIFS('상호연동 Two-way'!$P$5:$P$400,$O24,'상호연동 Two-way'!$B$5:$B$400,"<>Live",'상호연동 Two-way'!$D$5:$D$400,"") -> 8 | U24: =SUM(P24:T24) -> 21 | V24: =COUNTIFS('스위칭 업체 Switch vendors'!$P$5:$P$400,$O24,'스위칭 업체 Switch vendors'!$V$5:$V$400,"Stalled 60d+")+COUNTIFS('스위칭 업체 Switch vendors'!$P$5:$P$400,$O24,'스위칭 업체 Switch vendors'!$V$5:$V$400,"Stalled 90d+")+COUNTIFS('스위칭 연동 Switching'!$M$5:$M$400,$O24,'스위칭 연동 Switching'!$S$5:$S$400,"Stalled 60d+")+COUNTIFS('스위칭 연동 Switching'!$M$5:$M$400,$O24,'스위칭 연동 Switching'!$S$5:$S$400,"Stalled 90d+")+COUNTIFS('서드파티 연동 3rd Party'!$M$5:$M$399,$O24,'서드파티 연동 3rd Party'!$S$5:$S$399,"Stalled 60d+")+COUNTIFS('서드파티 연동 3rd Party'!$M$5:$M$399,$O24,'서드파티 연동 3rd Party'!$S$5:$S$399,"Stalled 90d+")+COUNTIFS('우리가 공급사 OMH Supply'!$M$5:$M$399,$O24,'우리가 공급사 OMH Supply'!$S$5:$S$399,"Stalled 60d+")+COUNTIFS('우리가 공급사 OMH Supply'!$M$5:$M$399,$O24,'우리가 공급사 OMH Supply'!$S$5:$S$399,"Stalled 90d+")+COUNTIFS('상호연동 Two-way'!$P$5:$P$400,$O24,'상호연동 Two-way'!$V$5:$V$400,"Stalled 60d+")+COUNTIFS('상호연동 Two-way'!$P$5:$P$400,$O24,'상호연동 Two-way'!$V$5:$V$400,"Stalled 90d+") -> 1 | W24: =COUNTIFS('스위칭 업체 Switch vendors'!$P$5:$P$400,$O24,'스위칭 업체 Switch vendors'!$AC$5:$AC$400,"Chase Overdue")+COUNTIFS('스위칭 업체 Switch vendors'!$P$5:$P$400,$O24,'스위칭 업체 Switch vendors'!$AC$5:$AC$400,"Chase Needed")+COUNTIFS('스위칭 연동 Switching'!$M$5:$M$400,$O24,'스위칭 연동 Switching'!$Z$5:$Z$400,"Chase Overdue")+COUNTIFS('스위칭 연동 Switching'!$M$5:$M$400,$O24,'스위칭 연동 Switching'!$Z$5:$Z$400,"Chase Needed")+COUNTIFS('서드파티 연동 3rd Party'!$M$5:$M$399,$O24,'서드파티 연동 3rd Party'!$Z$5:$Z$399,"Chase Overdue")+COUNTIFS('서드파티 연동 3rd Party'!$M$5:$M$399,$O24,'서드파티 연동 3rd Party'!$Z$5:$Z$399,"Chase Needed")+COUNTIFS('우리가 공급사 OMH Supply'!$M$5:$M$399,$O24,'우리가 공급사 OMH Supply'!$Z$5:$Z$399,"Chase Overdue")+COUNTIFS('우리가 공급사 OMH Supply'!$M$5:$M$399,$O24,'우리가 공급사 OMH Supply'!$Z$5:$Z$399,"Chase Needed")+COUNTIFS('상호연동 Two-way'!$P$5:$P$400,$O24,'상호연동 Two-way'!$AC$5:$AC$400,"Chase Overdue")+COUNTIFS('상호연동 Two-way'!$P$5:$P$400,$O24,'상호연동 Two-way'!$AC$5:$AC$400,"Chase Needed") -> 9
O25: Jane | P25: =COUNTIFS('스위칭 업체 Switch vendors'!$P$5:$P$400,$O25,'스위칭 업체 Switch vendors'!$B$5:$B$400,"<>Live",'스위칭 업체 Switch vendors'!$D$5:$D$400,"") -> 0 | Q25: =COUNTIFS('스위칭 연동 Switching'!$M$5:$M$400,$O25,'스위칭 연동 Switching'!$B$5:$B$400,"<>Live",'스위칭 연동 Switching'!$D$5:$D$400,"") -> 0 | R25: =COUNTIFS('서드파티 연동 3rd Party'!$M$5:$M$399,$O25,'서드파티 연동 3rd Party'!$B$5:$B$399,"<>Live",'서드파티 연동 3rd Party'!$D$5:$D$399,"") -> 0 | S25: =COUNTIFS('우리가 공급사 OMH Supply'!$M$5:$M$399,$O25,'우리가 공급사 OMH Supply'!$B$5:$B$399,"<>Live",'우리가 공급사 OMH Supply'!$D$5:$D$399,"") -> 8 | T25: =COUNTIFS('상호연동 Two-way'!$P$5:$P$400,$O25,'상호연동 Two-way'!$B$5:$B$400,"<>Live",'상호연동 Two-way'!$D$5:$D$400,"") -> 0 | U25: =SUM(P25:T25) -> 8 | V25: =COUNTIFS('스위칭 업체 Switch vendors'!$P$5:$P$400,$O25,'스위칭 업체 Switch vendors'!$V$5:$V$400,"Stalled 60d+")+COUNTIFS('스위칭 업체 Switch vendors'!$P$5:$P$400,$O25,'스위칭 업체 Switch vendors'!$V$5:$V$400,"Stalled 90d+")+COUNTIFS('스위칭 연동 Switching'!$M$5:$M$400,$O25,'스위칭 연동 Switching'!$S$5:$S$400,"Stalled 60d+")+COUNTIFS('스위칭 연동 Switching'!$M$5:$M$400,$O25,'스위칭 연동 Switching'!$S$5:$S$400,"Stalled 90d+")+COUNTIFS('서드파티 연동 3rd Party'!$M$5:$M$399,$O25,'서드파티 연동 3rd Party'!$S$5:$S$399,"Stalled 60d+")+COUNTIFS('서드파티 연동 3rd Party'!$M$5:$M$399,$O25,'서드파티 연동 3rd Party'!$S$5:$S$399,"Stalled 90d+")+COUNTIFS('우리가 공급사 OMH Supply'!$M$5:$M$399,$O25,'우리가 공급사 OMH Supply'!$S$5:$S$399,"Stalled 60d+")+COUNTIFS('우리가 공급사 OMH Supply'!$M$5:$M$399,$O25,'우리가 공급사 OMH Supply'!$S$5:$S$399,"Stalled 90d+")+COUNTIFS('상호연동 Two-way'!$P$5:$P$400,$O25,'상호연동 Two-way'!$V$5:$V$400,"Stalled 60d+")+COUNTIFS('상호연동 Two-way'!$P$5:$P$400,$O25,'상호연동 Two-way'!$V$5:$V$400,"Stalled 90d+") -> 1 | W25: =COUNTIFS('스위칭 업체 Switch vendors'!$P$5:$P$400,$O25,'스위칭 업체 Switch vendors'!$AC$5:$AC$400,"Chase Overdue")+COUNTIFS('스위칭 업체 Switch vendors'!$P$5:$P$400,$O25,'스위칭 업체 Switch vendors'!$AC$5:$AC$400,"Chase Needed")+COUNTIFS('스위칭 연동 Switching'!$M$5:$M$400,$O25,'스위칭 연동 Switching'!$Z$5:$Z$400,"Chase Overdue")+COUNTIFS('스위칭 연동 Switching'!$M$5:$M$400,$O25,'스위칭 연동 Switching'!$Z$5:$Z$400,"Chase Needed")+COUNTIFS('서드파티 연동 3rd Party'!$M$5:$M$399,$O25,'서드파티 연동 3rd Party'!$Z$5:$Z$399,"Chase Overdue")+COUNTIFS('서드파티 연동 3rd Party'!$M$5:$M$399,$O25,'서드파티 연동 3rd Party'!$Z$5:$Z$399,"Chase Needed")+COUNTIFS('우리가 공급사 OMH Supply'!$M$5:$M$399,$O25,'우리가 공급사 OMH Supply'!$Z$5:$Z$399,"Chase Overdue")+COUNTIFS('우리가 공급사 OMH Supply'!$M$5:$M$399,$O25,'우리가 공급사 OMH Supply'!$Z$5:$Z$399,"Chase Needed")+COUNTIFS('상호연동 Two-way'!$P$5:$P$400,$O25,'상호연동 Two-way'!$AC$5:$AC$400,"Chase Overdue")+COUNTIFS('상호연동 Two-way'!$P$5:$P$400,$O25,'상호연동 Two-way'!$AC$5:$AC$400,"Chase Needed") -> 2
O26: Aiden (일본 · interim JP) | P26: =COUNTIFS('스위칭 업체 Switch vendors'!$P$5:$P$400,$O26,'스위칭 업체 Switch vendors'!$B$5:$B$400,"<>Live",'스위칭 업체 Switch vendors'!$D$5:$D$400,"") -> 0 | Q26: =COUNTIFS('스위칭 연동 Switching'!$M$5:$M$400,$O26,'스위칭 연동 Switching'!$B$5:$B$400,"<>Live",'스위칭 연동 Switching'!$D$5:$D$400,"") -> 1 | R26: =COUNTIFS('서드파티 연동 3rd Party'!$M$5:$M$399,$O26,'서드파티 연동 3rd Party'!$B$5:$B$399,"<>Live",'서드파티 연동 3rd Party'!$D$5:$D$399,"") -> 0 | S26: =COUNTIFS('우리가 공급사 OMH Supply'!$M$5:$M$399,$O26,'우리가 공급사 OMH Supply'!$B$5:$B$399,"<>Live",'우리가 공급사 OMH Supply'!$D$5:$D$399,"") -> 2 | T26: =COUNTIFS('상호연동 Two-way'!$P$5:$P$400,$O26,'상호연동 Two-way'!$B$5:$B$400,"<>Live",'상호연동 Two-way'!$D$5:$D$400,"") -> 0 | U26: =SUM(P26:T26) -> 3 | V26: =COUNTIFS('스위칭 업체 Switch vendors'!$P$5:$P$400,$O26,'스위칭 업체 Switch vendors'!$V$5:$V$400,"Stalled 60d+")+COUNTIFS('스위칭 업체 Switch vendors'!$P$5:$P$400,$O26,'스위칭 업체 Switch vendors'!$V$5:$V$400,"Stalled 90d+")+COUNTIFS('스위칭 연동 Switching'!$M$5:$M$400,$O26,'스위칭 연동 Switching'!$S$5:$S$400,"Stalled 60d+")+COUNTIFS('스위칭 연동 Switching'!$M$5:$M$400,$O26,'스위칭 연동 Switching'!$S$5:$S$400,"Stalled 90d+")+COUNTIFS('서드파티 연동 3rd Party'!$M$5:$M$399,$O26,'서드파티 연동 3rd Party'!$S$5:$S$399,"Stalled 60d+")+COUNTIFS('서드파티 연동 3rd Party'!$M$5:$M$399,$O26,'서드파티 연동 3rd Party'!$S$5:$S$399,"Stalled 90d+")+COUNTIFS('우리가 공급사 OMH Supply'!$M$5:$M$399,$O26,'우리가 공급사 OMH Supply'!$S$5:$S$399,"Stalled 60d+")+COUNTIFS('우리가 공급사 OMH Supply'!$M$5:$M$399,$O26,'우리가 공급사 OMH Supply'!$S$5:$S$399,"Stalled 90d+")+COUNTIFS('상호연동 Two-way'!$P$5:$P$400,$O26,'상호연동 Two-way'!$V$5:$V$400,"Stalled 60d+")+COUNTIFS('상호연동 Two-way'!$P$5:$P$400,$O26,'상호연동 Two-way'!$V$5:$V$400,"Stalled 90d+") -> 0 | W26: =COUNTIFS('스위칭 업체 Switch vendors'!$P$5:$P$400,$O26,'스위칭 업체 Switch vendors'!$AC$5:$AC$400,"Chase Overdue")+COUNTIFS('스위칭 업체 Switch vendors'!$P$5:$P$400,$O26,'스위칭 업체 Switch vendors'!$AC$5:$AC$400,"Chase Needed")+COUNTIFS('스위칭 연동 Switching'!$M$5:$M$400,$O26,'스위칭 연동 Switching'!$Z$5:$Z$400,"Chase Overdue")+COUNTIFS('스위칭 연동 Switching'!$M$5:$M$400,$O26,'스위칭 연동 Switching'!$Z$5:$Z$400,"Chase Needed")+COUNTIFS('서드파티 연동 3rd Party'!$M$5:$M$399,$O26,'서드파티 연동 3rd Party'!$Z$5:$Z$399,"Chase Overdue")+COUNTIFS('서드파티 연동 3rd Party'!$M$5:$M$399,$O26,'서드파티 연동 3rd Party'!$Z$5:$Z$399,"Chase Needed")+COUNTIFS('우리가 공급사 OMH Supply'!$M$5:$M$399,$O26,'우리가 공급사 OMH Supply'!$Z$5:$Z$399,"Chase Overdue")+COUNTIFS('우리가 공급사 OMH Supply'!$M$5:$M$399,$O26,'우리가 공급사 OMH Supply'!$Z$5:$Z$399,"Chase Needed")+COUNTIFS('상호연동 Two-way'!$P$5:$P$400,$O26,'상호연동 Two-way'!$AC$5:$AC$400,"Chase Overdue")+COUNTIFS('상호연동 Two-way'!$P$5:$P$400,$O26,'상호연동 Two-way'!$AC$5:$AC$400,"Chase Needed") -> 0
O27: SCM by country · Aiden | P27: =COUNTIFS('스위칭 업체 Switch vendors'!$P$5:$P$400,$O27,'스위칭 업체 Switch vendors'!$B$5:$B$400,"<>Live",'스위칭 업체 Switch vendors'!$D$5:$D$400,"") -> 0 | Q27: =COUNTIFS('스위칭 연동 Switching'!$M$5:$M$400,$O27,'스위칭 연동 Switching'!$B$5:$B$400,"<>Live",'스위칭 연동 Switching'!$D$5:$D$400,"") -> 0 | R27: =COUNTIFS('서드파티 연동 3rd Party'!$M$5:$M$399,$O27,'서드파티 연동 3rd Party'!$B$5:$B$399,"<>Live",'서드파티 연동 3rd Party'!$D$5:$D$399,"") -> 0 | S27: =COUNTIFS('우리가 공급사 OMH Supply'!$M$5:$M$399,$O27,'우리가 공급사 OMH Supply'!$B$5:$B$399,"<>Live",'우리가 공급사 OMH Supply'!$D$5:$D$399,"") -> 0 | T27: =COUNTIFS('상호연동 Two-way'!$P$5:$P$400,$O27,'상호연동 Two-way'!$B$5:$B$400,"<>Live",'상호연동 Two-way'!$D$5:$D$400,"") -> 0 | U27: =SUM(P27:T27) -> 0 | V27: =COUNTIFS('스위칭 업체 Switch vendors'!$P$5:$P$400,$O27,'스위칭 업체 Switch vendors'!$V$5:$V$400,"Stalled 60d+")+COUNTIFS('스위칭 업체 Switch vendors'!$P$5:$P$400,$O27,'스위칭 업체 Switch vendors'!$V$5:$V$400,"Stalled 90d+")+COUNTIFS('스위칭 연동 Switching'!$M$5:$M$400,$O27,'스위칭 연동 Switching'!$S$5:$S$400,"Stalled 60d+")+COUNTIFS('스위칭 연동 Switching'!$M$5:$M$400,$O27,'스위칭 연동 Switching'!$S$5:$S$400,"Stalled 90d+")+COUNTIFS('서드파티 연동 3rd Party'!$M$5:$M$399,$O27,'서드파티 연동 3rd Party'!$S$5:$S$399,"Stalled 60d+")+COUNTIFS('서드파티 연동 3rd Party'!$M$5:$M$399,$O27,'서드파티 연동 3rd Party'!$S$5:$S$399,"Stalled 90d+")+COUNTIFS('우리가 공급사 OMH Supply'!$M$5:$M$399,$O27,'우리가 공급사 OMH Supply'!$S$5:$S$399,"Stalled 60d+")+COUNTIFS('우리가 공급사 OMH Supply'!$M$5:$M$399,$O27,'우리가 공급사 OMH Supply'!$S$5:$S$399,"Stalled 90d+")+COUNTIFS('상호연동 Two-way'!$P$5:$P$400,$O27,'상호연동 Two-way'!$V$5:$V$400,"Stalled 60d+")+COUNTIFS('상호연동 Two-way'!$P$5:$P$400,$O27,'상호연동 Two-way'!$V$5:$V$400,"Stalled 90d+") -> 0 | W27: =COUNTIFS('스위칭 업체 Switch vendors'!$P$5:$P$400,$O27,'스위칭 업체 Switch vendors'!$AC$5:$AC$400,"Chase Overdue")+COUNTIFS('스위칭 업체 Switch vendors'!$P$5:$P$400,$O27,'스위칭 업체 Switch vendors'!$AC$5:$AC$400,"Chase Needed")+COUNTIFS('스위칭 연동 Switching'!$M$5:$M$400,$O27,'스위칭 연동 Switching'!$Z$5:$Z$400,"Chase Overdue")+COUNTIFS('스위칭 연동 Switching'!$M$5:$M$400,$O27,'스위칭 연동 Switching'!$Z$5:$Z$400,"Chase Needed")+COUNTIFS('서드파티 연동 3rd Party'!$M$5:$M$399,$O27,'서드파티 연동 3rd Party'!$Z$5:$Z$399,"Chase Overdue")+COUNTIFS('서드파티 연동 3rd Party'!$M$5:$M$399,$O27,'서드파티 연동 3rd Party'!$Z$5:$Z$399,"Chase Needed")+COUNTIFS('우리가 공급사 OMH Supply'!$M$5:$M$399,$O27,'우리가 공급사 OMH Supply'!$Z$5:$Z$399,"Chase Overdue")+COUNTIFS('우리가 공급사 OMH Supply'!$M$5:$M$399,$O27,'우리가 공급사 OMH Supply'!$Z$5:$Z$399,"Chase Needed")+COUNTIFS('상호연동 Two-way'!$P$5:$P$400,$O27,'상호연동 Two-way'!$AC$5:$AC$400,"Chase Overdue")+COUNTIFS('상호연동 Two-way'!$P$5:$P$400,$O27,'상호연동 Two-way'!$AC$5:$AC$400,"Chase Needed") -> 0
O28: Aiden | P28: =COUNTIFS('스위칭 업체 Switch vendors'!$P$5:$P$400,$O28,'스위칭 업체 Switch vendors'!$B$5:$B$400,"<>Live",'스위칭 업체 Switch vendors'!$D$5:$D$400,"") -> 0 | Q28: =COUNTIFS('스위칭 연동 Switching'!$M$5:$M$400,$O28,'스위칭 연동 Switching'!$B$5:$B$400,"<>Live",'스위칭 연동 Switching'!$D$5:$D$400,"") -> 0 | R28: =COUNTIFS('서드파티 연동 3rd Party'!$M$5:$M$399,$O28,'서드파티 연동 3rd Party'!$B$5:$B$399,"<>Live",'서드파티 연동 3rd Party'!$D$5:$D$399,"") -> 0 | S28: =COUNTIFS('우리가 공급사 OMH Supply'!$M$5:$M$399,$O28,'우리가 공급사 OMH Supply'!$B$5:$B$399,"<>Live",'우리가 공급사 OMH Supply'!$D$5:$D$399,"") -> 0 | T28: =COUNTIFS('상호연동 Two-way'!$P$5:$P$400,$O28,'상호연동 Two-way'!$B$5:$B$400,"<>Live",'상호연동 Two-way'!$D$5:$D$400,"") -> 0 | U28: =SUM(P28:T28) -> 0 | V28: =COUNTIFS('스위칭 업체 Switch vendors'!$P$5:$P$400,$O28,'스위칭 업체 Switch vendors'!$V$5:$V$400,"Stalled 60d+")+COUNTIFS('스위칭 업체 Switch vendors'!$P$5:$P$400,$O28,'스위칭 업체 Switch vendors'!$V$5:$V$400,"Stalled 90d+")+COUNTIFS('스위칭 연동 Switching'!$M$5:$M$400,$O28,'스위칭 연동 Switching'!$S$5:$S$400,"Stalled 60d+")+COUNTIFS('스위칭 연동 Switching'!$M$5:$M$400,$O28,'스위칭 연동 Switching'!$S$5:$S$400,"Stalled 90d+")+COUNTIFS('서드파티 연동 3rd Party'!$M$5:$M$399,$O28,'서드파티 연동 3rd Party'!$S$5:$S$399,"Stalled 60d+")+COUNTIFS('서드파티 연동 3rd Party'!$M$5:$M$399,$O28,'서드파티 연동 3rd Party'!$S$5:$S$399,"Stalled 90d+")+COUNTIFS('우리가 공급사 OMH Supply'!$M$5:$M$399,$O28,'우리가 공급사 OMH Supply'!$S$5:$S$399,"Stalled 60d+")+COUNTIFS('우리가 공급사 OMH Supply'!$M$5:$M$399,$O28,'우리가 공급사 OMH Supply'!$S$5:$S$399,"Stalled 90d+")+COUNTIFS('상호연동 Two-way'!$P$5:$P$400,$O28,'상호연동 Two-way'!$V$5:$V$400,"Stalled 60d+")+COUNTIFS('상호연동 Two-way'!$P$5:$P$400,$O28,'상호연동 Two-way'!$V$5:$V$400,"Stalled 90d+") -> 0 | W28: =COUNTIFS('스위칭 업체 Switch vendors'!$P$5:$P$400,$O28,'스위칭 업체 Switch vendors'!$AC$5:$AC$400,"Chase Overdue")+COUNTIFS('스위칭 업체 Switch vendors'!$P$5:$P$400,$O28,'스위칭 업체 Switch vendors'!$AC$5:$AC$400,"Chase Needed")+COUNTIFS('스위칭 연동 Switching'!$M$5:$M$400,$O28,'스위칭 연동 Switching'!$Z$5:$Z$400,"Chase Overdue")+COUNTIFS('스위칭 연동 Switching'!$M$5:$M$400,$O28,'스위칭 연동 Switching'!$Z$5:$Z$400,"Chase Needed")+COUNTIFS('서드파티 연동 3rd Party'!$M$5:$M$399,$O28,'서드파티 연동 3rd Party'!$Z$5:$Z$399,"Chase Overdue")+COUNTIFS('서드파티 연동 3rd Party'!$M$5:$M$399,$O28,'서드파티 연동 3rd Party'!$Z$5:$Z$399,"Chase Needed")+COUNTIFS('우리가 공급사 OMH Supply'!$M$5:$M$399,$O28,'우리가 공급사 OMH Supply'!$Z$5:$Z$399,"Chase Overdue")+COUNTIFS('우리가 공급사 OMH Supply'!$M$5:$M$399,$O28,'우리가 공급사 OMH Supply'!$Z$5:$Z$399,"Chase Needed")+COUNTIFS('상호연동 Two-way'!$P$5:$P$400,$O28,'상호연동 Two-way'!$AC$5:$AC$400,"Chase Overdue")+COUNTIFS('상호연동 Two-way'!$P$5:$P$400,$O28,'상호연동 Two-way'!$AC$5:$AC$400,"Chase Needed") -> 0
B35: 지금 챙길 것 — 60일 이상 정체 (2026-10-19 스냅샷) · Watch list — stalled 60+ days (snapshot 19 Oct; use the 'Delay check' filter for live data)
B36: 카테고리 Category | C36: 프로젝트 Project | D36: 지역 Region | E36: 담당 Owner | F36: 진행률 Progress | G36: 경과일 Days | H36: 현황 · 다음 액션 Status · next action
B37: 우리가 공급사 OMH Supply | C37: Uone | D37: 중화권 · Greater China | E37: Grace | F37: 0.2 | G37: 406
B38: 스위칭 연동 Switching | C38: Lion Travel | D38: 중화권 · Greater China | E38: Grace | F38: 0.2 | G38: 402 | H38: Shiji 셀러 측 인터페이스 완료(10월 말~11월 초) 후 Shiji 경유 첫 채널 오픈 준비 — Shiji 폴더 TASKS #7(3자 미팅)과 연계 After Shiji seller-side interface is complete (late Oct–early Nov), prepare first channel launch via Shiji — link with Shiji folder TASKS #7 (three-party meeting)
B39: 우리가 공급사 OMH Supply | C39: Amerilink | D39: 중화권 · Greater China | E39: Grace | F39: 0.2 | G39: 357
B40: 우리가 공급사 OMH Supply | C40: Star Travel | D40: 중화권 · Greater China | E40: Grace | F40: 0.5 | G40: 321
B41: 상호연동 Two-way | C41: Chudu24 | D41: 동남아 · SE Asia | E41: GSM: Aiden → Jane (Dec~) | F41: 0.3 | G41: 313 | H41: API·2-way 제안 회신 체이스 + 탑셀링·피크 프로모션 공유 Chase reply on API/2-way proposal + share top-selling and peak promotions
B42: 우리가 공급사 OMH Supply | C42: Justgotrip | D42: 중화권 · Greater China | E42: Grace | F42: 0.2 | G42: 287
B43: 우리가 공급사 OMH Supply | C43: Gotadi - HN Branch | D43: 동남아 · SE Asia | E43: Aiden (지역 공백 · interim) | F43: 0.4 | G43: 102 | H43: 재가동 회신 2차 체이스 + OMH 측 개발 deliverable·ETA 확정 Second chase for re-engagement reply + confirm OMH-side development deliverables and ETA
B44: 상호연동 Two-way | C44: G2 Travel | D44: 유럽·미주 · Europe & Americas | E44: Aiden (지역 공백 · interim) | F44: 0.2 | G44: 101
B45: 상호연동 Two-way | C45: Tiket.com | D45: 동남아 · SE Asia | E45: Aiden (지역 공백 · interim) | F45: 0.2 | G45: 68 | H45: Celine 체이스 또는 Hold 결정 Chase Celine or decide to put on hold
B46: 상호연동 Two-way | C46: Tiket.com | D46: 동남아 · SE Asia | E46: Aiden (지역 공백 · interim) | F46: 0.2 | G46: 68 | H46: Celine 체이스 또는 Hold 결정 Chase Celine or decide to put on hold
B47: 우리가 공급사 OMH Supply | C47: Huamao | D47: 중화권 · Greater China | E47: Grace | F47: 0.5 | G47: 66 | H47: 개발 재개 확인 — 8/3 API 오류 해결 여부·인증 일정 Confirm development has resumed — whether the 3 Aug API error is resolved and certification schedule
B48: 우리가 공급사 OMH Supply | C48: Ziru (TMC) | D48: 중화권 · Greater China | E48: Grace | F48: 0.5 | G48: 66
B49: 우리가 공급사 OMH Supply | C49: Travelata(Vivatech) | D49: 중동·러시아 · ME & Russia | E49: Aiden (지역 공백 · interim) | F49: 0.5 | G49: 61 | H49: API 연동 진행(DEV·개발 일정·담당자·IP) 체이스 + 보증금 USD 20,000 입금 확인 Chase API integration progress (DEV, development schedule, contact person, IP) + confirm deposit of USD 20,000 received

Sheet 개발 간트 Dev Gantt
B1: 개발 진행 간트차트 · Dev Progress Gantt
B2: ="오늘 Today "&TEXT(TODAY(),"yyyy-mm-dd")&" · 주 단위 간트 · 날짜는 해당 주의 아무 날짜나 입력해도 그 주에 표시됩니다 · Weekly view – any date in the week works" -> 오늘 Today 2026-10-30 · 주 단위 간트 · 날짜는 해당 주의 아무 날짜나 입력해도 그 주에 표시됩니다 · Weekly view – any date in the week works
B4: 타임라인 시작일 Timeline start | E4: =EOMONTH(TODAY(),-2)+1 -> 46266 | F4: ← 이 날짜가 속한 주(월요일)부터 26주 표시 · Shows 26 weeks from this week | J4: 범례 Legend | M4: 개발중 | P4: 지연 | S4: 예정/완료 | V4: 라이브 주 | Y4: 이번 주
M5: In Dev | P5: Overdue | S5: Planned/Done | V5: Go-Live week | Y5: This week
B6: No. | C6: 업체명 Vendor | D6: 업체코드 Vendor Code | E6: 개발자 Developer | F6: 개발 시작일 Dev Start | G6: 완료 예정일 Dev End (plan) | H6: 라이브 일자 Go-Live | I6: 기간(주) Weeks | J6: 상태 Status | K6: =TEXT(K8,"yyyy-mm") -> 2026-08 | L6: =IF(MONTH(L8)<>MONTH(K8),TEXT(L8,"yyyy-mm"),"") -> 2026-09 | M6: =IF(MONTH(M8)<>MONTH(L8),TEXT(M8,"yyyy-mm"),"") | N6: =IF(MONTH(N8)<>MONTH(M8),TEXT(N8,"yyyy-mm"),"") | O6: =IF(MONTH(O8)<>MONTH(N8),TEXT(O8,"yyyy-mm"),"") | P6: =IF(MONTH(P8)<>MONTH(O8),TEXT(P8,"yyyy-mm"),"") -> 2026-10 | Q6: =IF(MONTH(Q8)<>MONTH(P8),TEXT(Q8,"yyyy-mm"),"") | R6: =IF(MONTH(R8)<>MONTH(Q8),TEXT(R8,"yyyy-mm"),"") | S6: =IF(MONTH(S8)<>MONTH(R8),TEXT(S8,"yyyy-mm"),"") | ... AJ6: =IF(MONTH(AJ8)<>MONTH(AI8),TEXT(AJ8,"yyyy-mm"),"")
K7: =INT((DAY(K8)-1)/7)+1&"주" -> 5주 | L7: =INT((DAY(L8)-1)/7)+1&"주" -> 1주 | M7: =INT((DAY(M8)-1)/7)+1&"주" -> 2주 | N7: =INT((DAY(N8)-1)/7)+1&"주" -> 3주 | O7: =INT((DAY(O8)-1)/7)+1&"주" -> 4주 | P7: =INT((DAY(P8)-1)/7)+1&"주" -> 1주 | Q7: =INT((DAY(Q8)-1)/7)+1&"주" -> 2주 | R7: =INT((DAY(R8)-1)/7)+1&"주" -> 3주 | ... AJ7: =INT((DAY(AJ8)-1)/7)+1&"주" -> 4주
K8: =$E$4-WEEKDAY($E$4,3) -> 46265 | L8: =K8+7 -> 46272 | M8: =L8+7 -> 46279 | N8: =M8+7 -> 46286 | O8: =N8+7 -> 46293 | P8: =O8+7 -> 46300 | Q8: =P8+7 -> 46307 | R8: =Q8+7 -> 46314 | S8: =R8+7 -> 46321 | ... AJ8: =AI8+7 -> 46440
B9: =IF(C9="","",ROW()-8) -> 1 | C9: test agency | E9: Aiden | F9: 46322 | G9: 46337 | H9: 46351 | I9: =IF(OR(F9="",G9=""),"",ROUNDUP((G9-F9+1)/7,0)) -> 3 | J9: =IF(C9="","",IF(AND(H9<>"",H9<=TODAY()),"라이브 Live",IF(F9="","미정 TBD",IF(TODAY()<F9,"예정 Planned",IF(AND(G9<>"",TODAY()>G9),"지연 Overdue","개발중 In Dev"))))) -> 개발중 In Dev
B10: =IF(C10="","",ROW()-8) -> 2 | C10: ABC Travel Service | E10: Tan | F10: 46357 | G10: 46386 | I10: =IF(OR(F10="",G10=""),"",ROUNDUP((G10-F10+1)/7,0)) -> 5 | J10: =IF(C10="","",IF(AND(H10<>"",H10<=TODAY()),"라이브 Live",IF(F10="","미정 TBD",IF(TODAY()<F10,"예정 Planned",IF(AND(G10<>"",TODAY()>G10),"지연 Overdue","개발중 In Dev"))))) -> 예정 Planned
B11: 3 | C11: STAYLAH | E11: Tan | F11: 46328 | G11: 46356 | I11: =IF(OR(F11="",G11=""),"",ROUNDUP((G11-F11+1)/7,0)) -> 5 | J11: =IF(C11="","",IF(AND(H11<>"",H11<=TODAY()),"라이브 Live",IF(F11="","미정 TBD",IF(TODAY()<F11,"예정 Planned",IF(AND(G11<>"",TODAY()>G11),"지연 Overdue","개발중 In Dev"))))) -> 예정 Planned
B12: 4 | C12: DiDi TMC | E12: Calvin | F12: 46371 | G12: 46402 | I12: =IF(OR(F12="",G12=""),"",ROUNDUP((G12-F12+1)/7,0)) -> 5 | J12: =IF(C12="","",IF(AND(H12<>"",H12<=TODAY()),"라이브 Live",IF(F12="","미정 TBD",IF(TODAY()<F12,"예정 Planned",IF(AND(G12<>"",TODAY()>G12),"지연 Overdue","개발중 In Dev"))))) -> 예정 Planned
B13: 5 | I13: =IF(OR(F13="",G13=""),"",ROUNDUP((G13-F13+1)/7,0)) | J13: =IF(C13="","",IF(AND(H13<>"",H13<=TODAY()),"라이브 Live",IF(F13="","미정 TBD",IF(TODAY()<F13,"예정 Planned",IF(AND(G13<>"",TODAY()>G13),"지연 Overdue","개발중 In Dev")))))
B14: 6 | I14: =IF(OR(F14="",G14=""),"",ROUNDUP((G14-F14+1)/7,0)) | J14: =IF(C14="","",IF(AND(H14<>"",H14<=TODAY()),"라이브 Live",IF(F14="","미정 TBD",IF(TODAY()<F14,"예정 Planned",IF(AND(G14<>"",TODAY()>G14),"지연 Overdue","개발중 In Dev")))))
B15: 7 | I15: =IF(OR(F15="",G15=""),"",ROUNDUP((G15-F15+1)/7,0)) | J15: =IF(C15="","",IF(AND(H15<>"",H15<=TODAY()),"라이브 Live",IF(F15="","미정 TBD",IF(TODAY()<F15,"예정 Planned",IF(AND(G15<>"",TODAY()>G15),"지연 Overdue","개발중 In Dev")))))
B16: 8 | I16: =IF(OR(F16="",G16=""),"",ROUNDUP((G16-F16+1)/7,0)) | J16: =IF(C16="","",IF(AND(H16<>"",H16<=TODAY()),"라이브 Live",IF(F16="","미정 TBD",IF(TODAY()<F16,"예정 Planned",IF(AND(G16<>"",TODAY()>G16),"지연 Overdue","개발중 In Dev")))))
B17: 9 | I17: =IF(OR(F17="",G17=""),"",ROUNDUP((G17-F17+1)/7,0)) | J17: =IF(C17="","",IF(AND(H17<>"",H17<=TODAY()),"라이브 Live",IF(F17="","미정 TBD",IF(TODAY()<F17,"예정 Planned",IF(AND(G17<>"",TODAY()>G17),"지연 Overdue","개발중 In Dev")))))
B18: 10 | I18: =IF(OR(F18="",G18=""),"",ROUNDUP((G18-F18+1)/7,0)) | J18: =IF(C18="","",IF(AND(H18<>"",H18<=TODAY()),"라이브 Live",IF(F18="","미정 TBD",IF(TODAY()<F18,"예정 Planned",IF(AND(G18<>"",TODAY()>G18),"지연 Overdue","개발중 In Dev")))))
B19: 11 | I19: =IF(OR(F19="",G19=""),"",ROUNDUP((G19-F19+1)/7,0)) | J19: =IF(C19="","",IF(AND(H19<>"",H19<=TODAY()),"라이브 Live",IF(F19="","미정 TBD",IF(TODAY()<F19,"예정 Planned",IF(AND(G19<>"",TODAY()>G19),"지연 Overdue","개발중 In Dev")))))
B20: =IF(C20="","",ROW()-8) | I20: =IF(OR(F20="",G20=""),"",ROUNDUP((G20-F20+1)/7,0)) | J20: =IF(C20="","",IF(AND(H20<>"",H20<=TODAY()),"라이브 Live",IF(F20="","미정 TBD",IF(TODAY()<F20,"예정 Planned",IF(AND(G20<>"",TODAY()>G20),"지연 Overdue","개발중 In Dev")))))
B21: =IF(C21="","",ROW()-8) | I21: =IF(OR(F21="",G21=""),"",ROUNDUP((G21-F21+1)/7,0)) | J21: =IF(C21="","",IF(AND(H21<>"",H21<=TODAY()),"라이브 Live",IF(F21="","미정 TBD",IF(TODAY()<F21,"예정 Planned",IF(AND(G21<>"",TODAY()>G21),"지연 Overdue","개발중 In Dev")))))
B22: =IF(C22="","",ROW()-8) | I22: =IF(OR(F22="",G22=""),"",ROUNDUP((G22-F22+1)/7,0)) | J22: =IF(C22="","",IF(AND(H22<>"",H22<=TODAY()),"라이브 Live",IF(F22="","미정 TBD",IF(TODAY()<F22,"예정 Planned",IF(AND(G22<>"",TODAY()>G22),"지연 Overdue","개발중 In Dev")))))
B23: =IF(C23="","",ROW()-8) | I23: =IF(OR(F23="",G23=""),"",ROUNDUP((G23-F23+1)/7,0)) | J23: =IF(C23="","",IF(AND(H23<>"",H23<=TODAY()),"라이브 Live",IF(F23="","미정 TBD",IF(TODAY()<F23,"예정 Planned",IF(AND(G23<>"",TODAY()>G23),"지연 Overdue","개발중 In Dev")))))
B24: =IF(C24="","",ROW()-8) | I24: =IF(OR(F24="",G24=""),"",ROUNDUP((G24-F24+1)/7,0)) | J24: =IF(C24="","",IF(AND(H24<>"",H24<=TODAY()),"라이브 Live",IF(F24="","미정 TBD",IF(TODAY()<F24,"예정 Planned",IF(AND(G24<>"",TODAY()>G24),"지연 Overdue","개발중 In Dev")))))
B25: =IF(C25="","",ROW()-8) | I25: =IF(OR(F25="",G25=""),"",ROUNDUP((G25-F25+1)/7,0)) | J25: =IF(C25="","",IF(AND(H25<>"",H25<=TODAY()),"라이브 Live",IF(F25="","미정 TBD",IF(TODAY()<F25,"예정 Planned",IF(AND(G25<>"",TODAY()>G25),"지연 Overdue","개발중 In Dev")))))
B26: =IF(C26="","",ROW()-8) | I26: =IF(OR(F26="",G26=""),"",ROUNDUP((G26-F26+1)/7,0)) | J26: =IF(C26="","",IF(AND(H26<>"",H26<=TODAY()),"라이브 Live",IF(F26="","미정 TBD",IF(TODAY()<F26,"예정 Planned",IF(AND(G26<>"",TODAY()>G26),"지연 Overdue","개발중 In Dev")))))
B27: =IF(C27="","",ROW()-8) | I27: =IF(OR(F27="",G27=""),"",ROUNDUP((G27-F27+1)/7,0)) | J27: =IF(C27="","",IF(AND(H27<>"",H27<=TODAY()),"라이브 Live",IF(F27="","미정 TBD",IF(TODAY()<F27,"예정 Planned",IF(AND(G27<>"",TODAY()>G27),"지연 Overdue","개발중 In Dev")))))
B28: =IF(C28="","",ROW()-8) | I28: =IF(OR(F28="",G28=""),"",ROUNDUP((G28-F28+1)/7,0)) | J28: =IF(C28="","",IF(AND(H28<>"",H28<=TODAY()),"라이브 Live",IF(F28="","미정 TBD",IF(TODAY()<F28,"예정 Planned",IF(AND(G28<>"",TODAY()>G28),"지연 Overdue","개발중 In Dev")))))
B29: =IF(C29="","",ROW()-8) | I29: =IF(OR(F29="",G29=""),"",ROUNDUP((G29-F29+1)/7,0)) | J29: =IF(C29="","",IF(AND(H29<>"",H29<=TODAY()),"라이브 Live",IF(F29="","미정 TBD",IF(TODAY()<F29,"예정 Planned",IF(AND(G29<>"",TODAY()>G29),"지연 Overdue","개발중 In Dev")))))
B30: =IF(C30="","",ROW()-8) | I30: =IF(OR(F30="",G30=""),"",ROUNDUP((G30-F30+1)/7,0)) | J30: =IF(C30="","",IF(AND(H30<>"",H30<=TODAY()),"라이브 Live",IF(F30="","미정 TBD",IF(TODAY()<F30,"예정 Planned",IF(AND(G30<>"",TODAY()>G30),"지연 Overdue","개발중 In Dev")))))
B31: =IF(C31="","",ROW()-8) | I31: =IF(OR(F31="",G31=""),"",ROUNDUP((G31-F31+1)/7,0)) | J31: =IF(C31="","",IF(AND(H31<>"",H31<=TODAY()),"라이브 Live",IF(F31="","미정 TBD",IF(TODAY()<F31,"예정 Planned",IF(AND(G31<>"",TODAY()>G31),"지연 Overdue","개발중 In Dev")))))
... B58: =IF(C58="","",ROW()-8) | I58: =IF(OR(F58="",G58=""),"",ROUNDUP((G58-F58+1)/7,0)) | J58: =IF(C58="","",IF(AND(H58<>"",H58<=TODAY()),"라이브 Live",IF(F58="","미정 TBD",IF(TODAY()<F58,"예정 Planned",IF(AND(G58<>"",TODAY()>G58),"지연 Overdue","개발중 In Dev")))))

Sheet 스위칭 업체 Switch vendors
A1: 스위칭 업체 Switch vendors | E1: 스위치 업체 자체와의 연동 (TGX·Shiji·Juniper·ZentrumHub 등) · 셀러(OMH 공급)·바이어(OMH 매입) 측 상태와 경유 파트너 수 · 오너 GSM (Aiden 인수 중, 12월~ Jane) Integration with the switch vendors themselves (TGX, Shiji, Juniper, ZentrumHub, etc.) · seller (OMH supply) and buyer (OMH sourcing) side status, partners routed via each switch · Owner: GSM (Aiden taking over, Jane lead from Dec)
A2: ="전체 Total "&COUNTA($G$5:$G$400)&" · 라이브 Live "&(COUNTIF($B$5:$B$400,"Live")+COUNTIF($B$5:$B$400,"Partially Live"))&" · 개발·테스트 Dev/Test "&(COUNTIF($B$5:$B$400,"In Development")+COUNTIF($B$5:$B$400,"Testing")+COUNTIF($B$5:$B$400,"Pending Live"))&" · 계약·NDA "&COUNTIF($B$5:$B$400,"NDA/Contract")&" · 파이프라인 Pipeline "&(COUNTIF($B$5:$B$400,"Pipeline")+COUNTIF($B$5:$B$400,"Contact"))&" · 60일+ 정체 Stalled 60d+ "&(COUNTIF($V$5:$V$400,"Stalled 60d+")+COUNTIF($V$5:$V$400,"Stalled 90d+")) -> 전체 Total 8 · 라이브 Live 0 · 개발·테스트 Dev/Test 2 · 계약·NDA 0 · 파이프라인 Pipeline 6 · 60일+ 정체 Stalled 60d+ 0 | AJ2: 단계 가중치 · Stage weight → | AK2: 0.05 | AL2: 0.1 | AM2: 0.15 | AN2: 0.2 | AO2: 0.3 | AP2: 0.4 | AQ2: 0.45 | AR2: 0.5 | AS2: 0.6 | AT2: 0.7 | AU2: 0.75 | AV2: 0.8 | AW2: 0.9 | AX2: 1
A3: 프로젝트 · 개발 정보 · Project / Dev Info | S3: 진행 · 체이스 현황 (자동 계산) · Progress & Chase Status (Auto-calculated) | AD3: 계획 · 이슈 (직접 입력) · Plan & Issues (manual entry) | AK3: 단계 이력 (실제 날짜) · Stage History (actual dates) — Pipeline → Contract → Dev → Customer Live
A4: No. | B4: 상태 Status | C4: 상태 수동 지정 Status override | D4: 보류/드롭 Hold/Drop | E4: 지역 Region | F4: 국가 Country | G4: 프로젝트 (업체) Project (Partner) | H4: 방향 Direction | I4: 셀러 측 (OMH 공급) Seller side (OMH supply) | J4: 바이어 측 (OMH 매입) Buyer side (OMH sourcing) | K4: 경유 파트너 수 Partners via this switch | L4: 연결 경로 Connection | M4: 원본 카테고리 Category (orig.) | N4: 비즈 임팩트 Biz Impact | O4: 영업 단계 (CRM) Sales stage (CRM) | P4: 담당 (현재) Owner (current) | Q4: 개발 주체 Dev Owner | R4: 처리 팀 Handling Team | S4: 진행률 Progress % | T4: 마지막 활동 Last Activity | U4: 단계 경과일 Days in Stage | V4: 지연 체크 Delay Check | W4: 현재 단계 Current Stage | X4: 파이프라인 기간 Pipeline Age | Y4: 체이스 # Chase # | Z4: 마지막 체이스 Last Chase | AA4: 체이스 후 경과일 Days Since Chase | AB4: 다음 체이스 Next Chase Due | AC4: 체이스 알림 Chase Alert | AD4: 목표 라이브 Target Go-Live | AE4: 대기 사유 Waiting On | AF4: 현황 · 다음 액션 (KR) Status · next action (KR) | AG4: 현황 · 다음 액션 (EN) Status · next action (EN) | AH4: 원본 Note (IT) Note (IT original) | AI4: 최종 연락 (CRM) Last contact (CRM) | AJ4: 출처 · 메모 Source · memo | AK4: ① 파이프라인 시작 Pipeline Start (5%) | AL4: ② 제안·소개 발송 Proposal / Intro Sent (10%) | AM4: ③ NDA 발송 NDA Sent (15%) | AN4: ④ NDA 체결 NDA Signed (20%) | AO4: ⑤ 계약 체결 Contract Signed (30%) | AP4: ⑥ SLA 확정 SLA Finalized (40%) | AQ4: ⑦ 개발 착수 예정 Dev Kickoff Planned (45%) | AR4: ⑧ 개발 착수 · SPEC/DEV 키 · 크리덴셜 Dev Kickoff / SPEC·DEV Key (50%) / Credential | AS4: ⑨ 인증 Certification (60%) | AT4: ⑩ 라이브 테스트 Live Test (70%) | AU4: ⑪ 개발 완료 예정 Dev Completion Planned (75%) | AV4: ⑫ 라이브 키 오픈 (OMH 측) Live Key Open – OMH side only (80%) | AW4: ⑬ 첫 예약 First Booking (90%) | AX4: ⑭ 고객 라이브 확정 (고객 통보) Customer Live Confirmed – client notified (100%)
A5: =IF($G5="","",ROW()-4) -> 1 | B5: =IF($G5="","",IF($C5<>"",$C5,IF($T5="","Contact",IF($S5>=1,"Live",IF($S5>=0.8,"Pending Live",IF($S5>=0.7,"Testing",IF($S5>=0.45,"In Development",IF($S5>=0.2,"NDA/Contract","Pipeline")))))))) -> Testing | E5: 중화권 · Greater China | F5: China | G5: Shiji | H5: 스위치 · Switch | I5: 진행 중 · In progress (셀러 인터페이스 10월 말~11월 초 · seller interface late Oct–early Nov, 첫 채널 Lion Travel · first channel Lion Travel) | J5: 테스트 완료 · Test done (인증 로그 전달만 남음 · only certification logs left) | K5: =COUNTIF('스위칭 연동 Switching'!$I$5:$I$400,"*Shiji*") -> 5 | L5: 스위치 자체 · Switch itself | M5: Switching System | N5: High | O5: API 연동 중 · Integrating | P5: GSM: Aiden → Jane (Dec~) | Q5: OHMY + Partner (50/50) | R5: SLA | S5: =IF($G5="","",IFERROR(LOOKUP(2,1/($AK5:$AX5<>""),$AK$2:$AX$2),0)) -> 0.7 | T5: =IF(COUNT($AK5:$AX5)=0,"",MAX($AK5:$AX5)) -> 46286 | U5: =IF($T5="","",TODAY()-$T5) -> 39 | V5: =IF($G5="","",IF($T5="","No Record",IF(OR($S5>=1,$C5="Live"),"Live",IF($U5>=90,"Stalled 90d+",IF($U5>=60,"Stalled 60d+",IF($U5>=30,"Stalled 30d+","In Progress")))))) -> Stalled 30d+ | W5: =IF(COUNT($AK5:$AX5)=0,"",LOOKUP(2,1/($AK5:$AX5<>""),{"① 파이프라인 시작 · Pipeline Start","② 제안·소개 발송 · Proposal Sent","③ NDA 발송 · NDA Sent","④ NDA 체결 · NDA Signed","⑤ 계약 체결 · Contract Signed","⑥ SLA 확정 · SLA Finalized","⑦ 개발 착수 예정 · Kickoff Planned","⑧ 개발 착수 · SPEC/DEV 키 · 크리덴셜 · Kickoff / Credential","⑨ 인증 · Certification","⑩ 라이브 테스트 · Live Test","⑪ 개발 완료 예정 · Dev Complete Planned","⑫ 라이브 키 오픈 (OMH 측) · Live Key Open","⑬ 첫 예약 · First Booking","⑭ 고객 라이브 확정 (고객 통보) · Customer Live"})) -> ⑩ 라이브 테스트 · Live Test | X5: =IF(COUNT($AK5:$AX5)=0,"",IF(N($S5)>=1,MAX($AK5:$AX5),TODAY())-MIN($AK5:$AX5)) -> 821 | Y5: =IF($G5="","",COUNTIF('Chase Log'!$B$4:$B$2000,$G5)) -> 2 | Z5: =IF(N($Y5)=0,"",_xlfn.MAXIFS('Chase Log'!$E$4:$E$2000,'Chase Log'!$B$4:$B$2000,$G5)) -> 46303 | AA5: =IF($Z5="","",TODAY()-$Z5) -> 22 | AB5: =IF($Z5="","",IF(OR(AND($T5<>"",N($T5)>N($Z5)),COUNTIFS('Chase Log'!$B$4:$B$2000,$G5,'Chase Log'!$E$4:$E$2000,$Z5,'Chase Log'!$I$4:$I$2000,"Y")>0),"",IF(_xlfn.MAXIFS('Chase Log'!$J$4:$J$2000,'Chase Log'!$B$4:$B$2000,$G5,'Chase Log'!$E$4:$E$2000,$Z5)=0,"",_xlfn.MAXIFS('Chase Log'!$J$4:$J$2000,'Chase Log'!$B$4:$B$2000,$G5,'Chase Log'!$E$4:$E$2000,$Z5)))) -> 46310 | AC5: =IF(OR($G5="",N($S5)>=1,$C5="Live",$D5<>""),"",IF(AND($AB5<>"",N($AB5)>0),IF($AB5<TODAY(),"Chase Overdue","Scheduled"),IF(AND($T5<>"",N($U5)>='안내 Guide'!$D$4,OR($AA5="",N($AA5)>='안내 Guide'!$D$4)),"Chase Needed",""))) -> Chase Overdue | AD5: 46302 | AF5: Ace Zhou 리캡 회신 — 마켓플레이스(셀러 2%) 진행 여부 결정 + 바이어 인증용 실행 로그 전달 | AG5: Reply to Ace Zhou's recap — decide whether to proceed with the marketplace (seller 2%) + send execution logs for buyer certification | AH5: Btw, regarding Shiji, current status is separate : Shiji (OMH are supply) : Shiji is doing it Shiji (OMH are demand - 3rd party integration) : Finish implementation, we're testing with them. | AI5: 2026-10-16 | AJ5: Tracker | AN5: 45504 | AO5: 46199 | AQ5: 46237 | AR5: 46267 | AS5: 46281 | AT5: 46286
A6: =IF($G6="","",ROW()-4) -> 2 | B6: =IF($G6="","",IF($C6<>"",$C6,IF($T6="","Contact",IF($S6>=1,"Live",IF($S6>=0.8,"Pending Live",IF($S6>=0.7,"Testing",IF($S6>=0.45,"In Development",IF($S6>=0.2,"NDA/Contract","Pipeline")))))))) -> In Development | E6: 유럽·미주 · Europe & Americas | F6: Spain | G6: TGX | H6: 스위치 · Switch | I6: 개발 중 · In development (인증 60% · certification 60%, Buyer 계약 1건 필요 · needs 1 buyer contract) | J6: 미확인 · Unconfirmed | K6: =COUNTIF('스위칭 연동 Switching'!$I$5:$I$400,"*TGX*") -> 13 | L6: 스위치 자체 · Switch itself | M6: Switching System | N6: High | O6: API 연동 중 · Integrating | P6: GSM: Aiden → Jane (Dec~) | Q6: OHMY + Partner (50/50) | R6: SLA | S6: =IF($G6="","",IFERROR(LOOKUP(2,1/($AK6:$AX6<>""),$AK$2:$AX$2),0)) -> 0.6 | T6: =IF(COUNT($AK6:$AX6)=0,"",MAX($AK6:$AX6)) -> 46287 | U6: =IF($T6="","",TODAY()-$T6) -> 38 | V6: =IF($G6="","",IF($T6="","No Record",IF(OR($S6>=1,$C6="Live"),"Live",IF($U6>=90,"Stalled 90d+",IF($U6>=60,"Stalled 60d+",IF($U6>=30,"Stalled 30d+","In Progress")))))) -> Stalled 30d+ | W6: =IF(COUNT($AK6:$AX6)=0,"",LOOKUP(2,1/($AK6:$AX6<>""),{"① 파이프라인 시작 · Pipeline Start","② 제안·소개 발송 · Proposal Sent","③ NDA 발송 · NDA Sent","④ NDA 체결 · NDA Signed","⑤ 계약 체결 · Contract Signed","⑥ SLA 확정 · SLA Finalized","⑦ 개발 착수 예정 · Kickoff Planned","⑧ 개발 착수 · SPEC/DEV 키 · 크리덴셜 · Kickoff / Credential","⑨ 인증 · Certification","⑩ 라이브 테스트 · Live Test","⑪ 개발 완료 예정 · Dev Complete Planned","⑫ 라이브 키 오픈 (OMH 측) · Live Key Open","⑬ 첫 예약 · First Booking","⑭ 고객 라이브 확정 (고객 통보) · Customer Live"})) -> ⑨ 인증 · Certification | X6: =IF(COUNT($AK6:$AX6)=0,"",IF(N($S6)>=1,MAX($AK6:$AX6),TODAY())-MIN($AK6:$AX6)) -> 38 | Y6: =IF($G6="","",COUNTIF('Chase Log'!$B$4:$B$2000,$G6)) -> 1 | Z6: =IF(N($Y6)=0,"",_xlfn.MAXIFS('Chase Log'!$E$4:$E$2000,'Chase Log'!$B$4:$B$2000,$G6)) -> 46300 | AA6: =IF($Z6="","",TODAY()-$Z6) -> 25 | AB6: =IF($Z6="","",IF(OR(AND($T6<>"",N($T6)>N($Z6)),COUNTIFS('Chase Log'!$B$4:$B$2000,$G6,'Chase Log'!$E$4:$E$2000,$Z6,'Chase Log'!$I$4:$I$2000,"Y")>0),"",IF(_xlfn.MAXIFS('Chase Log'!$J$4:$J$2000,'Chase Log'!$B$4:$B$2000,$G6,'Chase Log'!$E$4:$E$2000,$Z6)=0,"",_xlfn.MAXIFS('Chase Log'!$J$4:$J$2000,'Chase Log'!$B$4:$B$2000,$G6,'Chase Log'!$E$4:$E$2000,$Z6)))) | AC6: =IF(OR($G6="",N($S6)>=1,$C6="Live",$D6<>""),"",IF(AND($AB6<>"",N($AB6)>0),IF($AB6<TODAY(),"Chase Overdue","Scheduled"),IF(AND($T6<>"",N($U6)>='안내 Guide'!$D$4,OR($AA6="",N($AA6)>='안내 Guide'!$D$4)),"Chase Needed",""))) -> Chase Needed | AF6: OMH TGX 개발 완료 일정 확보 + Buyer 계약 1건(VOLT 또는 Welcomebeds) 확정 | AG6: Secure OMH TGX development completion date + confirm one Buyer contract (VOLT or Welcomebeds) | AI6: 2026-09-15 | AJ6: Tracker | AS6: 46287
A7: =IF($G7="","",ROW()-4) -> 3 | B7: =IF($G7="","",IF($C7<>"",$C7,IF($T7="","Contact",IF($S7>=1,"Live",IF($S7>=0.8,"Pending Live",IF($S7>=0.7,"Testing",IF($S7>=0.45,"In Development",IF($S7>=0.2,"NDA/Contract","Pipeline")))))))) -> Contact | E7: 인도 · India | F7: India | G7: Zentrumhub | H7: 스위치 · Switch | I7: 미확인 · Unconfirmed | J7: 미확인 · Unconfirmed | K7: =COUNTIF('스위칭 연동 Switching'!$I$5:$I$400,"*ZentrumHub*") -> 1 | L7: 스위치 자체 · Switch itself | O7: 신규 개발 · New lead | P7: GSM: Aiden → Jane (Dec~) | S7: =IF($G7="","",IFERROR(LOOKUP(2,1/($AK7:$AX7<>""),$AK$2:$AX$2),0)) -> 0 | T7: =IF(COUNT($AK7:$AX7)=0,"",MAX($AK7:$AX7)) | U7: =IF($T7="","",TODAY()-$T7) | V7: =IF($G7="","",IF($T7="","No Record",IF(OR($S7>=1,$C7="Live"),"Live",IF($U7>=90,"Stalled 90d+",IF($U7>=60,"Stalled 60d+",IF($U7>=30,"Stalled 30d+","In Progress")))))) -> No Record | W7: =IF(COUNT($AK7:$AX7)=0,"",LOOKUP(2,1/($AK7:$AX7<>""),{"① 파이프라인 시작 · Pipeline Start","② 제안·소개 발송 · Proposal Sent","③ NDA 발송 · NDA Sent","④ NDA 체결 · NDA Signed","⑤ 계약 체결 · Contract Signed","⑥ SLA 확정 · SLA Finalized","⑦ 개발 착수 예정 · Kickoff Planned","⑧ 개발 착수 · SPEC/DEV 키 · 크리덴셜 · Kickoff / Credential","⑨ 인증 · Certification","⑩ 라이브 테스트 · Live Test","⑪ 개발 완료 예정 · Dev Complete Planned","⑫ 라이브 키 오픈 (OMH 측) · Live Key Open","⑬ 첫 예약 · First Booking","⑭ 고객 라이브 확정 (고객 통보) · Customer Live"})) | X7: =IF(COUNT($AK7:$AX7)=0,"",IF(N($S7)>=1,MAX($AK7:$AX7),TODAY())-MIN($AK7:$AX7)) | Y7: =IF($G7="","",COUNTIF('Chase Log'!$B$4:$B$2000,$G7)) -> 3 | Z7: =IF(N($Y7)=0,"",_xlfn.MAXIFS('Chase Log'!$E$4:$E$2000,'Chase Log'!$B$4:$B$2000,$G7)) -> 46322 | AA7: =IF($Z7="","",TODAY()-$Z7) -> 3 | AB7: =IF($Z7="","",IF(OR(AND($T7<>"",N($T7)>N($Z7)),COUNTIFS('Chase Log'!$B$4:$B$2000,$G7,'Chase Log'!$E$4:$E$2000,$Z7,'Chase Log'!$I$4:$I$2000,"Y")>0),"",IF(_xlfn.MAXIFS('Chase Log'!$J$4:$J$2000,'Chase Log'!$B$4:$B$2000,$G7,'Chase Log'!$E$4:$E$2000,$Z7)=0,"",_xlfn.MAXIFS('Chase Log'!$J$4:$J$2000,'Chase Log'!$B$4:$B$2000,$G7,'Chase Log'!$E$4:$E$2000,$Z7)))) -> 46329 | AC7: =IF(OR($G7="",N($S7)>=1,$C7="Live",$D7<>""),"",IF(AND($AB7<>"",N($AB7)>0),IF($AB7<TODAY(),"Chase Overdue","Scheduled"),IF(AND($T7<>"",N($U7)>='안내 Guide'!$D$4,OR($AA7="",N($AA7)>='안내 Guide'!$D$4)),"Chase Needed",""))) -> Scheduled | AF7: GSM 인수 후 진행 상태 확인, 추가 스위치 여부는 Shiji·TGX 완료 후 판단 | AG7: Check progress after GSM takeover; decide on additional switches after Shiji and TGX are complete | AI7: 2026-10-05 | AJ7: CRM 추가 · Added from CRM (Tracker 미등록 · not in Tracker; 단계 날짜는 확인되는 대로 입력 · add stage dates when confirmed)
A8: =IF($G8="","",ROW()-4) -> 4 | B8: =IF($G8="","",IF($C8<>"",$C8,IF($T8="","Contact",IF($S8>=1,"Live",IF($S8>=0.8,"Pending Live",IF($S8>=0.7,"Testing",IF($S8>=0.45,"In Development",IF($S8>=0.2,"NDA/Contract","Pipeline")))))))) -> Contact | D8: Dropped | E8: 한국 · Korea | F8: Korea | G8: 11infortec | H8: 스위치 · Switch | I8: 미확인 · Unconfirmed | J8: 미확인 · Unconfirmed | K8: =COUNTIF('스위칭 연동 Switching'!$I$5:$I$400,"*11infortec*") -> 0 | L8: 스위치 자체 · Switch itself | M8: Switching System | N8: Low | O8: — | P8: GSM: Aiden → Jane (Dec~) | Q8: OHMY | R8: SLA | S8: =IF($G8="","",IFERROR(LOOKUP(2,1/($AK8:$AX8<>""),$AK$2:$AX$2),0)) -> 0 | T8: =IF(COUNT($AK8:$AX8)=0,"",MAX($AK8:$AX8)) | U8: =IF($T8="","",TODAY()-$T8) | V8: =IF($G8="","",IF($T8="","No Record",IF(OR($S8>=1,$C8="Live"),"Live",IF($U8>=90,"Stalled 90d+",IF($U8>=60,"Stalled 60d+",IF($U8>=30,"Stalled 30d+","In Progress")))))) -> No Record | W8: =IF(COUNT($AK8:$AX8)=0,"",LOOKUP(2,1/($AK8:$AX8<>""),{"① 파이프라인 시작 · Pipeline Start","② 제안·소개 발송 · Proposal Sent","③ NDA 발송 · NDA Sent","④ NDA 체결 · NDA Signed","⑤ 계약 체결 · Contract Signed","⑥ SLA 확정 · SLA Finalized","⑦ 개발 착수 예정 · Kickoff Planned","⑧ 개발 착수 · SPEC/DEV 키 · 크리덴셜 · Kickoff / Credential","⑨ 인증 · Certification","⑩ 라이브 테스트 · Live Test","⑪ 개발 완료 예정 · Dev Complete Planned","⑫ 라이브 키 오픈 (OMH 측) · Live Key Open","⑬ 첫 예약 · First Booking","⑭ 고객 라이브 확정 (고객 통보) · Customer Live"})) | X8: =IF(COUNT($AK8:$AX8)=0,"",IF(N($S8)>=1,MAX($AK8:$AX8),TODAY())-MIN($AK8:$AX8)) | Y8: =IF($G8="","",COUNTIF('Chase Log'!$B$4:$B$2000,$G8)) -> 0 | Z8: =IF(N($Y8)=0,"",_xlfn.MAXIFS('Chase Log'!$E$4:$E$2000,'Chase Log'!$B$4:$B$2000,$G8)) | AA8: =IF($Z8="","",TODAY()-$Z8) | AB8: =IF($Z8="","",IF(OR(AND($T8<>"",N($T8)>N($Z8)),COUNTIFS('Chase Log'!$B$4:$B$2000,$G8,'Chase Log'!$E$4:$E$2000,$Z8,'Chase Log'!$I$4:$I$2000,"Y")>0),"",IF(_xlfn.MAXIFS('Chase Log'!$J$4:$J$2000,'Chase Log'!$B$4:$B$2000,$G8,'Chase Log'!$E$4:$E$2000,$Z8)=0,"",_xlfn.MAXIFS('Chase Log'!$J$4:$J$2000,'Chase Log'!$B$4:$B$2000,$G8,'Chase Log'!$E$4:$E$2000,$Z8)))) | AC8: =IF(OR($G8="",N($S8)>=1,$C8="Live",$D8<>""),"",IF(AND($AB8<>"",N($AB8)>0),IF($AB8<TODAY(),"Chase Overdue","Scheduled"),IF(AND($T8<>"",N($U8)>='안내 Guide'!$D$4,OR($AA8="",N($AA8)>='안내 Guide'!$D$4)),"Chase Needed",""))) | AJ8: Tracker
A9: =IF($G9="","",ROW()-4) -> 5 | B9: =IF($G9="","",IF($C9<>"",$C9,IF($T9="","Contact",IF($S9>=1,"Live",IF($S9>=0.8,"Pending Live",IF($S9>=0.7,"Testing",IF($S9>=0.45,"In Development",IF($S9>=0.2,"NDA/Contract","Pipeline")))))))) -> Contact | D9: On Hold | E9: 중화권 · Greater China | F9: China | G9: Derbysoft | H9: 스위치 · Switch | I9: 미확인 · Unconfirmed | J9: 미확인 · Unconfirmed | K9: =COUNTIF('스위칭 연동 Switching'!$I$5:$I$400,"*Derbysoft*") -> 0 | L9: 스위치 자체 · Switch itself | M9: Switching System | N9: Low | O9: — | P9: GSM: Aiden → Jane (Dec~) | Q9: OHMY | R9: SLA | S9: =IF($G9="","",IFERROR(LOOKUP(2,1/($AK9:$AX9<>""),$AK$2:$AX$2),0)) -> 0 | T9: =IF(COUNT($AK9:$AX9)=0,"",MAX($AK9:$AX9)) | U9: =IF($T9="","",TODAY()-$T9) | V9: =IF($G9="","",IF($T9="","No Record",IF(OR($S9>=1,$C9="Live"),"Live",IF($U9>=90,"Stalled 90d+",IF($U9>=60,"Stalled 60d+",IF($U9>=30,"Stalled 30d+","In Progress")))))) -> No Record | W9: =IF(COUNT($AK9:$AX9)=0,"",LOOKUP(2,1/($AK9:$AX9<>""),{"① 파이프라인 시작 · Pipeline Start","② 제안·소개 발송 · Proposal Sent","③ NDA 발송 · NDA Sent","④ NDA 체결 · NDA Signed","⑤ 계약 체결 · Contract Signed","⑥ SLA 확정 · SLA Finalized","⑦ 개발 착수 예정 · Kickoff Planned","⑧ 개발 착수 · SPEC/DEV 키 · 크리덴셜 · Kickoff / Credential","⑨ 인증 · Certification","⑩ 라이브 테스트 · Live Test","⑪ 개발 완료 예정 · Dev Complete Planned","⑫ 라이브 키 오픈 (OMH 측) · Live Key Open","⑬ 첫 예약 · First Booking","⑭ 고객 라이브 확정 (고객 통보) · Customer Live"})) | X9: =IF(COUNT($AK9:$AX9)=0,"",IF(N($S9)>=1,MAX($AK9:$AX9),TODAY())-MIN($AK9:$AX9)) | Y9: =IF($G9="","",COUNTIF('Chase Log'!$B$4:$B$2000,$G9)) -> 0 | Z9: =IF(N($Y9)=0,"",_xlfn.MAXIFS('Chase Log'!$E$4:$E$2000,'Chase Log'!$B$4:$B$2000,$G9)) | AA9: =IF($Z9="","",TODAY()-$Z9) | AB9: =IF($Z9="","",IF(OR(AND($T9<>"",N($T9)>N($Z9)),COUNTIFS('Chase Log'!$B$4:$B$2000,$G9,'Chase Log'!$E$4:$E$2000,$Z9,'Chase Log'!$I$4:$I$2000,"Y")>0),"",IF(_xlfn.MAXIFS('Chase Log'!$J$4:$J$2000,'Chase Log'!$B$4:$B$2000,$G9,'Chase Log'!$E$4:$E$2000,$Z9)=0,"",_xlfn.MAXIFS('Chase Log'!$J$4:$J$2000,'Chase Log'!$B$4:$B$2000,$G9,'Chase Log'!$E$4:$E$2000,$Z9)))) | AC9: =IF(OR($G9="",N($S9)>=1,$C9="Live",$D9<>""),"",IF(AND($AB9<>"",N($AB9)>0),IF($AB9<TODAY(),"Chase Overdue","Scheduled"),IF(AND($T9<>"",N($U9)>='안내 Guide'!$D$4,OR($AA9="",N($AA9)>='안내 Guide'!$D$4)),"Chase Needed",""))) | AJ9: Tracker
A10: =IF($G10="","",ROW()-4) -> 6 | B10: =IF($G10="","",IF($C10<>"",$C10,IF($T10="","Contact",IF($S10>=1,"Live",IF($S10>=0.8,"Pending Live",IF($S10>=0.7,"Testing",IF($S10>=0.45,"In Development",IF($S10>=0.2,"NDA/Contract","Pipeline")))))))) -> Contact | D10: On Hold | E10: 동남아 · SE Asia | F10: Singapore | G10: TAN | H10: 스위치 · Switch | I10: 미확인 · Unconfirmed | J10: 미확인 · Unconfirmed | K10: =COUNTIF('스위칭 연동 Switching'!$I$5:$I$400,"*TAN*") -> 1 | L10: 스위치 자체 · Switch itself | M10: Switching System | N10: Low | O10: — | P10: GSM: Aiden → Jane (Dec~) | Q10: OHMY | R10: SLA | S10: =IF($G10="","",IFERROR(LOOKUP(2,1/($AK10:$AX10<>""),$AK$2:$AX$2),0)) -> 0 | T10: =IF(COUNT($AK10:$AX10)=0,"",MAX($AK10:$AX10)) | U10: =IF($T10="","",TODAY()-$T10) | V10: =IF($G10="","",IF($T10="","No Record",IF(OR($S10>=1,$C10="Live"),"Live",IF($U10>=90,"Stalled 90d+",IF($U10>=60,"Stalled 60d+",IF($U10>=30,"Stalled 30d+","In Progress")))))) -> No Record | W10: =IF(COUNT($AK10:$AX10)=0,"",LOOKUP(2,1/($AK10:$AX10<>""),{"① 파이프라인 시작 · Pipeline Start","② 제안·소개 발송 · Proposal Sent","③ NDA 발송 · NDA Sent","④ NDA 체결 · NDA Signed","⑤ 계약 체결 · Contract Signed","⑥ SLA 확정 · SLA Finalized","⑦ 개발 착수 예정 · Kickoff Planned","⑧ 개발 착수 · SPEC/DEV 키 · 크리덴셜 · Kickoff / Credential","⑨ 인증 · Certification","⑩ 라이브 테스트 · Live Test","⑪ 개발 완료 예정 · Dev Complete Planned","⑫ 라이브 키 오픈 (OMH 측) · Live Key Open","⑬ 첫 예약 · First Booking","⑭ 고객 라이브 확정 (고객 통보) · Customer Live"})) | X10: =IF(COUNT($AK10:$AX10)=0,"",IF(N($S10)>=1,MAX($AK10:$AX10),TODAY())-MIN($AK10:$AX10)) | Y10: =IF($G10="","",COUNTIF('Chase Log'!$B$4:$B$2000,$G10)) -> 0 | Z10: =IF(N($Y10)=0,"",_xlfn.MAXIFS('Chase Log'!$E$4:$E$2000,'Chase Log'!$B$4:$B$2000,$G10)) | AA10: =IF($Z10="","",TODAY()-$Z10) | AB10: =IF($Z10="","",IF(OR(AND($T10<>"",N($T10)>N($Z10)),COUNTIFS('Chase Log'!$B$4:$B$2000,$G10,'Chase Log'!$E$4:$E$2000,$Z10,'Chase Log'!$I$4:$I$2000,"Y")>0),"",IF(_xlfn.MAXIFS('Chase Log'!$J$4:$J$2000,'Chase Log'!$B$4:$B$2000,$G10,'Chase Log'!$E$4:$E$2000,$Z10)=0,"",_xlfn.MAXIFS('Chase Log'!$J$4:$J$2000,'Chase Log'!$B$4:$B$2000,$G10,'Chase Log'!$E$4:$E$2000,$Z10)))) | AC10: =IF(OR($G10="",N($S10)>=1,$C10="Live",$D10<>""),"",IF(AND($AB10<>"",N($AB10)>0),IF($AB10<TODAY(),"Chase Overdue","Scheduled"),IF(AND($T10<>"",N($U10)>='안내 Guide'!$D$4,OR($AA10="",N($AA10)>='안내 Guide'!$D$4)),"Chase Needed",""))) | AJ10: Tracker
A11: =IF($G11="","",ROW()-4) -> 7 | B11: =IF($G11="","",IF($C11<>"",$C11,IF($T11="","Contact",IF($S11>=1,"Live",IF($S11>=0.8,"Pending Live",IF($S11>=0.7,"Testing",IF($S11>=0.45,"In Development",IF($S11>=0.2,"NDA/Contract","Pipeline")))))))) -> Contact | D11: On Hold | E11: 유럽·미주 · Europe & Americas | F11: Spain | G11: Juniper | H11: 스위치 · Switch | I11: 미확인 · Unconfirmed | J11: 미확인 · Unconfirmed | K11: =COUNTIF('스위칭 연동 Switching'!$I$5:$I$400,"*Juniper*") -> 1 | L11: 스위치 자체 · Switch itself | M11: Switching System | N11: Mid | O11: 보류·종료 · On hold · closed | P11: GSM: Aiden → Jane (Dec~) | Q11: Partner (client-side) | R11: SLA | S11: =IF($G11="","",IFERROR(LOOKUP(2,1/($AK11:$AX11<>""),$AK$2:$AX$2),0)) -> 0 | T11: =IF(COUNT($AK11:$AX11)=0,"",MAX($AK11:$AX11)) | U11: =IF($T11="","",TODAY()-$T11) | V11: =IF($G11="","",IF($T11="","No Record",IF(OR($S11>=1,$C11="Live"),"Live",IF($U11>=90,"Stalled 90d+",IF($U11>=60,"Stalled 60d+",IF($U11>=30,"Stalled 30d+","In Progress")))))) -> No Record | W11: =IF(COUNT($AK11:$AX11)=0,"",LOOKUP(2,1/($AK11:$AX11<>""),{"① 파이프라인 시작 · Pipeline Start","② 제안·소개 발송 · Proposal Sent","③ NDA 발송 · NDA Sent","④ NDA 체결 · NDA Signed","⑤ 계약 체결 · Contract Signed","⑥ SLA 확정 · SLA Finalized","⑦ 개발 착수 예정 · Kickoff Planned","⑧ 개발 착수 · SPEC/DEV 키 · 크리덴셜 · Kickoff / Credential","⑨ 인증 · Certification","⑩ 라이브 테스트 · Live Test","⑪ 개발 완료 예정 · Dev Complete Planned","⑫ 라이브 키 오픈 (OMH 측) · Live Key Open","⑬ 첫 예약 · First Booking","⑭ 고객 라이브 확정 (고객 통보) · Customer Live"})) | X11: =IF(COUNT($AK11:$AX11)=0,"",IF(N($S11)>=1,MAX($AK11:$AX11),TODAY())-MIN($AK11:$AX11)) | Y11: =IF($G11="","",COUNTIF('Chase Log'!$B$4:$B$2000,$G11)) -> 0 | Z11: =IF(N($Y11)=0,"",_xlfn.MAXIFS('Chase Log'!$E$4:$E$2000,'Chase Log'!$B$4:$B$2000,$G11)) | AA11: =IF($Z11="","",TODAY()-$Z11) | AB11: =IF($Z11="","",IF(OR(AND($T11<>"",N($T11)>N($Z11)),COUNTIFS('Chase Log'!$B$4:$B$2000,$G11,'Chase Log'!$E$4:$E$2000,$Z11,'Chase Log'!$I$4:$I$2000,"Y")>0),"",IF(_xlfn.MAXIFS('Chase Log'!$J$4:$J$2000,'Chase Log'!$B$4:$B$2000,$G11,'Chase Log'!$E$4:$E$2000,$Z11)=0,"",_xlfn.MAXIFS('Chase Log'!$J$4:$J$2000,'Chase Log'!$B$4:$B$2000,$G11,'Chase Log'!$E$4:$E$2000,$Z11)))) | AC11: =IF(OR($G11="",N($S11)>=1,$C11="Live",$D11<>""),"",IF(AND($AB11<>"",N($AB11)>0),IF($AB11<TODAY(),"Chase Overdue","Scheduled"),IF(AND($T11<>"",N($U11)>='안내 Guide'!$D$4,OR($AA11="",N($AA11)>='안내 Guide'!$D$4)),"Chase Needed",""))) | AF11: 3rd party GSM 인수 과정에서 Juniper 검토 유지/종료 결정 | AG11: Decide whether to continue or end the Juniper review as part of the 3rd-party handover to GSM | AI11: 미확인 | AJ11: Tracker
A12: =IF($G12="","",ROW()-4) -> 8 | B12: =IF($G12="","",IF($C12<>"",$C12,IF($T12="","Contact",IF($S12>=1,"Live",IF($S12>=0.8,"Pending Live",IF($S12>=0.7,"Testing",IF($S12>=0.45,"In Development",IF($S12>=0.2,"NDA/Contract","Pipeline")))))))) -> Contact | D12: On Hold | E12: 유럽·미주 · Europe & Americas | F12: USA | G12: Synxis | H12: 스위치 · Switch | I12: 미확인 · Unconfirmed | J12: 미확인 · Unconfirmed | K12: =COUNTIF('스위칭 연동 Switching'!$I$5:$I$400,"*Synxis*") -> 0 | L12: 스위치 자체 · Switch itself | M12: Switching System | N12: Low | O12: — | P12: GSM: Aiden → Jane (Dec~) | Q12: OHMY | R12: SLA | S12: =IF($G12="","",IFERROR(LOOKUP(2,1/($AK12:$AX12<>""),$AK$2:$AX$2),0)) -> 0 | T12: =IF(COUNT($AK12:$AX12)=0,"",MAX($AK12:$AX12)) | U12: =IF($T12="","",TODAY()-$T12) | V12: =IF($G12="","",IF($T12="","No Record",IF(OR($S12>=1,$C12="Live"),"Live",IF($U12>=90,"Stalled 90d+",IF($U12>=60,"Stalled 60d+",IF($U12>=30,"Stalled 30d+","In Progress")))))) -> No Record | W12: =IF(COUNT($AK12:$AX12)=0,"",LOOKUP(2,1/($AK12:$AX12<>""),{"① 파이프라인 시작 · Pipeline Start","② 제안·소개 발송 · Proposal Sent","③ NDA 발송 · NDA Sent","④ NDA 체결 · NDA Signed","⑤ 계약 체결 · Contract Signed","⑥ SLA 확정 · SLA Finalized","⑦ 개발 착수 예정 · Kickoff Planned","⑧ 개발 착수 · SPEC/DEV 키 · 크리덴셜 · Kickoff / Credential","⑨ 인증 · Certification","⑩ 라이브 테스트 · Live Test","⑪ 개발 완료 예정 · Dev Complete Planned","⑫ 라이브 키 오픈 (OMH 측) · Live Key Open","⑬ 첫 예약 · First Booking","⑭ 고객 라이브 확정 (고객 통보) · Customer Live"})) | X12: =IF(COUNT($AK12:$AX12)=0,"",IF(N($S12)>=1,MAX($AK12:$AX12),TODAY())-MIN($AK12:$AX12)) | Y12: =IF($G12="","",COUNTIF('Chase Log'!$B$4:$B$2000,$G12)) -> 0 | Z12: =IF(N($Y12)=0,"",_xlfn.MAXIFS('Chase Log'!$E$4:$E$2000,'Chase Log'!$B$4:$B$2000,$G12)) | AA12: =IF($Z12="","",TODAY()-$Z12) | AB12: =IF($Z12="","",IF(OR(AND($T12<>"",N($T12)>N($Z12)),COUNTIFS('Chase Log'!$B$4:$B$2000,$G12,'Chase Log'!$E$4:$E$2000,$Z12,'Chase Log'!$I$4:$I$2000,"Y")>0),"",IF(_xlfn.MAXIFS('Chase Log'!$J$4:$J$2000,'Chase Log'!$B$4:$B$2000,$G12,'Chase Log'!$E$4:$E$2000,$Z12)=0,"",_xlfn.MAXIFS('Chase Log'!$J$4:$J$2000,'Chase Log'!$B$4:$B$2000,$G12,'Chase Log'!$E$4:$E$2000,$Z12)))) | AC12: =IF(OR($G12="",N($S12)>=1,$C12="Live",$D12<>""),"",IF(AND($AB12<>"",N($AB12)>0),IF($AB12<TODAY(),"Chase Overdue","Scheduled"),IF(AND($T12<>"",N($U12)>='안내 Guide'!$D$4,OR($AA12="",N($AA12)>='안내 Guide'!$D$4)),"Chase Needed",""))) | AJ12: Tracker

Sheet 스위칭 연동 Switching
A1: 스위칭 연동 Switching | E1: 스위치(TGX·Shiji 등)를 거쳐 연결하는 파트너 · 스위치 업체 자체는 '스위칭 업체' 시트 · 오너 GSM (Aiden 인수 중, 12월~ Jane) Partners connected through a switch (TGX, Shiji, etc.) · the switch vendors themselves are on the 'Switch vendors' sheet · Owner: GSM (Aiden taking over, Jane lead from Dec)
A2: ="전체 Total "&COUNTA($G$5:$G$400)&" · 라이브 Live "&(COUNTIF($B$5:$B$400,"Live")+COUNTIF($B$5:$B$400,"Partially Live"))&" · 개발·테스트 Dev/Test "&(COUNTIF($B$5:$B$400,"In Development")+COUNTIF($B$5:$B$400,"Testing")+COUNTIF($B$5:$B$400,"Pending Live"))&" · 계약·NDA "&COUNTIF($B$5:$B$400,"NDA/Contract")&" · 파이프라인 Pipeline "&(COUNTIF($B$5:$B$400,"Pipeline")+COUNTIF($B$5:$B$400,"Contact"))&" · 60일+ 정체 Stalled 60d+ "&(COUNTIF($S$5:$S$400,"Stalled 60d+")+COUNTIF($S$5:$S$400,"Stalled 90d+")) -> 전체 Total 16 · 라이브 Live 0 · 개발·테스트 Dev/Test 0 · 계약·NDA 3 · 파이프라인 Pipeline 13 · 60일+ 정체 Stalled 60d+ 1 | AG2: 단계 가중치 · Stage weight → | AH2: 0.05 | AI2: 0.1 | AJ2: 0.15 | AK2: 0.2 | AL2: 0.3 | AM2: 0.4 | AN2: 0.45 | AO2: 0.5 | AP2: 0.6 | AQ2: 0.7 | AR2: 0.75 | AS2: 0.8 | AT2: 0.9 | AU2: 1
A3: 프로젝트 · 개발 정보 · Project / Dev Info | P3: 진행 · 체이스 현황 (자동 계산) · Progress & Chase Status (Auto-calculated) | AA3: 계획 · 이슈 (직접 입력) · Plan & Issues (manual entry) | AH3: 단계 이력 (실제 날짜) · Stage History (actual dates) — Pipeline → Contract → Dev → Customer Live
A4: No. | B4: 상태 Status | C4: 상태 수동 지정 Status override | D4: 보류/드롭 Hold/Drop | E4: 지역 Region | F4: 국가 Country | G4: 프로젝트 (업체) Project (Partner) | H4: 방향 Direction | I4: 연결 경로 Connection | J4: 원본 카테고리 Category (orig.) | K4: 비즈 임팩트 Biz Impact | L4: 영업 단계 (CRM) Sales stage (CRM) | M4: 담당 (현재) Owner (current) | N4: 개발 주체 Dev Owner | O4: 처리 팀 Handling Team | P4: 진행률 Progress % | Q4: 마지막 활동 Last Activity | R4: 단계 경과일 Days in Stage | S4: 지연 체크 Delay Check | T4: 현재 단계 Current Stage | U4: 파이프라인 기간 Pipeline Age | V4: 체이스 # Chase # | W4: 마지막 체이스 Last Chase | X4: 체이스 후 경과일 Days Since Chase | Y4: 다음 체이스 Next Chase Due | Z4: 체이스 알림 Chase Alert | AA4: 목표 라이브 Target Go-Live | AB4: 대기 사유 Waiting On | AC4: 현황 · 다음 액션 (KR) Status · next action (KR) | AD4: 현황 · 다음 액션 (EN) Status · next action (EN) | AE4: 원본 Note (IT) Note (IT original) | AF4: 최종 연락 (CRM) Last contact (CRM) | AG4: 출처 · 메모 Source · memo | AH4: ① 파이프라인 시작 Pipeline Start (5%) | AI4: ② 제안·소개 발송 Proposal / Intro Sent (10%) | AJ4: ③ NDA 발송 NDA Sent (15%) | AK4: ④ NDA 체결 NDA Signed (20%) | AL4: ⑤ 계약 체결 Contract Signed (30%) | AM4: ⑥ SLA 확정 SLA Finalized (40%) | AN4: ⑦ 개발 착수 예정 Dev Kickoff Planned (45%) | AO4: ⑧ 개발 착수 · SPEC/DEV 키 · 크리덴셜 Dev Kickoff / SPEC·DEV Key (50%) / Credential | AP4: ⑨ 인증 Certification (60%) | AQ4: ⑩ 라이브 테스트 Live Test (70%) | AR4: ⑪ 개발 완료 예정 Dev Completion Planned (75%) | AS4: ⑫ 라이브 키 오픈 (OMH 측) Live Key Open – OMH side only (80%) | AT4: ⑬ 첫 예약 First Booking (90%) | AU4: ⑭ 고객 라이브 확정 (고객 통보) Customer Live Confirmed – client notified (100%)
A5: =IF($G5="","",ROW()-4) -> 1 | B5: =IF($G5="","",IF($C5<>"",$C5,IF($Q5="","Contact",IF($P5>=1,"Live",IF($P5>=0.8,"Pending Live",IF($P5>=0.7,"Testing",IF($P5>=0.45,"In Development",IF($P5>=0.2,"NDA/Contract","Pipeline")))))))) -> NDA/Contract | E5: 중화권 · Greater China | F5: Taiwan | G5: Lion Travel | H5: 공급 · OMH → Partner | I5: SHIJI | J5: Channel API | K5: High | L5: 계약 협상 중 · Contract talks | M5: Grace | N5: Partner (client-side) | O5: GSM | P5: =IF($G5="","",IFERROR(LOOKUP(2,1/($AH5:$AU5<>""),$AH$2:$AU$2),0)) -> 0.2 | Q5: =IF(COUNT($AH5:$AU5)=0,"",MAX($AH5:$AU5)) -> 45912 | R5: =IF($Q5="","",TODAY()-$Q5) -> 413 | S5: =IF($G5="","",IF($Q5="","No Record",IF(OR($P5>=1,$C5="Live"),"Live",IF($R5>=90,"Stalled 90d+",IF($R5>=60,"Stalled 60d+",IF($R5>=30,"Stalled 30d+","In Progress")))))) -> Stalled 90d+ | T5: =IF(COUNT($AH5:$AU5)=0,"",LOOKUP(2,1/($AH5:$AU5<>""),{"① 파이프라인 시작 · Pipeline Start","② 제안·소개 발송 · Proposal Sent","③ NDA 발송 · NDA Sent","④ NDA 체결 · NDA Signed","⑤ 계약 체결 · Contract Signed","⑥ SLA 확정 · SLA Finalized","⑦ 개발 착수 예정 · Kickoff Planned","⑧ 개발 착수 · SPEC/DEV 키 · 크리덴셜 · Kickoff / Credential","⑨ 인증 · Certification","⑩ 라이브 테스트 · Live Test","⑪ 개발 완료 예정 · Dev Complete Planned","⑫ 라이브 키 오픈 (OMH 측) · Live Key Open","⑬ 첫 예약 · First Booking","⑭ 고객 라이브 확정 (고객 통보) · Customer Live"})) -> ④ NDA 체결 · NDA Signed | U5: =IF(COUNT($AH5:$AU5)=0,"",IF(N($P5)>=1,MAX($AH5:$AU5),TODAY())-MIN($AH5:$AU5)) -> 413 | V5: =IF($G5="","",COUNTIF('Chase Log'!$B$4:$B$2000,$G5)) -> 1 | W5: =IF(N($V5)=0,"",_xlfn.MAXIFS('Chase Log'!$E$4:$E$2000,'Chase Log'!$B$4:$B$2000,$G5)) -> 46300 | X5: =IF($W5="","",TODAY()-$W5) -> 25 | Y5: =IF($W5="","",IF(OR(AND($Q5<>"",N($Q5)>N($W5)),COUNTIFS('Chase Log'!$B$4:$B$2000,$G5,'Chase Log'!$E$4:$E$2000,$W5,'Chase Log'!$I$4:$I$2000,"Y")>0),"",IF(_xlfn.MAXIFS('Chase Log'!$J$4:$J$2000,'Chase Log'!$B$4:$B$2000,$G5,'Chase Log'!$E$4:$E$2000,$W5)=0,"",_xlfn.MAXIFS('Chase Log'!$J$4:$J$2000,'Chase Log'!$B$4:$B$2000,$G5,'Chase Log'!$E$4:$E$2000,$W5)))) | Z5: =IF(OR($G5="",N($P5)>=1,$C5="Live",$D5<>""),"",IF(AND($Y5<>"",N($Y5)>0),IF($Y5<TODAY(),"Chase Overdue","Scheduled"),IF(AND($Q5<>"",N($R5)>='안내 Guide'!$D$4,OR($X5="",N($X5)>='안내 Guide'!$D$4)),"Chase Needed",""))) -> Chase Needed | AC5: Shiji 셀러 측 인터페이스 완료(10월 말~11월 초) 후 Shiji 경유 첫 채널 오픈 준비 — Shiji 폴더 TASKS #7(3자 미팅)과 연계 | AD5: After Shiji seller-side interface is complete (late Oct–early Nov), prepare first channel launch via Shiji — link with Shiji folder TASKS #7 (three-party meeting) | AF5: 2026-10-05 | AG5: Tracker | AK5: 45912
A6: =IF($G6="","",ROW()-4) -> 2 | B6: =IF($G6="","",IF($C6<>"",$C6,IF($Q6="","Contact",IF($P6>=1,"Live",IF($P6>=0.8,"Pending Live",IF($P6>=0.7,"Testing",IF($P6>=0.45,"In Development",IF($P6>=0.2,"NDA/Contract","Pipeline")))))))) -> NDA/Contract | E6: 동남아 · SE Asia | F6: Thailand | G6: Pax2night | H6: 양방향 · Two-way | I6: Shiji (TGX에서 전환) · Shiji (moved from TGX) | J6: TGX Switching | K6: Mid | L6: API 연동 중 · Integrating | M6: GSM: Aiden → Jane (Dec~) | N6: OHMY + Partner (50/50) | O6: GSM | P6: =IF($G6="","",IFERROR(LOOKUP(2,1/($AH6:$AU6<>""),$AH$2:$AU$2),0)) -> 0.2 | Q6: =IF(COUNT($AH6:$AU6)=0,"",MAX($AH6:$AU6)) -> 46267 | R6: =IF($Q6="","",TODAY()-$Q6) -> 58 | S6: =IF($G6="","",IF($Q6="","No Record",IF(OR($P6>=1,$C6="Live"),"Live",IF($R6>=90,"Stalled 90d+",IF($R6>=60,"Stalled 60d+",IF($R6>=30,"Stalled 30d+","In Progress")))))) -> Stalled 30d+ | T6: =IF(COUNT($AH6:$AU6)=0,"",LOOKUP(2,1/($AH6:$AU6<>""),{"① 파이프라인 시작 · Pipeline Start","② 제안·소개 발송 · Proposal Sent","③ NDA 발송 · NDA Sent","④ NDA 체결 · NDA Signed","⑤ 계약 체결 · Contract Signed","⑥ SLA 확정 · SLA Finalized","⑦ 개발 착수 예정 · Kickoff Planned","⑧ 개발 착수 · SPEC/DEV 키 · 크리덴셜 · Kickoff / Credential","⑨ 인증 · Certification","⑩ 라이브 테스트 · Live Test","⑪ 개발 완료 예정 · Dev Complete Planned","⑫ 라이브 키 오픈 (OMH 측) · Live Key Open","⑬ 첫 예약 · First Booking","⑭ 고객 라이브 확정 (고객 통보) · Customer Live"})) -> ④ NDA 체결 · NDA Signed | U6: =IF(COUNT($AH6:$AU6)=0,"",IF(N($P6)>=1,MAX($AH6:$AU6),TODAY())-MIN($AH6:$AU6)) -> 58 | V6: =IF($G6="","",COUNTIF('Chase Log'!$B$4:$B$2000,$G6)) -> 3 | W6: =IF(N($V6)=0,"",_xlfn.MAXIFS('Chase Log'!$E$4:$E$2000,'Chase Log'!$B$4:$B$2000,$G6)) -> 46321 | X6: =IF($W6="","",TODAY()-$W6) -> 4 | Y6: =IF($W6="","",IF(OR(AND($Q6<>"",N($Q6)>N($W6)),COUNTIFS('Chase Log'!$B$4:$B$2000,$G6,'Chase Log'!$E$4:$E$2000,$W6,'Chase Log'!$I$4:$I$2000,"Y")>0),"",IF(_xlfn.MAXIFS('Chase Log'!$J$4:$J$2000,'Chase Log'!$B$4:$B$2000,$G6,'Chase Log'!$E$4:$E$2000,$W6)=0,"",_xlfn.MAXIFS('Chase Log'!$J$4:$J$2000,'Chase Log'!$B$4:$B$2000,$G6,'Chase Log'!$E$4:$E$2000,$W6)))) -> 46328 | Z6: =IF(OR($G6="",N($P6)>=1,$C6="Live",$D6<>""),"",IF(AND($Y6<>"",N($Y6)>0),IF($Y6<TODAY(),"Chase Overdue","Scheduled"),IF(AND($Q6<>"",N($R6)>='안내 Guide'!$D$4,OR($X6="",N($X6)>='안내 Guide'!$D$4)),"Chase Needed",""))) -> Scheduled | AC6: Shiji 경유 양방향 연동 개발 일정 확정(Ella↔상대 기술팀) 결과 확인 | AD6: Confirm outcome of finalizing the development schedule for two-way integration via Shiji (Ella ↔ partner's tech team) | AF6: 2026-09-19 | AG6: Tracker · TGX 불가 → Shiji 전환 · TGX not possible, moved to Shiji | AK6: 46267
A7: =IF($G7="","",ROW()-4) -> 3 | B7: =IF($G7="","",IF($C7<>"",$C7,IF($Q7="","Contact",IF($P7>=1,"Live",IF($P7>=0.8,"Pending Live",IF($P7>=0.7,"Testing",IF($P7>=0.45,"In Development",IF($P7>=0.2,"NDA/Contract","Pipeline")))))))) -> NDA/Contract | E7: 인도 · India | F7: India | G7: Volt | H7: 공급 · OMH → Partner | I7: TGX 또는 ZentrumHub · TGX or ZentrumHub | J7: TGX Switching | K7: Mid | L7: 계약 협상 중 · Contract talks | M7: Aiden (지역 공백 · interim) | N7: OHMY + Partner (50/50) | O7: GSM | P7: =IF($G7="","",IFERROR(LOOKUP(2,1/($AH7:$AU7<>""),$AH$2:$AU$2),0)) -> 0.2 | Q7: =IF(COUNT($AH7:$AU7)=0,"",MAX($AH7:$AU7)) -> 46267 | R7: =IF($Q7="","",TODAY()-$Q7) -> 58 | S7: =IF($G7="","",IF($Q7="","No Record",IF(OR($P7>=1,$C7="Live"),"Live",IF($R7>=90,"Stalled 90d+",IF($R7>=60,"Stalled 60d+",IF($R7>=30,"Stalled 30d+","In Progress")))))) -> Stalled 30d+ | T7: =IF(COUNT($AH7:$AU7)=0,"",LOOKUP(2,1/($AH7:$AU7<>""),{"① 파이프라인 시작 · Pipeline Start","② 제안·소개 발송 · Proposal Sent","③ NDA 발송 · NDA Sent","④ NDA 체결 · NDA Signed","⑤ 계약 체결 · Contract Signed","⑥ SLA 확정 · SLA Finalized","⑦ 개발 착수 예정 · Kickoff Planned","⑧ 개발 착수 · SPEC/DEV 키 · 크리덴셜 · Kickoff / Credential","⑨ 인증 · Certification","⑩ 라이브 테스트 · Live Test","⑪ 개발 완료 예정 · Dev Complete Planned","⑫ 라이브 키 오픈 (OMH 측) · Live Key Open","⑬ 첫 예약 · First Booking","⑭ 고객 라이브 확정 (고객 통보) · Customer Live"})) -> ④ NDA 체결 · NDA Signed | U7: =IF(COUNT($AH7:$AU7)=0,"",IF(N($P7)>=1,MAX($AH7:$AU7),TODAY())-MIN($AH7:$AU7)) -> 58 | V7: =IF($G7="","",COUNTIF('Chase Log'!$B$4:$B$2000,$G7)) -> 1 | W7: =IF(N($V7)=0,"",_xlfn.MAXIFS('Chase Log'!$E$4:$E$2000,'Chase Log'!$B$4:$B$2000,$G7)) -> 46300 | X7: =IF($W7="","",TODAY()-$W7) -> 25 | Y7: =IF($W7="","",IF(OR(AND($Q7<>"",N($Q7)>N($W7)),COUNTIFS('Chase Log'!$B$4:$B$2000,$G7,'Chase Log'!$E$4:$E$2000,$W7,'Chase Log'!$I$4:$I$2000,"Y")>0),"",IF(_xlfn.MAXIFS('Chase Log'!$J$4:$J$2000,'Chase Log'!$B$4:$B$2000,$G7,'Chase Log'!$E$4:$E$2000,$W7)=0,"",_xlfn.MAXIFS('Chase Log'!$J$4:$J$2000,'Chase Log'!$B$4:$B$2000,$G7,'Chase Log'!$E$4:$E$2000,$W7)))) | Z7: =IF(OR($G7="",N($P7)>=1,$C7="Live",$D7<>""),"",IF(AND($Y7<>"",N($Y7)>0),IF($Y7<TODAY(),"Chase Overdue","Scheduled"),IF(AND($Q7<>"",N($R7)>='안내 Guide'!$D$4,OR($X7="",N($X7)>='안내 Guide'!$D$4)),"Chase Needed",""))) -> Chase Needed | AC7: 10/18 발송한 Buyer SLA 조정점에 대한 최종 양자 SLA·TTG 버전·준거법 회신 체이스 + ITB Asia 미팅 요청 회신(부스 B108 안내) → 무응답 지속 시 TGX Buyer 계약을 Welcomebeds로 전환 판단 | AD7: Chase reply on final bilateral SLA, TTG version and governing law following the Buyer SLA adjustments sent 18 Oct + reply to ITB Asia meeting request (point to booth B108) → if still no response, decide whether to switch the TGX Buyer contract to Welcomebeds | AF7: 2026-10-18 | AG7: Tracker | AK7: 46267
A8: =IF($G8="","",ROW()-4) -> 4 | B8: =IF($G8="","",IF($C8<>"",$C8,IF($Q8="","Contact",IF($P8>=1,"Live",IF($P8>=0.8,"Pending Live",IF($P8>=0.7,"Testing",IF($P8>=0.45,"In Development",IF($P8>=0.2,"NDA/Contract","Pipeline")))))))) -> Contact | E8: 일본 · Japan | F8: Japan | G8: Miki | H8: 미확인 · Unconfirmed | I8: TGX | J8: TGX Switching | K8: Mid | L8: 신규 개발 · New lead | M8: Aiden (일본 · interim JP) | N8: OHMY + Partner (50/50) | O8: GSM | P8: =IF($G8="","",IFERROR(LOOKUP(2,1/($AH8:$AU8<>""),$AH$2:$AU$2),0)) -> 0 | Q8: =IF(COUNT($AH8:$AU8)=0,"",MAX($AH8:$AU8)) | R8: =IF($Q8="","",TODAY()-$Q8) | S8: =IF($G8="","",IF($Q8="","No Record",IF(OR($P8>=1,$C8="Live"),"Live",IF($R8>=90,"Stalled 90d+",IF($R8>=60,"Stalled 60d+",IF($R8>=30,"Stalled 30d+","In Progress")))))) -> No Record | T8: =IF(COUNT($AH8:$AU8)=0,"",LOOKUP(2,1/($AH8:$AU8<>""),{"① 파이프라인 시작 · Pipeline Start","② 제안·소개 발송 · Proposal Sent","③ NDA 발송 · NDA Sent","④ NDA 체결 · NDA Signed","⑤ 계약 체결 · Contract Signed","⑥ SLA 확정 · SLA Finalized","⑦ 개발 착수 예정 · Kickoff Planned","⑧ 개발 착수 · SPEC/DEV 키 · 크리덴셜 · Kickoff / Credential","⑨ 인증 · Certification","⑩ 라이브 테스트 · Live Test","⑪ 개발 완료 예정 · Dev Complete Planned","⑫ 라이브 키 오픈 (OMH 측) · Live Key Open","⑬ 첫 예약 · First Booking","⑭ 고객 라이브 확정 (고객 통보) · Customer Live"})) | U8: =IF(COUNT($AH8:$AU8)=0,"",IF(N($P8)>=1,MAX($AH8:$AU8),TODAY())-MIN($AH8:$AU8)) | V8: =IF($G8="","",COUNTIF('Chase Log'!$B$4:$B$2000,$G8)) -> 0 | W8: =IF(N($V8)=0,"",_xlfn.MAXIFS('Chase Log'!$E$4:$E$2000,'Chase Log'!$B$4:$B$2000,$G8)) | X8: =IF($W8="","",TODAY()-$W8) | Y8: =IF($W8="","",IF(OR(AND($Q8<>"",N($Q8)>N($W8)),COUNTIFS('Chase Log'!$B$4:$B$2000,$G8,'Chase Log'!$E$4:$E$2000,$W8,'Chase Log'!$I$4:$I$2000,"Y")>0),"",IF(_xlfn.MAXIFS('Chase Log'!$J$4:$J$2000,'Chase Log'!$B$4:$B$2000,$G8,'Chase Log'!$E$4:$E$2000,$W8)=0,"",_xlfn.MAXIFS('Chase Log'!$J$4:$J$2000,'Chase Log'!$B$4:$B$2000,$G8,'Chase Log'!$E$4:$E$2000,$W8)))) | Z8: =IF(OR($G8="",N($P8)>=1,$C8="Live",$D8<>""),"",IF(AND($Y8<>"",N($Y8)>0),IF($Y8<TODAY(),"Chase Overdue","Scheduled"),IF(AND($Q8<>"",N($R8)>='안내 Guide'!$D$4,OR($X8="",N($X8)>='안내 Guide'!$D$4)),"Chase Needed",""))) | AC8: 일본·한국·베트남 톱100 리스트 준비 완료 확인 후 Miki 재체크 시점 회신 대기 | AD8: Confirm Japan/Korea/Vietnam top-100 lists are ready, then await Miki's reply on re-check timing | AF8: 2026-09-16 | AG8: Tracker
A9: =IF($G9="","",ROW()-4) -> 5 | B9: =IF($G9="","",IF($C9<>"",$C9,IF($Q9="","Contact",IF($P9>=1,"Live",IF($P9>=0.8,"Pending Live",IF($P9>=0.7,"Testing",IF($P9>=0.45,"In Development",IF($P9>=0.2,"NDA/Contract","Pipeline")))))))) -> Contact | E9: 동남아 · SE Asia | F9: Singapore | G9: Luxury Tours | H9: 공급 · OMH → Partner | I9: 미정 (TAN vs Shiji·TGX) · TBD (TAN vs Shiji/TGX) | J9: TGX Switching | K9: Mid | L9: 신규 개발 · New lead | M9: Aiden (지역 공백 · interim) | N9: OHMY + Partner (50/50) | O9: GSM | P9: =IF($G9="","",IFERROR(LOOKUP(2,1/($AH9:$AU9<>""),$AH$2:$AU$2),0)) -> 0 | Q9: =IF(COUNT($AH9:$AU9)=0,"",MAX($AH9:$AU9)) | R9: =IF($Q9="","",TODAY()-$Q9) | S9: =IF($G9="","",IF($Q9="","No Record",IF(OR($P9>=1,$C9="Live"),"Live",IF($R9>=90,"Stalled 90d+",IF($R9>=60,"Stalled 60d+",IF($R9>=30,"Stalled 30d+","In Progress")))))) -> No Record | T9: =IF(COUNT($AH9:$AU9)=0,"",LOOKUP(2,1/($AH9:$AU9<>""),{"① 파이프라인 시작 · Pipeline Start","② 제안·소개 발송 · Proposal Sent","③ NDA 발송 · NDA Sent","④ NDA 체결 · NDA Signed","⑤ 계약 체결 · Contract Signed","⑥ SLA 확정 · SLA Finalized","⑦ 개발 착수 예정 · Kickoff Planned","⑧ 개발 착수 · SPEC/DEV 키 · 크리덴셜 · Kickoff / Credential","⑨ 인증 · Certification","⑩ 라이브 테스트 · Live Test","⑪ 개발 완료 예정 · Dev Complete Planned","⑫ 라이브 키 오픈 (OMH 측) · Live Key Open","⑬ 첫 예약 · First Booking","⑭ 고객 라이브 확정 (고객 통보) · Customer Live"})) | U9: =IF(COUNT($AH9:$AU9)=0,"",IF(N($P9)>=1,MAX($AH9:$AU9),TODAY())-MIN($AH9:$AU9)) | V9: =IF($G9="","",COUNTIF('Chase Log'!$B$4:$B$2000,$G9)) -> 4 | W9: =IF(N($V9)=0,"",_xlfn.MAXIFS('Chase Log'!$E$4:$E$2000,'Chase Log'!$B$4:$B$2000,$G9)) -> 46304 | X9: =IF($W9="","",TODAY()-$W9) -> 21 | Y9: =IF($W9="","",IF(OR(AND($Q9<>"",N($Q9)>N($W9)),COUNTIFS('Chase Log'!$B$4:$B$2000,$G9,'Chase Log'!$E$4:$E$2000,$W9,'Chase Log'!$I$4:$I$2000,"Y")>0),"",IF(_xlfn.MAXIFS('Chase Log'!$J$4:$J$2000,'Chase Log'!$B$4:$B$2000,$G9,'Chase Log'!$E$4:$E$2000,$W9)=0,"",_xlfn.MAXIFS('Chase Log'!$J$4:$J$2000,'Chase Log'!$B$4:$B$2000,$G9,'Chase Log'!$E$4:$E$2000,$W9)))) -> 46311 | Z9: =IF(OR($G9="",N($P9)>=1,$C9="Live",$D9<>""),"",IF(AND($Y9<>"",N($Y9)>0),IF($Y9<TODAY(),"Chase Overdue","Scheduled"),IF(AND($Q9<>"",N($R9)>='안내 Guide'!$D$4,OR($X9="",N($X9)>='안내 Guide'!$D$4)),"Chase Needed",""))) -> Chase Overdue | AC9: ITB Asia(10/21–23) 현장 미팅 — 양방향 스코프·연동 경로(TAN vs SHIJI/TGX) 확정 | AD9: On-site meeting at ITB Asia (21–23 Oct) — confirm two-way scope and integration route (TAN vs SHIJI/TGX) | AF9: 2026-10-08 | AG9: Tracker
A10: =IF($G10="","",ROW()-4) -> 6 | B10: =IF($G10="","",IF($C10<>"",$C10,IF($Q10="","Contact",IF($P10>=1,"Live",IF($P10>=0.8,"Pending Live",IF($P10>=0.7,"Testing",IF($P10>=0.45,"In Development",IF($P10>=0.2,"NDA/Contract","Pipeline")))))))) -> Contact | E10: 인도 · India | F10: India | G10: Ottila | H10: 양방향 · Two-way | I10: TGX | J10: TGX Switching | K10: High | L10: 계약 협상 중 · Contract talks | M10: GSM: Aiden → Jane (Dec~) | N10: OHMY + Partner (50/50) | O10: GSM | P10: =IF($G10="","",IFERROR(LOOKUP(2,1/($AH10:$AU10<>""),$AH$2:$AU$2),0)) -> 0 | Q10: =IF(COUNT($AH10:$AU10)=0,"",MAX($AH10:$AU10)) | R10: =IF($Q10="","",TODAY()-$Q10) | S10: =IF($G10="","",IF($Q10="","No Record",IF(OR($P10>=1,$C10="Live"),"Live",IF($R10>=90,"Stalled 90d+",IF($R10>=60,"Stalled 60d+",IF($R10>=30,"Stalled 30d+","In Progress")))))) -> No Record | T10: =IF(COUNT($AH10:$AU10)=0,"",LOOKUP(2,1/($AH10:$AU10<>""),{"① 파이프라인 시작 · Pipeline Start","② 제안·소개 발송 · Proposal Sent","③ NDA 발송 · NDA Sent","④ NDA 체결 · NDA Signed","⑤ 계약 체결 · Contract Signed","⑥ SLA 확정 · SLA Finalized","⑦ 개발 착수 예정 · Kickoff Planned","⑧ 개발 착수 · SPEC/DEV 키 · 크리덴셜 · Kickoff / Credential","⑨ 인증 · Certification","⑩ 라이브 테스트 · Live Test","⑪ 개발 완료 예정 · Dev Complete Planned","⑫ 라이브 키 오픈 (OMH 측) · Live Key Open","⑬ 첫 예약 · First Booking","⑭ 고객 라이브 확정 (고객 통보) · Customer Live"})) | U10: =IF(COUNT($AH10:$AU10)=0,"",IF(N($P10)>=1,MAX($AH10:$AU10),TODAY())-MIN($AH10:$AU10)) | V10: =IF($G10="","",COUNTIF('Chase Log'!$B$4:$B$2000,$G10)) -> 0 | W10: =IF(N($V10)=0,"",_xlfn.MAXIFS('Chase Log'!$E$4:$E$2000,'Chase Log'!$B$4:$B$2000,$G10)) | X10: =IF($W10="","",TODAY()-$W10) | Y10: =IF($W10="","",IF(OR(AND($Q10<>"",N($Q10)>N($W10)),COUNTIFS('Chase Log'!$B$4:$B$2000,$G10,'Chase Log'!$E$4:$E$2000,$W10,'Chase Log'!$I$4:$I$2000,"Y")>0),"",IF(_xlfn.MAXIFS('Chase Log'!$J$4:$J$2000,'Chase Log'!$B$4:$B$2000,$G10,'Chase Log'!$E$4:$E$2000,$W10)=0,"",_xlfn.MAXIFS('Chase Log'!$J$4:$J$2000,'Chase Log'!$B$4:$B$2000,$G10,'Chase Log'!$E$4:$E$2000,$W10)))) | Z10: =IF(OR($G10="",N($P10)>=1,$C10="Live",$D10<>""),"",IF(AND($Y10<>"",N($Y10)>0),IF($Y10<TODAY(),"Chase Overdue","Scheduled"),IF(AND($Q10<>"",N($R10)>='안내 Guide'!$D$4,OR($X10="",N($X10)>='안내 Guide'!$D$4)),"Chase Needed",""))) | AC10: 계약서 v1 회신 체이스(2주+ 무응답, 기한 10/13 경과) | AD10: Chase reply on contract v1 (no response 2+ weeks; due 13 Oct passed) | AF10: 2026-09-29 | AG10: Tracker · CRM상 계약 단계 — 단계 날짜 입력 필요 · contract stage per CRM, stage dates missing
A11: =IF($G11="","",ROW()-4) -> 7 | B11: =IF($G11="","",IF($C11<>"",$C11,IF($Q11="","Contact",IF($P11>=1,"Live",IF($P11>=0.8,"Pending Live",IF($P11>=0.7,"Testing",IF($P11>=0.45,"In Development",IF($P11>=0.2,"NDA/Contract","Pipeline")))))))) -> Contact | E11: 중동·러시아 · ME & Russia | F11: UAE | G11: IOL | H11: 미확인 · Unconfirmed | I11: TGX | J11: Switching System | K11: Low | L11: — | M11: Aiden (지역 공백 · interim) | N11: OHMY + Partner (50/50) | O11: GSM | P11: =IF($G11="","",IFERROR(LOOKUP(2,1/($AH11:$AU11<>""),$AH$2:$AU$2),0)) -> 0 | Q11: =IF(COUNT($AH11:$AU11)=0,"",MAX($AH11:$AU11)) | R11: =IF($Q11="","",TODAY()-$Q11) | S11: =IF($G11="","",IF($Q11="","No Record",IF(OR($P11>=1,$C11="Live"),"Live",IF($R11>=90,"Stalled 90d+",IF($R11>=60,"Stalled 60d+",IF($R11>=30,"Stalled 30d+","In Progress")))))) -> No Record | T11: =IF(COUNT($AH11:$AU11)=0,"",LOOKUP(2,1/($AH11:$AU11<>""),{"① 파이프라인 시작 · Pipeline Start","② 제안·소개 발송 · Proposal Sent","③ NDA 발송 · NDA Sent","④ NDA 체결 · NDA Signed","⑤ 계약 체결 · Contract Signed","⑥ SLA 확정 · SLA Finalized","⑦ 개발 착수 예정 · Kickoff Planned","⑧ 개발 착수 · SPEC/DEV 키 · 크리덴셜 · Kickoff / Credential","⑨ 인증 · Certification","⑩ 라이브 테스트 · Live Test","⑪ 개발 완료 예정 · Dev Complete Planned","⑫ 라이브 키 오픈 (OMH 측) · Live Key Open","⑬ 첫 예약 · First Booking","⑭ 고객 라이브 확정 (고객 통보) · Customer Live"})) | U11: =IF(COUNT($AH11:$AU11)=0,"",IF(N($P11)>=1,MAX($AH11:$AU11),TODAY())-MIN($AH11:$AU11)) | V11: =IF($G11="","",COUNTIF('Chase Log'!$B$4:$B$2000,$G11)) -> 0 | W11: =IF(N($V11)=0,"",_xlfn.MAXIFS('Chase Log'!$E$4:$E$2000,'Chase Log'!$B$4:$B$2000,$G11)) | X11: =IF($W11="","",TODAY()-$W11) | Y11: =IF($W11="","",IF(OR(AND($Q11<>"",N($Q11)>N($W11)),COUNTIFS('Chase Log'!$B$4:$B$2000,$G11,'Chase Log'!$E$4:$E$2000,$W11,'Chase Log'!$I$4:$I$2000,"Y")>0),"",IF(_xlfn.MAXIFS('Chase Log'!$J$4:$J$2000,'Chase Log'!$B$4:$B$2000,$G11,'Chase Log'!$E$4:$E$2000,$W11)=0,"",_xlfn.MAXIFS('Chase Log'!$J$4:$J$2000,'Chase Log'!$B$4:$B$2000,$G11,'Chase Log'!$E$4:$E$2000,$W11)))) | Z11: =IF(OR($G11="",N($P11)>=1,$C11="Live",$D11<>""),"",IF(AND($Y11<>"",N($Y11)>0),IF($Y11<TODAY(),"Chase Overdue","Scheduled"),IF(AND($Q11<>"",N($R11)>='안내 Guide'!$D$4,OR($X11="",N($X11)>='안내 Guide'!$D$4)),"Chase Needed",""))) | AG11: Tracker
A12: =IF($G12="","",ROW()-4) -> 8 | B12: =IF($G12="","",IF($C12<>"",$C12,IF($Q12="","Contact",IF($P12>=1,"Live",IF($P12>=0.8,"Pending Live",IF($P12>=0.7,"Testing",IF($P12>=0.45,"In Development",IF($P12>=0.2,"NDA/Contract","Pipeline")))))))) -> Contact | E12: 유럽·미주 · Europe & Americas | F12: Spain | G12: HBX | H12: 양방향 · Two-way | I12: TGX | J12: Channel API | K12: High | L12: 계약 협상 중 · Contract talks | M12: GSM: Aiden → Jane (Dec~) | N12: OHMY | O12: GSM | P12: =IF($G12="","",IFERROR(LOOKUP(2,1/($AH12:$AU12<>""),$AH$2:$AU$2),0)) -> 0 | Q12: =IF(COUNT($AH12:$AU12)=0,"",MAX($AH12:$AU12)) | R12: =IF($Q12="","",TODAY()-$Q12) | S12: =IF($G12="","",IF($Q12="","No Record",IF(OR($P12>=1,$C12="Live"),"Live",IF($R12>=90,"Stalled 90d+",IF($R12>=60,"Stalled 60d+",IF($R12>=30,"Stalled 30d+","In Progress")))))) -> No Record | T12: =IF(COUNT($AH12:$AU12)=0,"",LOOKUP(2,1/($AH12:$AU12<>""),{"① 파이프라인 시작 · Pipeline Start","② 제안·소개 발송 · Proposal Sent","③ NDA 발송 · NDA Sent","④ NDA 체결 · NDA Signed","⑤ 계약 체결 · Contract Signed","⑥ SLA 확정 · SLA Finalized","⑦ 개발 착수 예정 · Kickoff Planned","⑧ 개발 착수 · SPEC/DEV 키 · 크리덴셜 · Kickoff / Credential","⑨ 인증 · Certification","⑩ 라이브 테스트 · Live Test","⑪ 개발 완료 예정 · Dev Complete Planned","⑫ 라이브 키 오픈 (OMH 측) · Live Key Open","⑬ 첫 예약 · First Booking","⑭ 고객 라이브 확정 (고객 통보) · Customer Live"})) | U12: =IF(COUNT($AH12:$AU12)=0,"",IF(N($P12)>=1,MAX($AH12:$AU12),TODAY())-MIN($AH12:$AU12)) | V12: =IF($G12="","",COUNTIF('Chase Log'!$B$4:$B$2000,$G12)) -> 0 | W12: =IF(N($V12)=0,"",_xlfn.MAXIFS('Chase Log'!$E$4:$E$2000,'Chase Log'!$B$4:$B$2000,$G12)) | X12: =IF($W12="","",TODAY()-$W12) | Y12: =IF($W12="","",IF(OR(AND($Q12<>"",N($Q12)>N($W12)),COUNTIFS('Chase Log'!$B$4:$B$2000,$G12,'Chase Log'!$E$4:$E$2000,$W12,'Chase Log'!$I$4:$I$2000,"Y")>0),"",IF(_xlfn.MAXIFS('Chase Log'!$J$4:$J$2000,'Chase Log'!$B$4:$B$2000,$G12,'Chase Log'!$E$4:$E$2000,$W12)=0,"",_xlfn.MAXIFS('Chase Log'!$J$4:$J$2000,'Chase Log'!$B$4:$B$2000,$G12,'Chase Log'!$E$4:$E$2000,$W12)))) | Z12: =IF(OR($G12="",N($P12)>=1,$C12="Live",$D12<>""),"",IF(AND($Y12<>"",N($Y12)>0),IF($Y12<TODAY(),"Chase Overdue","Scheduled"),IF(AND($Q12<>"",N($R12)>='안내 Guide'!$D$4,OR($X12="",N($X12)>='안내 Guide'!$D$4)),"Chase Needed",""))) | AC12: 재무 실사 결과 재체이스(다른 담당자 CC) — 10/13 발송 여부 확인 후 미발송이면 즉시 발송 | AD12: Chase financial due diligence result again (CC another contact) — check whether it was sent on 13 Oct; if not, send immediately | AF12: 2026-09-23 | AG12: Tracker
A13: =IF($G13="","",ROW()-4) -> 9 | B13: =IF($G13="","",IF($C13<>"",$C13,IF($Q13="","Contact",IF($P13>=1,"Live",IF($P13>=0.8,"Pending Live",IF($P13>=0.7,"Testing",IF($P13>=0.45,"In Development",IF($P13>=0.2,"NDA/Contract","Pipeline")))))))) -> Contact | E13: 유럽·미주 · Europe & Americas | F13: Spain | G13: Restel Hotels | H13: 양방향 · Two-way | I13: TGX 양방향 · TGX two-way | J13: TGX Switching | K13: High | L13: 계약 협상 중 · Contract talks | M13: GSM: Aiden → Jane (Dec~) | N13: OHMY + Partner (50/50) | O13: GSM | P13: =IF($G13="","",IFERROR(LOOKUP(2,1/($AH13:$AU13<>""),$AH$2:$AU$2),0)) -> 0 | Q13: =IF(COUNT($AH13:$AU13)=0,"",MAX($AH13:$AU13)) | R13: =IF($Q13="","",TODAY()-$Q13) | S13: =IF($G13="","",IF($Q13="","No Record",IF(OR($P13>=1,$C13="Live"),"Live",IF($R13>=90,"Stalled 90d+",IF($R13>=60,"Stalled 60d+",IF($R13>=30,"Stalled 30d+","In Progress")))))) -> No Record | T13: =IF(COUNT($AH13:$AU13)=0,"",LOOKUP(2,1/($AH13:$AU13<>""),{"① 파이프라인 시작 · Pipeline Start","② 제안·소개 발송 · Proposal Sent","③ NDA 발송 · NDA Sent","④ NDA 체결 · NDA Signed","⑤ 계약 체결 · Contract Signed","⑥ SLA 확정 · SLA Finalized","⑦ 개발 착수 예정 · Kickoff Planned","⑧ 개발 착수 · SPEC/DEV 키 · 크리덴셜 · Kickoff / Credential","⑨ 인증 · Certification","⑩ 라이브 테스트 · Live Test","⑪ 개발 완료 예정 · Dev Complete Planned","⑫ 라이브 키 오픈 (OMH 측) · Live Key Open","⑬ 첫 예약 · First Booking","⑭ 고객 라이브 확정 (고객 통보) · Customer Live"})) | U13: =IF(COUNT($AH13:$AU13)=0,"",IF(N($P13)>=1,MAX($AH13:$AU13),TODAY())-MIN($AH13:$AU13)) | V13: =IF($G13="","",COUNTIF('Chase Log'!$B$4:$B$2000,$G13)) -> 1 | W13: =IF(N($V13)=0,"",_xlfn.MAXIFS('Chase Log'!$E$4:$E$2000,'Chase Log'!$B$4:$B$2000,$G13)) -> 46323 | X13: =IF($W13="","",TODAY()-$W13) -> 2 | Y13: =IF($W13="","",IF(OR(AND($Q13<>"",N($Q13)>N($W13)),COUNTIFS('Chase Log'!$B$4:$B$2000,$G13,'Chase Log'!$E$4:$E$2000,$W13,'Chase Log'!$I$4:$I$2000,"Y")>0),"",IF(_xlfn.MAXIFS('Chase Log'!$J$4:$J$2000,'Chase Log'!$B$4:$B$2000,$G13,'Chase Log'!$E$4:$E$2000,$W13)=0,"",_xlfn.MAXIFS('Chase Log'!$J$4:$J$2000,'Chase Log'!$B$4:$B$2000,$G13,'Chase Log'!$E$4:$E$2000,$W13)))) -> 46330 | Z13: =IF(OR($G13="",N($P13)>=1,$C13="Live",$D13<>""),"",IF(AND($Y13<>"",N($Y13)>0),IF($Y13<TODAY(),"Chase Overdue","Scheduled"),IF(AND($Q13<>"",N($R13)>='안내 Guide'!$D$4,OR($X13="",N($X13)>='안내 Guide'!$D$4)),"Chase Needed",""))) -> Scheduled | AC13: SG 법인 수정 계약서 검토 후 ITB Asia 10/22 11:00(Kai Wei) 미팅에서 서명 일정 합의 + Jihee 11월 방한 미팅·트래블쇼 시즌2 회신 | AD13: Review revised contract for SG entity, then agree signing date at ITB Asia meeting 22 Oct 11:00 (Kai Wei) + reply to Jihee on November Korea-visit meeting and Travel Show Season 2 | AF13: 2026-10-14 | AG13: Tracker · CRM상 계약 단계 — 단계 날짜 입력 필요 · contract stage per CRM, stage dates missing
A14: =IF($G14="","",ROW()-4) -> 10 | B14: =IF($G14="","",IF($C14<>"",$C14,IF($Q14="","Contact",IF($P14>=1,"Live",IF($P14>=0.8,"Pending Live",IF($P14>=0.7,"Testing",IF($P14>=0.45,"In Development",IF($P14>=0.2,"NDA/Contract","Pipeline")))))))) -> Contact | E14: 유럽·미주 · Europe & Americas | F14: Spain | G14: Veturis | H14: 양방향 · Two-way | I14: Shiji | J14: SHIJI Switching | K14: Mid | L14: 계약 협상 중 · Contract talks | M14: GSM: Aiden → Jane (Dec~) | N14: OHMY + Partner (50/50) | O14: GSM | P14: =IF($G14="","",IFERROR(LOOKUP(2,1/($AH14:$AU14<>""),$AH$2:$AU$2),0)) -> 0 | Q14: =IF(COUNT($AH14:$AU14)=0,"",MAX($AH14:$AU14)) | R14: =IF($Q14="","",TODAY()-$Q14) | S14: =IF($G14="","",IF($Q14="","No Record",IF(OR($P14>=1,$C14="Live"),"Live",IF($R14>=90,"Stalled 90d+",IF($R14>=60,"Stalled 60d+",IF($R14>=30,"Stalled 30d+","In Progress")))))) -> No Record | T14: =IF(COUNT($AH14:$AU14)=0,"",LOOKUP(2,1/($AH14:$AU14<>""),{"① 파이프라인 시작 · Pipeline Start","② 제안·소개 발송 · Proposal Sent","③ NDA 발송 · NDA Sent","④ NDA 체결 · NDA Signed","⑤ 계약 체결 · Contract Signed","⑥ SLA 확정 · SLA Finalized","⑦ 개발 착수 예정 · Kickoff Planned","⑧ 개발 착수 · SPEC/DEV 키 · 크리덴셜 · Kickoff / Credential","⑨ 인증 · Certification","⑩ 라이브 테스트 · Live Test","⑪ 개발 완료 예정 · Dev Complete Planned","⑫ 라이브 키 오픈 (OMH 측) · Live Key Open","⑬ 첫 예약 · First Booking","⑭ 고객 라이브 확정 (고객 통보) · Customer Live"})) | U14: =IF(COUNT($AH14:$AU14)=0,"",IF(N($P14)>=1,MAX($AH14:$AU14),TODAY())-MIN($AH14:$AU14)) | V14: =IF($G14="","",COUNTIF('Chase Log'!$B$4:$B$2000,$G14)) -> 5 | W14: =IF(N($V14)=0,"",_xlfn.MAXIFS('Chase Log'!$E$4:$E$2000,'Chase Log'!$B$4:$B$2000,$G14)) -> 46325 | X14: =IF($W14="","",TODAY()-$W14) -> 0 | Y14: =IF($W14="","",IF(OR(AND($Q14<>"",N($Q14)>N($W14)),COUNTIFS('Chase Log'!$B$4:$B$2000,$G14,'Chase Log'!$E$4:$E$2000,$W14,'Chase Log'!$I$4:$I$2000,"Y")>0),"",IF(_xlfn.MAXIFS('Chase Log'!$J$4:$J$2000,'Chase Log'!$B$4:$B$2000,$G14,'Chase Log'!$E$4:$E$2000,$W14)=0,"",_xlfn.MAXIFS('Chase Log'!$J$4:$J$2000,'Chase Log'!$B$4:$B$2000,$G14,'Chase Log'!$E$4:$E$2000,$W14)))) -> 46332 | Z14: =IF(OR($G14="",N($P14)>=1,$C14="Live",$D14<>""),"",IF(AND($Y14<>"",N($Y14)>0),IF($Y14<TODAY(),"Chase Overdue","Scheduled"),IF(AND($Q14<>"",N($R14)>='안내 Guide'!$D$4,OR($X14="",N($X14)>='안내 Guide'!$D$4)),"Chase Needed",""))) -> Scheduled | AC14: 크로스셀 계약 초안 v4 발송(우리 차례) + 단체 견적 C261117(11/17~20 도쿄)·JO270314S 회신(Vicky 경유 JP팀) | AD14: Send cross-sell contract draft v4 (our turn) + reply on group quotes C261117 (17–20 Nov, Tokyo) and JO270314S (JP team via Vicky) | AF14: 2026-10-15 | AG14: Tracker
A15: =IF($G15="","",ROW()-4) -> 11 | B15: =IF($G15="","",IF($C15<>"",$C15,IF($Q15="","Contact",IF($P15>=1,"Live",IF($P15>=0.8,"Pending Live",IF($P15>=0.7,"Testing",IF($P15>=0.45,"In Development",IF($P15>=0.2,"NDA/Contract","Pipeline")))))))) -> Contact | E15: 유럽·미주 · Europe & Americas | F15: Spain | G15: Welcomebeds | H15: 양방향 · Two-way | I15: TGX | J15: 3rd Party Hotel | K15: Mid | L15: 계약 협상 중 · Contract talks | M15: GSM: Aiden → Jane (Dec~) | N15: Partner (client-side) | O15: GSM | P15: =IF($G15="","",IFERROR(LOOKUP(2,1/($AH15:$AU15<>""),$AH$2:$AU$2),0)) -> 0 | Q15: =IF(COUNT($AH15:$AU15)=0,"",MAX($AH15:$AU15)) | R15: =IF($Q15="","",TODAY()-$Q15) | S15: =IF($G15="","",IF($Q15="","No Record",IF(OR($P15>=1,$C15="Live"),"Live",IF($R15>=90,"Stalled 90d+",IF($R15>=60,"Stalled 60d+",IF($R15>=30,"Stalled 30d+","In Progress")))))) -> No Record | T15: =IF(COUNT($AH15:$AU15)=0,"",LOOKUP(2,1/($AH15:$AU15<>""),{"① 파이프라인 시작 · Pipeline Start","② 제안·소개 발송 · Proposal Sent","③ NDA 발송 · NDA Sent","④ NDA 체결 · NDA Signed","⑤ 계약 체결 · Contract Signed","⑥ SLA 확정 · SLA Finalized","⑦ 개발 착수 예정 · Kickoff Planned","⑧ 개발 착수 · SPEC/DEV 키 · 크리덴셜 · Kickoff / Credential","⑨ 인증 · Certification","⑩ 라이브 테스트 · Live Test","⑪ 개발 완료 예정 · Dev Complete Planned","⑫ 라이브 키 오픈 (OMH 측) · Live Key Open","⑬ 첫 예약 · First Booking","⑭ 고객 라이브 확정 (고객 통보) · Customer Live"})) | U15: =IF(COUNT($AH15:$AU15)=0,"",IF(N($P15)>=1,MAX($AH15:$AU15),TODAY())-MIN($AH15:$AU15)) | V15: =IF($G15="","",COUNTIF('Chase Log'!$B$4:$B$2000,$G15)) -> 4 | W15: =IF(N($V15)=0,"",_xlfn.MAXIFS('Chase Log'!$E$4:$E$2000,'Chase Log'!$B$4:$B$2000,$G15)) -> 46323 | X15: =IF($W15="","",TODAY()-$W15) -> 2 | Y15: =IF($W15="","",IF(OR(AND($Q15<>"",N($Q15)>N($W15)),COUNTIFS('Chase Log'!$B$4:$B$2000,$G15,'Chase Log'!$E$4:$E$2000,$W15,'Chase Log'!$I$4:$I$2000,"Y")>0),"",IF(_xlfn.MAXIFS('Chase Log'!$J$4:$J$2000,'Chase Log'!$B$4:$B$2000,$G15,'Chase Log'!$E$4:$E$2000,$W15)=0,"",_xlfn.MAXIFS('Chase Log'!$J$4:$J$2000,'Chase Log'!$B$4:$B$2000,$G15,'Chase Log'!$E$4:$E$2000,$W15)))) -> 46330 | Z15: =IF(OR($G15="",N($P15)>=1,$C15="Live",$D15<>""),"",IF(AND($Y15<>"",N($Y15)>0),IF($Y15<TODAY(),"Chase Overdue","Scheduled"),IF(AND($Q15<>"",N($R15)>='안내 Guide'!$D$4,OR($X15="",N($X15)>='안내 Guide'!$D$4)),"Chase Needed",""))) -> Scheduled | AC15: 계약 법인 결정 후 ITB Asia에서 Nora와 TGX·크레딧 정리 | AD15: Decide contracting entity, then settle TGX and credit with Nora at ITB Asia | AF15: 2026-10-07 | AG15: Tracker
A16: =IF($G16="","",ROW()-4) -> 12 | B16: =IF($G16="","",IF($C16<>"",$C16,IF($Q16="","Contact",IF($P16>=1,"Live",IF($P16>=0.8,"Pending Live",IF($P16>=0.7,"Testing",IF($P16>=0.45,"In Development",IF($P16>=0.2,"NDA/Contract","Pipeline")))))))) -> Contact | E16: 동남아 · SE Asia | F16: Thailand | G16: Asian Trails | H16: 양방향 · Two-way | I16: TGX 단방향 + HotelsTrack · TGX one-way + HotelsTrack | L16: 신규 개발 · New lead | M16: GSM: Aiden → Jane (Dec~) | O16: GSM | P16: =IF($G16="","",IFERROR(LOOKUP(2,1/($AH16:$AU16<>""),$AH$2:$AU$2),0)) -> 0 | Q16: =IF(COUNT($AH16:$AU16)=0,"",MAX($AH16:$AU16)) | R16: =IF($Q16="","",TODAY()-$Q16) | S16: =IF($G16="","",IF($Q16="","No Record",IF(OR($P16>=1,$C16="Live"),"Live",IF($R16>=90,"Stalled 90d+",IF($R16>=60,"Stalled 60d+",IF($R16>=30,"Stalled 30d+","In Progress")))))) -> No Record | T16: =IF(COUNT($AH16:$AU16)=0,"",LOOKUP(2,1/($AH16:$AU16<>""),{"① 파이프라인 시작 · Pipeline Start","② 제안·소개 발송 · Proposal Sent","③ NDA 발송 · NDA Sent","④ NDA 체결 · NDA Signed","⑤ 계약 체결 · Contract Signed","⑥ SLA 확정 · SLA Finalized","⑦ 개발 착수 예정 · Kickoff Planned","⑧ 개발 착수 · SPEC/DEV 키 · 크리덴셜 · Kickoff / Credential","⑨ 인증 · Certification","⑩ 라이브 테스트 · Live Test","⑪ 개발 완료 예정 · Dev Complete Planned","⑫ 라이브 키 오픈 (OMH 측) · Live Key Open","⑬ 첫 예약 · First Booking","⑭ 고객 라이브 확정 (고객 통보) · Customer Live"})) | U16: =IF(COUNT($AH16:$AU16)=0,"",IF(N($P16)>=1,MAX($AH16:$AU16),TODAY())-MIN($AH16:$AU16)) | V16: =IF($G16="","",COUNTIF('Chase Log'!$B$4:$B$2000,$G16)) -> 1 | W16: =IF(N($V16)=0,"",_xlfn.MAXIFS('Chase Log'!$E$4:$E$2000,'Chase Log'!$B$4:$B$2000,$G16)) -> 46323 | X16: =IF($W16="","",TODAY()-$W16) -> 2 | Y16: =IF($W16="","",IF(OR(AND($Q16<>"",N($Q16)>N($W16)),COUNTIFS('Chase Log'!$B$4:$B$2000,$G16,'Chase Log'!$E$4:$E$2000,$W16,'Chase Log'!$I$4:$I$2000,"Y")>0),"",IF(_xlfn.MAXIFS('Chase Log'!$J$4:$J$2000,'Chase Log'!$B$4:$B$2000,$G16,'Chase Log'!$E$4:$E$2000,$W16)=0,"",_xlfn.MAXIFS('Chase Log'!$J$4:$J$2000,'Chase Log'!$B$4:$B$2000,$G16,'Chase Log'!$E$4:$E$2000,$W16)))) -> 46330 | Z16: =IF(OR($G16="",N($P16)>=1,$C16="Live",$D16<>""),"",IF(AND($Y16<>"",N($Y16)>0),IF($Y16<TODAY(),"Chase Overdue","Scheduled"),IF(AND($Q16<>"",N($R16)>='안내 Guide'!$D$4,OR($X16="",N($X16)>='안내 Guide'!$D$4)),"Chase Needed",""))) -> Scheduled | AC16: ITB Asia 10/21 13:30 Virat 미팅 + HotelsTrack(Edwin) 미팅 일정 확정 | AD16: ITB Asia meeting with Virat 21 Oct 13:30 + confirm meeting date with HotelsTrack (Edwin) | AF16: 2026-09-23 | AG16: CRM 추가 · Added from CRM (Tracker 미등록 · not in Tracker; 단계 날짜는 확인되는 대로 입력 · add stage dates when confirmed)
A17: =IF($G17="","",ROW()-4) -> 13 | B17: =IF($G17="","",IF($C17<>"",$C17,IF($Q17="","Contact",IF($P17>=1,"Live",IF($P17>=0.8,"Pending Live",IF($P17>=0.7,"Testing",IF($P17>=0.45,"In Development",IF($P17>=0.2,"NDA/Contract","Pipeline")))))))) -> Contact | E17: 인도 · India | F17: India | G17: Rezlive | H17: 양방향 · Two-way | I17: TGX 등 대안 · TGX or other switch | L17: 재가동 대상 · Re-engage | M17: GSM: Aiden → Jane (Dec~) | O17: GSM | P17: =IF($G17="","",IFERROR(LOOKUP(2,1/($AH17:$AU17<>""),$AH$2:$AU$2),0)) -> 0 | Q17: =IF(COUNT($AH17:$AU17)=0,"",MAX($AH17:$AU17)) | R17: =IF($Q17="","",TODAY()-$Q17) | S17: =IF($G17="","",IF($Q17="","No Record",IF(OR($P17>=1,$C17="Live"),"Live",IF($R17>=90,"Stalled 90d+",IF($R17>=60,"Stalled 60d+",IF($R17>=30,"Stalled 30d+","In Progress")))))) -> No Record | T17: =IF(COUNT($AH17:$AU17)=0,"",LOOKUP(2,1/($AH17:$AU17<>""),{"① 파이프라인 시작 · Pipeline Start","② 제안·소개 발송 · Proposal Sent","③ NDA 발송 · NDA Sent","④ NDA 체결 · NDA Signed","⑤ 계약 체결 · Contract Signed","⑥ SLA 확정 · SLA Finalized","⑦ 개발 착수 예정 · Kickoff Planned","⑧ 개발 착수 · SPEC/DEV 키 · 크리덴셜 · Kickoff / Credential","⑨ 인증 · Certification","⑩ 라이브 테스트 · Live Test","⑪ 개발 완료 예정 · Dev Complete Planned","⑫ 라이브 키 오픈 (OMH 측) · Live Key Open","⑬ 첫 예약 · First Booking","⑭ 고객 라이브 확정 (고객 통보) · Customer Live"})) | U17: =IF(COUNT($AH17:$AU17)=0,"",IF(N($P17)>=1,MAX($AH17:$AU17),TODAY())-MIN($AH17:$AU17)) | V17: =IF($G17="","",COUNTIF('Chase Log'!$B$4:$B$2000,$G17)) -> 1 | W17: =IF(N($V17)=0,"",_xlfn.MAXIFS('Chase Log'!$E$4:$E$2000,'Chase Log'!$B$4:$B$2000,$G17)) -> 46300 | X17: =IF($W17="","",TODAY()-$W17) -> 25 | Y17: =IF($W17="","",IF(OR(AND($Q17<>"",N($Q17)>N($W17)),COUNTIFS('Chase Log'!$B$4:$B$2000,$G17,'Chase Log'!$E$4:$E$2000,$W17,'Chase Log'!$I$4:$I$2000,"Y")>0),"",IF(_xlfn.MAXIFS('Chase Log'!$J$4:$J$2000,'Chase Log'!$B$4:$B$2000,$G17,'Chase Log'!$E$4:$E$2000,$W17)=0,"",_xlfn.MAXIFS('Chase Log'!$J$4:$J$2000,'Chase Log'!$B$4:$B$2000,$G17,'Chase Log'!$E$4:$E$2000,$W17)))) -> 46307 | Z17: =IF(OR($G17="",N($P17)>=1,$C17="Live",$D17<>""),"",IF(AND($Y17<>"",N($Y17)>0),IF($Y17<TODAY(),"Chase Overdue","Scheduled"),IF(AND($Q17<>"",N($R17)>='안내 Guide'!$D$4,OR($X17="",N($X17)>='안내 Guide'!$D$4)),"Chase Needed",""))) -> Chase Overdue | AC17: 10/5 재가동 메일 · 10/19 2차 일괄 체이스 | AD17: Re-engagement email 5 Oct · second batch chase 19 Oct | AG17: CRM 추가 · Added from CRM (Tracker 미등록 · not in Tracker; 단계 날짜는 확인되는 대로 입력 · add stage dates when confirmed)
A18: =IF($G18="","",ROW()-4) -> 14 | B18: =IF($G18="","",IF($C18<>"",$C18,IF($Q18="","Contact",IF($P18>=1,"Live",IF($P18>=0.8,"Pending Live",IF($P18>=0.7,"Testing",IF($P18>=0.45,"In Development",IF($P18>=0.2,"NDA/Contract","Pipeline")))))))) -> Contact | E18: 인도 · India | F18: India | G18: Tripjack | H18: 공급 · OMH → Partner | I18: TGX 또는 Shiji · TGX or Shiji | L18: 신규 개발 · New lead | M18: Aiden (지역 공백 · interim) | O18: GSM | P18: =IF($G18="","",IFERROR(LOOKUP(2,1/($AH18:$AU18<>""),$AH$2:$AU$2),0)) -> 0 | Q18: =IF(COUNT($AH18:$AU18)=0,"",MAX($AH18:$AU18)) | R18: =IF($Q18="","",TODAY()-$Q18) | S18: =IF($G18="","",IF($Q18="","No Record",IF(OR($P18>=1,$C18="Live"),"Live",IF($R18>=90,"Stalled 90d+",IF($R18>=60,"Stalled 60d+",IF($R18>=30,"Stalled 30d+","In Progress")))))) -> No Record | T18: =IF(COUNT($AH18:$AU18)=0,"",LOOKUP(2,1/($AH18:$AU18<>""),{"① 파이프라인 시작 · Pipeline Start","② 제안·소개 발송 · Proposal Sent","③ NDA 발송 · NDA Sent","④ NDA 체결 · NDA Signed","⑤ 계약 체결 · Contract Signed","⑥ SLA 확정 · SLA Finalized","⑦ 개발 착수 예정 · Kickoff Planned","⑧ 개발 착수 · SPEC/DEV 키 · 크리덴셜 · Kickoff / Credential","⑨ 인증 · Certification","⑩ 라이브 테스트 · Live Test","⑪ 개발 완료 예정 · Dev Complete Planned","⑫ 라이브 키 오픈 (OMH 측) · Live Key Open","⑬ 첫 예약 · First Booking","⑭ 고객 라이브 확정 (고객 통보) · Customer Live"})) | U18: =IF(COUNT($AH18:$AU18)=0,"",IF(N($P18)>=1,MAX($AH18:$AU18),TODAY())-MIN($AH18:$AU18)) | V18: =IF($G18="","",COUNTIF('Chase Log'!$B$4:$B$2000,$G18)) -> 4 | W18: =IF(N($V18)=0,"",_xlfn.MAXIFS('Chase Log'!$E$4:$E$2000,'Chase Log'!$B$4:$B$2000,$G18)) -> 46324 | X18: =IF($W18="","",TODAY()-$W18) -> 1 | Y18: =IF($W18="","",IF(OR(AND($Q18<>"",N($Q18)>N($W18)),COUNTIFS('Chase Log'!$B$4:$B$2000,$G18,'Chase Log'!$E$4:$E$2000,$W18,'Chase Log'!$I$4:$I$2000,"Y")>0),"",IF(_xlfn.MAXIFS('Chase Log'!$J$4:$J$2000,'Chase Log'!$B$4:$B$2000,$G18,'Chase Log'!$E$4:$E$2000,$W18)=0,"",_xlfn.MAXIFS('Chase Log'!$J$4:$J$2000,'Chase Log'!$B$4:$B$2000,$G18,'Chase Log'!$E$4:$E$2000,$W18)))) -> 46331 | Z18: =IF(OR($G18="",N($P18)>=1,$C18="Live",$D18<>""),"",IF(AND($Y18<>"",N($Y18)>0),IF($Y18<TODAY(),"Chase Overdue","Scheduled"),IF(AND($Q18<>"",N($R18)>='안내 Guide'!$D$4,OR($X18="",N($X18)>='안내 Guide'!$D$4)),"Chase Needed",""))) -> Scheduled | AC18: Anitya 회신 체이스(10/19 2차 일괄) + ITB Asia 미팅(10/22 14:30, Tauseef) | AD18: Chase Anitya's reply (second batch, 19 Oct) + ITB Asia meeting (22 Oct 14:30, Tauseef) | AF18: 2026-10-05 | AG18: CRM 추가 · Added from CRM (Tracker 미등록 · not in Tracker; 단계 날짜는 확인되는 대로 입력 · add stage dates when confirmed)
A19: =IF($G19="","",ROW()-4) -> 15 | B19: =IF($G19="","",IF($C19<>"",$C19,IF($Q19="","Contact",IF($P19>=1,"Live",IF($P19>=0.8,"Pending Live",IF($P19>=0.7,"Testing",IF($P19>=0.45,"In Development",IF($P19>=0.2,"NDA/Contract","Pipeline")))))))) -> Contact | E19: 중동·러시아 · ME & Russia | F19: UAE | G19: Yalago | H19: 양방향 · Two-way | I19: TGX (양방향 제안) · TGX (two-way proposed) | L19: 신규 개발 · New lead | M19: GSM: Aiden → Jane (Dec~) | O19: GSM | P19: =IF($G19="","",IFERROR(LOOKUP(2,1/($AH19:$AU19<>""),$AH$2:$AU$2),0)) -> 0 | Q19: =IF(COUNT($AH19:$AU19)=0,"",MAX($AH19:$AU19)) | R19: =IF($Q19="","",TODAY()-$Q19) | S19: =IF($G19="","",IF($Q19="","No Record",IF(OR($P19>=1,$C19="Live"),"Live",IF($R19>=90,"Stalled 90d+",IF($R19>=60,"Stalled 60d+",IF($R19>=30,"Stalled 30d+","In Progress")))))) -> No Record | T19: =IF(COUNT($AH19:$AU19)=0,"",LOOKUP(2,1/($AH19:$AU19<>""),{"① 파이프라인 시작 · Pipeline Start","② 제안·소개 발송 · Proposal Sent","③ NDA 발송 · NDA Sent","④ NDA 체결 · NDA Signed","⑤ 계약 체결 · Contract Signed","⑥ SLA 확정 · SLA Finalized","⑦ 개발 착수 예정 · Kickoff Planned","⑧ 개발 착수 · SPEC/DEV 키 · 크리덴셜 · Kickoff / Credential","⑨ 인증 · Certification","⑩ 라이브 테스트 · Live Test","⑪ 개발 완료 예정 · Dev Complete Planned","⑫ 라이브 키 오픈 (OMH 측) · Live Key Open","⑬ 첫 예약 · First Booking","⑭ 고객 라이브 확정 (고객 통보) · Customer Live"})) | U19: =IF(COUNT($AH19:$AU19)=0,"",IF(N($P19)>=1,MAX($AH19:$AU19),TODAY())-MIN($AH19:$AU19)) | V19: =IF($G19="","",COUNTIF('Chase Log'!$B$4:$B$2000,$G19)) -> 2 | W19: =IF(N($V19)=0,"",_xlfn.MAXIFS('Chase Log'!$E$4:$E$2000,'Chase Log'!$B$4:$B$2000,$G19)) -> 46302 | X19: =IF($W19="","",TODAY()-$W19) -> 23 | Y19: =IF($W19="","",IF(OR(AND($Q19<>"",N($Q19)>N($W19)),COUNTIFS('Chase Log'!$B$4:$B$2000,$G19,'Chase Log'!$E$4:$E$2000,$W19,'Chase Log'!$I$4:$I$2000,"Y")>0),"",IF(_xlfn.MAXIFS('Chase Log'!$J$4:$J$2000,'Chase Log'!$B$4:$B$2000,$G19,'Chase Log'!$E$4:$E$2000,$W19)=0,"",_xlfn.MAXIFS('Chase Log'!$J$4:$J$2000,'Chase Log'!$B$4:$B$2000,$G19,'Chase Log'!$E$4:$E$2000,$W19)))) -> 46309 | Z19: =IF(OR($G19="",N($P19)>=1,$C19="Live",$D19<>""),"",IF(AND($Y19<>"",N($Y19)>0),IF($Y19<TODAY(),"Chase Overdue","Scheduled"),IF(AND($Q19<>"",N($R19)>='안내 Guide'!$D$4,OR($X19="",N($X19)>='안내 Guide'!$D$4)),"Chase Needed",""))) -> Chase Overdue | AC19: ITB Asia(10/21–23) 현장 미팅으로 TGX 양방향 연동 방향 합의 + Yalago TGX 라이브 여부 확인 | AD19: Agree TGX two-way integration direction at on-site meeting at ITB Asia (21–23 Oct) + confirm whether Yalago is live on TGX | AF19: 2026-10-07 | AG19: CRM 추가 · Added from CRM (Tracker 미등록 · not in Tracker; 단계 날짜는 확인되는 대로 입력 · add stage dates when confirmed)
A20: =IF($G20="","",ROW()-4) -> 16 | B20: =IF($G20="","",IF($C20<>"",$C20,IF($Q20="","Contact",IF($P20>=1,"Live",IF($P20>=0.8,"Pending Live",IF($P20>=0.7,"Testing",IF($P20>=0.45,"In Development",IF($P20>=0.2,"NDA/Contract","Pipeline")))))))) -> Contact | E20: 유럽·미주 · Europe & Americas | F20: Spain | G20: W2M | H20: 양방향 · Two-way | I20: Juniper | L20: 신규 개발 · New lead | M20: GSM: Aiden → Jane (Dec~) | O20: GSM | P20: =IF($G20="","",IFERROR(LOOKUP(2,1/($AH20:$AU20<>""),$AH$2:$AU$2),0)) -> 0 | Q20: =IF(COUNT($AH20:$AU20)=0,"",MAX($AH20:$AU20)) | R20: =IF($Q20="","",TODAY()-$Q20) | S20: =IF($G20="","",IF($Q20="","No Record",IF(OR($P20>=1,$C20="Live"),"Live",IF($R20>=90,"Stalled 90d+",IF($R20>=60,"Stalled 60d+",IF($R20>=30,"Stalled 30d+","In Progress")))))) -> No Record | T20: =IF(COUNT($AH20:$AU20)=0,"",LOOKUP(2,1/($AH20:$AU20<>""),{"① 파이프라인 시작 · Pipeline Start","② 제안·소개 발송 · Proposal Sent","③ NDA 발송 · NDA Sent","④ NDA 체결 · NDA Signed","⑤ 계약 체결 · Contract Signed","⑥ SLA 확정 · SLA Finalized","⑦ 개발 착수 예정 · Kickoff Planned","⑧ 개발 착수 · SPEC/DEV 키 · 크리덴셜 · Kickoff / Credential","⑨ 인증 · Certification","⑩ 라이브 테스트 · Live Test","⑪ 개발 완료 예정 · Dev Complete Planned","⑫ 라이브 키 오픈 (OMH 측) · Live Key Open","⑬ 첫 예약 · First Booking","⑭ 고객 라이브 확정 (고객 통보) · Customer Live"})) | U20: =IF(COUNT($AH20:$AU20)=0,"",IF(N($P20)>=1,MAX($AH20:$AU20),TODAY())-MIN($AH20:$AU20)) | V20: =IF($G20="","",COUNTIF('Chase Log'!$B$4:$B$2000,$G20)) -> 0 | W20: =IF(N($V20)=0,"",_xlfn.MAXIFS('Chase Log'!$E$4:$E$2000,'Chase Log'!$B$4:$B$2000,$G20)) | X20: =IF($W20="","",TODAY()-$W20) | Y20: =IF($W20="","",IF(OR(AND($Q20<>"",N($Q20)>N($W20)),COUNTIFS('Chase Log'!$B$4:$B$2000,$G20,'Chase Log'!$E$4:$E$2000,$W20,'Chase Log'!$I$4:$I$2000,"Y")>0),"",IF(_xlfn.MAXIFS('Chase Log'!$J$4:$J$2000,'Chase Log'!$B$4:$B$2000,$G20,'Chase Log'!$E$4:$E$2000,$W20)=0,"",_xlfn.MAXIFS('Chase Log'!$J$4:$J$2000,'Chase Log'!$B$4:$B$2000,$G20,'Chase Log'!$E$4:$E$2000,$W20)))) | Z20: =IF(OR($G20="",N($P20)>=1,$C20="Live",$D20<>""),"",IF(AND($Y20<>"",N($Y20)>0),IF($Y20<TODAY(),"Chase Overdue","Scheduled"),IF(AND($Q20<>"",N($R20)>='안내 Guide'!$D$4,OR($X20="",N($X20)>='안내 Guide'!$D$4)),"Chase Needed",""))) | AC20: ITB Asia B167 현장에서 TGX↔Juniper 연결 방식 확인 | AD20: Confirm TGX↔Juniper connection method on site at ITB Asia B167 | AF20: 2026-09-28 | AG20: CRM 추가 · Added from CRM (Tracker 미등록 · not in Tracker; 단계 날짜는 확인되는 대로 입력 · add stage dates when confirmed)

Sheet 서드파티 연동 3rd Party
A1: 서드파티 연동 3rd Party | E1: 상대 재고를 OMH가 가져와 파는 연동 (OMH = 매입) We source the partner's inventory and resell it (OMH = buyer)
A2: ="전체 Total "&COUNTA($G$5:$G$399)&" · 라이브 Live "&(COUNTIF($B$5:$B$399,"Live")+COUNTIF($B$5:$B$399,"Partially Live"))&" · 개발·테스트 Dev/Test "&(COUNTIF($B$5:$B$399,"In Development")+COUNTIF($B$5:$B$399,"Testing")+COUNTIF($B$5:$B$399,"Pending Live"))&" · 계약·NDA "&COUNTIF($B$5:$B$399,"NDA/Contract")&" · 파이프라인 Pipeline "&(COUNTIF($B$5:$B$399,"Pipeline")+COUNTIF($B$5:$B$399,"Contact"))&" · 60일+ 정체 Stalled 60d+ "&(COUNTIF($S$5:$S$399,"Stalled 60d+")+COUNTIF($S$5:$S$399,"Stalled 90d+")) -> 전체 Total 4 · 라이브 Live 0 · 개발·테스트 Dev/Test 0 · 계약·NDA 0 · 파이프라인 Pipeline 4 · 60일+ 정체 Stalled 60d+ 0 | AG2: 단계 가중치 · Stage weight → | AH2: 0.05 | AI2: 0.1 | AJ2: 0.15 | AK2: 0.2 | AL2: 0.3 | AM2: 0.4 | AN2: 0.45 | AO2: 0.5 | AP2: 0.6 | AQ2: 0.7 | AR2: 0.75 | AS2: 0.8 | AT2: 0.9 | AU2: 1
A3: 프로젝트 · 개발 정보 · Project / Dev Info | P3: 진행 · 체이스 현황 (자동 계산) · Progress & Chase Status (Auto-calculated) | AA3: 계획 · 이슈 (직접 입력) · Plan & Issues (manual entry) | AH3: 단계 이력 (실제 날짜) · Stage History (actual dates) — Pipeline → Contract → Dev → Customer Live
A4: No. | B4: 상태 Status | C4: 상태 수동 지정 Status override | D4: 보류/드롭 Hold/Drop | E4: 지역 Region | F4: 국가 Country | G4: 프로젝트 (업체) Project (Partner) | H4: 방향 Direction | I4: 연결 경로 Connection | J4: 원본 카테고리 Category (orig.) | K4: 비즈 임팩트 Biz Impact | L4: 영업 단계 (CRM) Sales stage (CRM) | M4: 담당 (현재) Owner (current) | N4: 개발 주체 Dev Owner | O4: 처리 팀 Handling Team | P4: 진행률 Progress % | Q4: 마지막 활동 Last Activity | R4: 단계 경과일 Days in Stage | S4: 지연 체크 Delay Check | T4: 현재 단계 Current Stage | U4: 파이프라인 기간 Pipeline Age | V4: 체이스 # Chase # | W4: 마지막 체이스 Last Chase | X4: 체이스 후 경과일 Days Since Chase | Y4: 다음 체이스 Next Chase Due | Z4: 체이스 알림 Chase Alert | AA4: 목표 라이브 Target Go-Live | AB4: 대기 사유 Waiting On | AC4: 현황 · 다음 액션 (KR) Status · next action (KR) | AD4: 현황 · 다음 액션 (EN) Status · next action (EN) | AE4: 원본 Note (IT) Note (IT original) | AF4: 최종 연락 (CRM) Last contact (CRM) | AG4: 출처 · 메모 Source · memo | AH4: ① 파이프라인 시작 Pipeline Start (5%) | AI4: ② 제안·소개 발송 Proposal / Intro Sent (10%) | AJ4: ③ NDA 발송 NDA Sent (15%) | AK4: ④ NDA 체결 NDA Signed (20%) | AL4: ⑤ 계약 체결 Contract Signed (30%) | AM4: ⑥ SLA 확정 SLA Finalized (40%) | AN4: ⑦ 개발 착수 예정 Dev Kickoff Planned (45%) | AO4: ⑧ 개발 착수 · SPEC/DEV 키 · 크리덴셜 Dev Kickoff / SPEC·DEV Key (50%) / Credential | AP4: ⑨ 인증 Certification (60%) | AQ4: ⑩ 라이브 테스트 Live Test (70%) | AR4: ⑪ 개발 완료 예정 Dev Completion Planned (75%) | AS4: ⑫ 라이브 키 오픈 (OMH 측) Live Key Open – OMH side only (80%) | AT4: ⑬ 첫 예약 First Booking (90%) | AU4: ⑭ 고객 라이브 확정 (고객 통보) Customer Live Confirmed – client notified (100%)
A5: =IF($G5="","",ROW()-4) -> 1 | B5: =IF($G5="","",IF($C5<>"",$C5,IF($Q5="","Contact",IF($P5>=1,"Live",IF($P5>=0.8,"Pending Live",IF($P5>=0.7,"Testing",IF($P5>=0.45,"In Development",IF($P5>=0.2,"NDA/Contract","Pipeline")))))))) -> Contact | E5: 일본 · Japan | F5: Japan | G5: JTR | H5: 매입 · Partner → OMH | I5: 직접 · Direct | J5: 3rd Party Activity | K5: Low | L5: — | N5: OHMY | O5: GSM | P5: =IF($G5="","",IFERROR(LOOKUP(2,1/($AH5:$AU5<>""),$AH$2:$AU$2),0)) -> 0 | Q5: =IF(COUNT($AH5:$AU5)=0,"",MAX($AH5:$AU5)) | R5: =IF($Q5="","",TODAY()-$Q5) | S5: =IF($G5="","",IF($Q5="","No Record",IF(OR($P5>=1,$C5="Live"),"Live",IF($R5>=90,"Stalled 90d+",IF($R5>=60,"Stalled 60d+",IF($R5>=30,"Stalled 30d+","In Progress")))))) -> No Record | T5: =IF(COUNT($AH5:$AU5)=0,"",LOOKUP(2,1/($AH5:$AU5<>""),{"① 파이프라인 시작 · Pipeline Start","② 제안·소개 발송 · Proposal Sent","③ NDA 발송 · NDA Sent","④ NDA 체결 · NDA Signed","⑤ 계약 체결 · Contract Signed","⑥ SLA 확정 · SLA Finalized","⑦ 개발 착수 예정 · Kickoff Planned","⑧ 개발 착수 · SPEC/DEV 키 · 크리덴셜 · Kickoff / Credential","⑨ 인증 · Certification","⑩ 라이브 테스트 · Live Test","⑪ 개발 완료 예정 · Dev Complete Planned","⑫ 라이브 키 오픈 (OMH 측) · Live Key Open","⑬ 첫 예약 · First Booking","⑭ 고객 라이브 확정 (고객 통보) · Customer Live"})) | U5: =IF(COUNT($AH5:$AU5)=0,"",IF(N($P5)>=1,MAX($AH5:$AU5),TODAY())-MIN($AH5:$AU5)) | V5: =IF($G5="","",COUNTIF('Chase Log'!$B$4:$B$2000,$G5)) -> 0 | W5: =IF(N($V5)=0,"",_xlfn.MAXIFS('Chase Log'!$E$4:$E$2000,'Chase Log'!$B$4:$B$2000,$G5)) | X5: =IF($W5="","",TODAY()-$W5) | Y5: =IF($W5="","",IF(OR(AND($Q5<>"",N($Q5)>N($W5)),COUNTIFS('Chase Log'!$B$4:$B$2000,$G5,'Chase Log'!$E$4:$E$2000,$W5,'Chase Log'!$I$4:$I$2000,"Y")>0),"",IF(_xlfn.MAXIFS('Chase Log'!$J$4:$J$2000,'Chase Log'!$B$4:$B$2000,$G5,'Chase Log'!$E$4:$E$2000,$W5)=0,"",_xlfn.MAXIFS('Chase Log'!$J$4:$J$2000,'Chase Log'!$B$4:$B$2000,$G5,'Chase Log'!$E$4:$E$2000,$W5)))) | Z5: =IF(OR($G5="",N($P5)>=1,$C5="Live",$D5<>""),"",IF(AND($Y5<>"",N($Y5)>0),IF($Y5<TODAY(),"Chase Overdue","Scheduled"),IF(AND($Q5<>"",N($R5)>='안내 Guide'!$D$4,OR($X5="",N($X5)>='안내 Guide'!$D$4)),"Chase Needed",""))) | AG5: Tracker
A6: =IF($G6="","",ROW()-4) -> 2 | B6: =IF($G6="","",IF($C6<>"",$C6,IF($Q6="","Contact",IF($P6>=1,"Live",IF($P6>=0.8,"Pending Live",IF($P6>=0.7,"Testing",IF($P6>=0.45,"In Development",IF($P6>=0.2,"NDA/Contract","Pipeline")))))))) -> Contact | E6: 일본 · Japan | F6: Japan | G6: Linktivity | H6: 매입 · Partner → OMH | I6: 직접 · Direct | J6: 3rd Party Activity | K6: Low | L6: 보류·종료 · On hold · closed | N6: OHMY | O6: GSM | P6: =IF($G6="","",IFERROR(LOOKUP(2,1/($AH6:$AU6<>""),$AH$2:$AU$2),0)) -> 0 | Q6: =IF(COUNT($AH6:$AU6)=0,"",MAX($AH6:$AU6)) | R6: =IF($Q6="","",TODAY()-$Q6) | S6: =IF($G6="","",IF($Q6="","No Record",IF(OR($P6>=1,$C6="Live"),"Live",IF($R6>=90,"Stalled 90d+",IF($R6>=60,"Stalled 60d+",IF($R6>=30,"Stalled 30d+","In Progress")))))) -> No Record | T6: =IF(COUNT($AH6:$AU6)=0,"",LOOKUP(2,1/($AH6:$AU6<>""),{"① 파이프라인 시작 · Pipeline Start","② 제안·소개 발송 · Proposal Sent","③ NDA 발송 · NDA Sent","④ NDA 체결 · NDA Signed","⑤ 계약 체결 · Contract Signed","⑥ SLA 확정 · SLA Finalized","⑦ 개발 착수 예정 · Kickoff Planned","⑧ 개발 착수 · SPEC/DEV 키 · 크리덴셜 · Kickoff / Credential","⑨ 인증 · Certification","⑩ 라이브 테스트 · Live Test","⑪ 개발 완료 예정 · Dev Complete Planned","⑫ 라이브 키 오픈 (OMH 측) · Live Key Open","⑬ 첫 예약 · First Booking","⑭ 고객 라이브 확정 (고객 통보) · Customer Live"})) | U6: =IF(COUNT($AH6:$AU6)=0,"",IF(N($P6)>=1,MAX($AH6:$AU6),TODAY())-MIN($AH6:$AU6)) | V6: =IF($G6="","",COUNTIF('Chase Log'!$B$4:$B$2000,$G6)) -> 0 | W6: =IF(N($V6)=0,"",_xlfn.MAXIFS('Chase Log'!$E$4:$E$2000,'Chase Log'!$B$4:$B$2000,$G6)) | X6: =IF($W6="","",TODAY()-$W6) | Y6: =IF($W6="","",IF(OR(AND($Q6<>"",N($Q6)>N($W6)),COUNTIFS('Chase Log'!$B$4:$B$2000,$G6,'Chase Log'!$E$4:$E$2000,$W6,'Chase Log'!$I$4:$I$2000,"Y")>0),"",IF(_xlfn.MAXIFS('Chase Log'!$J$4:$J$2000,'Chase Log'!$B$4:$B$2000,$G6,'Chase Log'!$E$4:$E$2000,$W6)=0,"",_xlfn.MAXIFS('Chase Log'!$J$4:$J$2000,'Chase Log'!$B$4:$B$2000,$G6,'Chase Log'!$E$4:$E$2000,$W6)))) | Z6: =IF(OR($G6="",N($P6)>=1,$C6="Live",$D6<>""),"",IF(AND($Y6<>"",N($Y6)>0),IF($Y6<TODAY(),"Chase Overdue","Scheduled"),IF(AND($Q6<>"",N($R6)>='안내 Guide'!$D$4,OR($X6="",N($X6)>='안내 Guide'!$D$4)),"Chase Needed",""))) | AC6: 신규 시스템 세부 일정 안내 수신 여부 확인(10월경 완료 목표였음) | AD6: Check whether the detailed schedule for the new system has been received (target was completion around October) | AF6: 미확인 | AG6: Tracker
A7: =IF($G7="","",ROW()-4) -> 3 | B7: =IF($G7="","",IF($C7<>"",$C7,IF($Q7="","Contact",IF($P7>=1,"Live",IF($P7>=0.8,"Pending Live",IF($P7>=0.7,"Testing",IF($P7>=0.45,"In Development",IF($P7>=0.2,"NDA/Contract","Pipeline")))))))) -> Contact | E7: 일본 · Japan | F7: Japan | G7: Toto booking | H7: 매입 · Partner → OMH | I7: 직접 · Direct | J7: 3rd Party Activity | K7: Low | L7: — | N7: OHMY | O7: GSM | P7: =IF($G7="","",IFERROR(LOOKUP(2,1/($AH7:$AU7<>""),$AH$2:$AU$2),0)) -> 0 | Q7: =IF(COUNT($AH7:$AU7)=0,"",MAX($AH7:$AU7)) | R7: =IF($Q7="","",TODAY()-$Q7) | S7: =IF($G7="","",IF($Q7="","No Record",IF(OR($P7>=1,$C7="Live"),"Live",IF($R7>=90,"Stalled 90d+",IF($R7>=60,"Stalled 60d+",IF($R7>=30,"Stalled 30d+","In Progress")))))) -> No Record | T7: =IF(COUNT($AH7:$AU7)=0,"",LOOKUP(2,1/($AH7:$AU7<>""),{"① 파이프라인 시작 · Pipeline Start","② 제안·소개 발송 · Proposal Sent","③ NDA 발송 · NDA Sent","④ NDA 체결 · NDA Signed","⑤ 계약 체결 · Contract Signed","⑥ SLA 확정 · SLA Finalized","⑦ 개발 착수 예정 · Kickoff Planned","⑧ 개발 착수 · SPEC/DEV 키 · 크리덴셜 · Kickoff / Credential","⑨ 인증 · Certification","⑩ 라이브 테스트 · Live Test","⑪ 개발 완료 예정 · Dev Complete Planned","⑫ 라이브 키 오픈 (OMH 측) · Live Key Open","⑬ 첫 예약 · First Booking","⑭ 고객 라이브 확정 (고객 통보) · Customer Live"})) | U7: =IF(COUNT($AH7:$AU7)=0,"",IF(N($P7)>=1,MAX($AH7:$AU7),TODAY())-MIN($AH7:$AU7)) | V7: =IF($G7="","",COUNTIF('Chase Log'!$B$4:$B$2000,$G7)) -> 0 | W7: =IF(N($V7)=0,"",_xlfn.MAXIFS('Chase Log'!$E$4:$E$2000,'Chase Log'!$B$4:$B$2000,$G7)) | X7: =IF($W7="","",TODAY()-$W7) | Y7: =IF($W7="","",IF(OR(AND($Q7<>"",N($Q7)>N($W7)),COUNTIFS('Chase Log'!$B$4:$B$2000,$G7,'Chase Log'!$E$4:$E$2000,$W7,'Chase Log'!$I$4:$I$2000,"Y")>0),"",IF(_xlfn.MAXIFS('Chase Log'!$J$4:$J$2000,'Chase Log'!$B$4:$B$2000,$G7,'Chase Log'!$E$4:$E$2000,$W7)=0,"",_xlfn.MAXIFS('Chase Log'!$J$4:$J$2000,'Chase Log'!$B$4:$B$2000,$G7,'Chase Log'!$E$4:$E$2000,$W7)))) | Z7: =IF(OR($G7="",N($P7)>=1,$C7="Live",$D7<>""),"",IF(AND($Y7<>"",N($Y7)>0),IF($Y7<TODAY(),"Chase Overdue","Scheduled"),IF(AND($Q7<>"",N($R7)>='안내 Guide'!$D$4,OR($X7="",N($X7)>='안내 Guide'!$D$4)),"Chase Needed",""))) | AG7: Tracker
A8: =IF($G8="","",ROW()-4) -> 4 | B8: =IF($G8="","",IF($C8<>"",$C8,IF($Q8="","Contact",IF($P8>=1,"Live",IF($P8>=0.8,"Pending Live",IF($P8>=0.7,"Testing",IF($P8>=0.45,"In Development",IF($P8>=0.2,"NDA/Contract","Pipeline")))))))) -> Contact | E8: 중화권 · Greater China | F8: Taiwan | G8: ABC Travel | H8: 매입 · Partner → OMH | I8: 직접 · Direct | J8: 3rd Party Hotel | K8: High | L8: — | N8: OHMY | O8: GSM | P8: =IF($G8="","",IFERROR(LOOKUP(2,1/($AH8:$AU8<>""),$AH$2:$AU$2),0)) -> 0 | Q8: =IF(COUNT($AH8:$AU8)=0,"",MAX($AH8:$AU8)) | R8: =IF($Q8="","",TODAY()-$Q8) | S8: =IF($G8="","",IF($Q8="","No Record",IF(OR($P8>=1,$C8="Live"),"Live",IF($R8>=90,"Stalled 90d+",IF($R8>=60,"Stalled 60d+",IF($R8>=30,"Stalled 30d+","In Progress")))))) -> No Record | T8: =IF(COUNT($AH8:$AU8)=0,"",LOOKUP(2,1/($AH8:$AU8<>""),{"① 파이프라인 시작 · Pipeline Start","② 제안·소개 발송 · Proposal Sent","③ NDA 발송 · NDA Sent","④ NDA 체결 · NDA Signed","⑤ 계약 체결 · Contract Signed","⑥ SLA 확정 · SLA Finalized","⑦ 개발 착수 예정 · Kickoff Planned","⑧ 개발 착수 · SPEC/DEV 키 · 크리덴셜 · Kickoff / Credential","⑨ 인증 · Certification","⑩ 라이브 테스트 · Live Test","⑪ 개발 완료 예정 · Dev Complete Planned","⑫ 라이브 키 오픈 (OMH 측) · Live Key Open","⑬ 첫 예약 · First Booking","⑭ 고객 라이브 확정 (고객 통보) · Customer Live"})) | U8: =IF(COUNT($AH8:$AU8)=0,"",IF(N($P8)>=1,MAX($AH8:$AU8),TODAY())-MIN($AH8:$AU8)) | V8: =IF($G8="","",COUNTIF('Chase Log'!$B$4:$B$2000,$G8)) -> 3 | W8: =IF(N($V8)=0,"",_xlfn.MAXIFS('Chase Log'!$E$4:$E$2000,'Chase Log'!$B$4:$B$2000,$G8)) -> 46323 | X8: =IF($W8="","",TODAY()-$W8) -> 2 | Y8: =IF($W8="","",IF(OR(AND($Q8<>"",N($Q8)>N($W8)),COUNTIFS('Chase Log'!$B$4:$B$2000,$G8,'Chase Log'!$E$4:$E$2000,$W8,'Chase Log'!$I$4:$I$2000,"Y")>0),"",IF(_xlfn.MAXIFS('Chase Log'!$J$4:$J$2000,'Chase Log'!$B$4:$B$2000,$G8,'Chase Log'!$E$4:$E$2000,$W8)=0,"",_xlfn.MAXIFS('Chase Log'!$J$4:$J$2000,'Chase Log'!$B$4:$B$2000,$G8,'Chase Log'!$E$4:$E$2000,$W8)))) -> 46330 | Z8: =IF(OR($G8="",N($P8)>=1,$C8="Live",$D8<>""),"",IF(AND($Y8<>"",N($Y8)>0),IF($Y8<TODAY(),"Chase Overdue","Scheduled"),IF(AND($Q8<>"",N($R8)>='안내 Guide'!$D$4,OR($X8="",N($X8)>='안내 Guide'!$D$4)),"Chase Needed",""))) -> Scheduled | AG8: Tracker

Sheet 우리가 공급사 OMH Supply
A1: 우리가 공급사 OMH Supply | E1: OMH 재고를 채널에 직접 공급하는 연동 (OMH = 공급사) We supply OMH inventory directly to the channel (OMH = supplier)
A2: ="전체 Total "&COUNTA($G$5:$G$399)&" · 라이브 Live "&(COUNTIF($B$5:$B$399,"Live")+COUNTIF($B$5:$B$399,"Partially Live"))&" · 개발·테스트 Dev/Test "&(COUNTIF($B$5:$B$399,"In Development")+COUNTIF($B$5:$B$399,"Testing")+COUNTIF($B$5:$B$399,"Pending Live"))&" · 계약·NDA "&COUNTIF($B$5:$B$399,"NDA/Contract")&" · 파이프라인 Pipeline "&(COUNTIF($B$5:$B$399,"Pipeline")+COUNTIF($B$5:$B$399,"Contact"))&" · 60일+ 정체 Stalled 60d+ "&(COUNTIF($S$5:$S$399,"Stalled 60d+")+COUNTIF($S$5:$S$399,"Stalled 90d+")) -> 전체 Total 94 · 라이브 Live 31 · 개발·테스트 Dev/Test 10 · 계약·NDA 5 · 파이프라인 Pipeline 48 · 60일+ 정체 Stalled 60d+ 9 | AG2: 단계 가중치 · Stage weight → | AH2: 0.05 | AI2: 0.1 | AJ2: 0.15 | AK2: 0.2 | AL2: 0.3 | AM2: 0.4 | AN2: 0.45 | AO2: 0.5 | AP2: 0.6 | AQ2: 0.7 | AR2: 0.75 | AS2: 0.8 | AT2: 0.9 | AU2: 1
A3: 프로젝트 · 개발 정보 · Project / Dev Info | P3: 진행 · 체이스 현황 (자동 계산) · Progress & Chase Status (Auto-calculated) | AA3: 계획 · 이슈 (직접 입력) · Plan & Issues (manual entry) | AH3: 단계 이력 (실제 날짜) · Stage History (actual dates) — Pipeline → Contract → Dev → Customer Live
A4: No. | B4: 상태 Status | C4: 상태 수동 지정 Status override | D4: 보류/드롭 Hold/Drop | E4: 지역 Region | F4: 국가 Country | G4: 프로젝트 (업체) Project (Partner) | H4: 방향 Direction | I4: 연결 경로 Connection | J4: 원본 카테고리 Category (orig.) | K4: 비즈 임팩트 Biz Impact | L4: 영업 단계 (CRM) Sales stage (CRM) | M4: 담당 (현재) Owner (current) | N4: 개발 주체 Dev Owner | O4: 처리 팀 Handling Team | P4: 진행률 Progress % | Q4: 마지막 활동 Last Activity | R4: 단계 경과일 Days in Stage | S4: 지연 체크 Delay Check | T4: 현재 단계 Current Stage | U4: 파이프라인 기간 Pipeline Age | V4: 체이스 # Chase # | W4: 마지막 체이스 Last Chase | X4: 체이스 후 경과일 Days Since Chase | Y4: 다음 체이스 Next Chase Due | Z4: 체이스 알림 Chase Alert | AA4: 목표 라이브 Target Go-Live | AB4: 대기 사유 Waiting On | AC4: 현황 · 다음 액션 (KR) Status · next action (KR) | AD4: 현황 · 다음 액션 (EN) Status · next action (EN) | AE4: 원본 Note (IT) Note (IT original) | AF4: 최종 연락 (CRM) Last contact (CRM) | AG4: 출처 · 메모 Source · memo | AH4: ① 파이프라인 시작 Pipeline Start (5%) | AI4: ② 제안·소개 발송 Proposal / Intro Sent (10%) | AJ4: ③ NDA 발송 NDA Sent (15%) | AK4: ④ NDA 체결 NDA Signed (20%) | AL4: ⑤ 계약 체결 Contract Signed (30%) | AM4: ⑥ SLA 확정 SLA Finalized (40%) | AN4: ⑦ 개발 착수 예정 Dev Kickoff Planned (45%) | AO4: ⑧ 개발 착수 · SPEC/DEV 키 · 크리덴셜 Dev Kickoff / SPEC·DEV Key (50%) / Credential | AP4: ⑨ 인증 Certification (60%) | AQ4: ⑩ 라이브 테스트 Live Test (70%) | AR4: ⑪ 개발 완료 예정 Dev Completion Planned (75%) | AS4: ⑫ 라이브 키 오픈 (OMH 측) Live Key Open – OMH side only (80%) | AT4: ⑬ 첫 예약 First Booking (90%) | AU4: ⑭ 고객 라이브 확정 (고객 통보) Customer Live Confirmed – client notified (100%)
A5: =IF($G5="","",ROW()-4) -> 1 | B5: =IF($G5="","",IF($C5<>"",$C5,IF($Q5="","Contact",IF($P5>=1,"Live",IF($P5>=0.8,"Pending Live",IF($P5>=0.7,"Testing",IF($P5>=0.45,"In Development",IF($P5>=0.2,"NDA/Contract","Pipeline")))))))) -> Live | E5: 중화권 · Greater China | F5: Hong Kong | G5: Klook | H5: 공급 · OMH → Partner | I5: 직접 · Direct | J5: Channel API | K5: High | L5: API 연동 중 · Integrating | M5: Grace | N5: OHMY | O5: GSM | P5: =IF($G5="","",IFERROR(LOOKUP(2,1/($AH5:$AU5<>""),$AH$2:$AU$2),0)) -> 1 | Q5: =IF(COUNT($AH5:$AU5)=0,"",MAX($AH5:$AU5)) -> 46316 | R5: =IF($Q5="","",TODAY()-$Q5) -> 9 | S5: =IF($G5="","",IF($Q5="","No Record",IF(OR($P5>=1,$C5="Live"),"Live",IF($R5>=90,"Stalled 90d+",IF($R5>=60,"Stalled 60d+",IF($R5>=30,"Stalled 30d+","In Progress")))))) -> Live | T5: =IF(COUNT($AH5:$AU5)=0,"",LOOKUP(2,1/($AH5:$AU5<>""),{"① 파이프라인 시작 · Pipeline Start","② 제안·소개 발송 · Proposal Sent","③ NDA 발송 · NDA Sent","④ NDA 체결 · NDA Signed","⑤ 계약 체결 · Contract Signed","⑥ SLA 확정 · SLA Finalized","⑦ 개발 착수 예정 · Kickoff Planned","⑧ 개발 착수 · SPEC/DEV 키 · 크리덴셜 · Kickoff / Credential","⑨ 인증 · Certification","⑩ 라이브 테스트 · Live Test","⑪ 개발 완료 예정 · Dev Complete Planned","⑫ 라이브 키 오픈 (OMH 측) · Live Key Open","⑬ 첫 예약 · First Booking","⑭ 고객 라이브 확정 (고객 통보) · Customer Live"})) -> ⑭ 고객 라이브 확정 (고객 통보) · Customer Live | U5: =IF(COUNT($AH5:$AU5)=0,"",IF(N($P5)>=1,MAX($AH5:$AU5),TODAY())-MIN($AH5:$AU5)) -> 354 | V5: =IF($G5="","",COUNTIF('Chase Log'!$B$4:$B$2000,$G5)) -> 1 | W5: =IF(N($V5)=0,"",_xlfn.MAXIFS('Chase Log'!$E$4:$E$2000,'Chase Log'!$B$4:$B$2000,$G5)) -> 46300 | X5: =IF($W5="","",TODAY()-$W5) -> 25 | Y5: =IF($W5="","",IF(OR(AND($Q5<>"",N($Q5)>N($W5)),COUNTIFS('Chase Log'!$B$4:$B$2000,$G5,'Chase Log'!$E$4:$E$2000,$W5,'Chase Log'!$I$4:$I$2000,"Y")>0),"",IF(_xlfn.MAXIFS('Chase Log'!$J$4:$J$2000,'Chase Log'!$B$4:$B$2000,$G5,'Chase Log'!$E$4:$E$2000,$W5)=0,"",_xlfn.MAXIFS('Chase Log'!$J$4:$J$2000,'Chase Log'!$B$4:$B$2000,$G5,'Chase Log'!$E$4:$E$2000,$W5)))) | Z5: =IF(OR($G5="",N($P5)>=1,$C5="Live",$D5<>""),"",IF(AND($Y5<>"",N($Y5)>0),IF($Y5<TODAY(),"Chase Overdue","Scheduled"),IF(AND($Q5<>"",N($R5)>='안내 Guide'!$D$4,OR($X5="",N($X5)>='안내 Guide'!$D$4)),"Chase Needed",""))) | AA5: 46302 | AC5: 언어코드 수정 배포(다음 주) 후 재오픈 + Qi Li 질의(9명 기준·미적재 호텔)·크로스매핑 결과 회신 | AD5: Reopen after language code fix is deployed (next week) + reply to Qi Li's questions (9-person basis, hotels not loaded) and cross-mapping results | AF5: 2026-10-16 | AG5: Tracker | AN5: 45962 | AO5: 45962 | AP5: 45963 | AQ5: 45964 | AR5: 45965 | AS5: 46287 | AT5: 46316 | AU5: 46316
A6: =IF($G6="","",ROW()-4) -> 2 | B6: =IF($G6="","",IF($C6<>"",$C6,IF($Q6="","Contact",IF($P6>=1,"Live",IF($P6>=0.8,"Pending Live",IF($P6>=0.7,"Testing",IF($P6>=0.45,"In Development",IF($P6>=0.2,"NDA/Contract","Pipeline")))))))) -> Pending Live | E6: 동남아 · SE Asia | F6: Vietnam | G6: Momo | H6: 공급 · OMH → Partner | I6: 직접 · Direct | J6: Channel API | K6: High | L6: API 연동 중 · Integrating | M6: Aiden (지역 공백 · interim) | N6: Partner (client-side) | O6: GSM | P6: =IF($G6="","",IFERROR(LOOKUP(2,1/($AH6:$AU6<>""),$AH$2:$AU$2),0)) -> 0.8 | Q6: =IF(COUNT($AH6:$AU6)=0,"",MAX($AH6:$AU6)) -> 46297 | R6: =IF($Q6="","",TODAY()-$Q6) -> 28 | S6: =IF($G6="","",IF($Q6="","No Record",IF(OR($P6>=1,$C6="Live"),"Live",IF($R6>=90,"Stalled 90d+",IF($R6>=60,"Stalled 60d+",IF($R6>=30,"Stalled 30d+","In Progress")))))) -> In Progress | T6: =IF(COUNT($AH6:$AU6)=0,"",LOOKUP(2,1/($AH6:$AU6<>""),{"① 파이프라인 시작 · Pipeline Start","② 제안·소개 발송 · Proposal Sent","③ NDA 발송 · NDA Sent","④ NDA 체결 · NDA Signed","⑤ 계약 체결 · Contract Signed","⑥ SLA 확정 · SLA Finalized","⑦ 개발 착수 예정 · Kickoff Planned","⑧ 개발 착수 · SPEC/DEV 키 · 크리덴셜 · Kickoff / Credential","⑨ 인증 · Certification","⑩ 라이브 테스트 · Live Test","⑪ 개발 완료 예정 · Dev Complete Planned","⑫ 라이브 키 오픈 (OMH 측) · Live Key Open","⑬ 첫 예약 · First Booking","⑭ 고객 라이브 확정 (고객 통보) · Customer Live"})) -> ⑫ 라이브 키 오픈 (OMH 측) · Live Key Open | U6: =IF(COUNT($AH6:$AU6)=0,"",IF(N($P6)>=1,MAX($AH6:$AU6),TODAY())-MIN($AH6:$AU6)) -> 147 | V6: =IF($G6="","",COUNTIF('Chase Log'!$B$4:$B$2000,$G6)) -> 2 | W6: =IF(N($V6)=0,"",_xlfn.MAXIFS('Chase Log'!$E$4:$E$2000,'Chase Log'!$B$4:$B$2000,$G6)) -> 46297 | X6: =IF($W6="","",TODAY()-$W6) -> 28 | Y6: =IF($W6="","",IF(OR(AND($Q6<>"",N($Q6)>N($W6)),COUNTIFS('Chase Log'!$B$4:$B$2000,$G6,'Chase Log'!$E$4:$E$2000,$W6,'Chase Log'!$I$4:$I$2000,"Y")>0),"",IF(_xlfn.MAXIFS('Chase Log'!$J$4:$J$2000,'Chase Log'!$B$4:$B$2000,$G6,'Chase Log'!$E$4:$E$2000,$W6)=0,"",_xlfn.MAXIFS('Chase Log'!$J$4:$J$2000,'Chase Log'!$B$4:$B$2000,$G6,'Chase Log'!$E$4:$E$2000,$W6)))) -> 46304 | Z6: =IF(OR($G6="",N($P6)>=1,$C6="Live",$D6<>""),"",IF(AND($Y6<>"",N($Y6)>0),IF($Y6<TODAY(),"Chase Overdue","Scheduled"),IF(AND($Q6<>"",N($R6)>='안내 Guide'!$D$4,OR($X6="",N($X6)>='안내 Guide'!$D$4)),"Chase Needed",""))) -> Chase Overdue | AA6: 46372 | AC6: 정산 리포트·대사 키 회신(Vicky 경유) + Tracker '라이브 포착'(10/18) 근거 확인 → PROD 연결·go-live일 확정(목표 12/16) | AD6: Reply on settlement report and reconciliation key (via Vicky) + verify basis for Tracker 'live detected' (18 Oct) → confirm PROD connection and go-live date (target 16 Dec) | AF6: 2026-10-12 | AG6: Tracker | AK6: 46178 | AL6: 46223 | AM6: 46223 | AN6: 46223 | AO6: 46219 | AP6: 46296 | AQ6: 46297 | AR6: 46297 | AS6: 46297
A7: =IF($G7="","",ROW()-4) -> 3 | B7: =IF($G7="","",IF($C7<>"",$C7,IF($Q7="","Contact",IF($P7>=1,"Live",IF($P7>=0.8,"Pending Live",IF($P7>=0.7,"Testing",IF($P7>=0.45,"In Development",IF($P7>=0.2,"NDA/Contract","Pipeline")))))))) -> Testing | E7: 중화권 · Greater China | F7: Taiwan | G7: Cola Tour | H7: 공급 · OMH → Partner | I7: 직접 · Direct | J7: Channel API | K7: High | L7: API 연동 중 · Integrating | M7: Grace | N7: Partner (client-side) | O7: GSM | P7: =IF($G7="","",IFERROR(LOOKUP(2,1/($AH7:$AU7<>""),$AH$2:$AU$2),0)) -> 0.7 | Q7: =IF(COUNT($AH7:$AU7)=0,"",MAX($AH7:$AU7)) -> 46296 | R7: =IF($Q7="","",TODAY()-$Q7) -> 29 | S7: =IF($G7="","",IF($Q7="","No Record",IF(OR($P7>=1,$C7="Live"),"Live",IF($R7>=90,"Stalled 90d+",IF($R7>=60,"Stalled 60d+",IF($R7>=30,"Stalled 30d+","In Progress")))))) -> In Progress | T7: =IF(COUNT($AH7:$AU7)=0,"",LOOKUP(2,1/($AH7:$AU7<>""),{"① 파이프라인 시작 · Pipeline Start","② 제안·소개 발송 · Proposal Sent","③ NDA 발송 · NDA Sent","④ NDA 체결 · NDA Signed","⑤ 계약 체결 · Contract Signed","⑥ SLA 확정 · SLA Finalized","⑦ 개발 착수 예정 · Kickoff Planned","⑧ 개발 착수 · SPEC/DEV 키 · 크리덴셜 · Kickoff / Credential","⑨ 인증 · Certification","⑩ 라이브 테스트 · Live Test","⑪ 개발 완료 예정 · Dev Complete Planned","⑫ 라이브 키 오픈 (OMH 측) · Live Key Open","⑬ 첫 예약 · First Booking","⑭ 고객 라이브 확정 (고객 통보) · Customer Live"})) -> ⑩ 라이브 테스트 · Live Test | U7: =IF(COUNT($AH7:$AU7)=0,"",IF(N($P7)>=1,MAX($AH7:$AU7),TODAY())-MIN($AH7:$AU7)) -> 90 | V7: =IF($G7="","",COUNTIF('Chase Log'!$B$4:$B$2000,$G7)) -> 0 | W7: =IF(N($V7)=0,"",_xlfn.MAXIFS('Chase Log'!$E$4:$E$2000,'Chase Log'!$B$4:$B$2000,$G7)) | X7: =IF($W7="","",TODAY()-$W7) | Y7: =IF($W7="","",IF(OR(AND($Q7<>"",N($Q7)>N($W7)),COUNTIFS('Chase Log'!$B$4:$B$2000,$G7,'Chase Log'!$E$4:$E$2000,$W7,'Chase Log'!$I$4:$I$2000,"Y")>0),"",IF(_xlfn.MAXIFS('Chase Log'!$J$4:$J$2000,'Chase Log'!$B$4:$B$2000,$G7,'Chase Log'!$E$4:$E$2000,$W7)=0,"",_xlfn.MAXIFS('Chase Log'!$J$4:$J$2000,'Chase Log'!$B$4:$B$2000,$G7,'Chase Log'!$E$4:$E$2000,$W7)))) | Z7: =IF(OR($G7="",N($P7)>=1,$C7="Live",$D7<>""),"",IF(AND($Y7<>"",N($Y7)>0),IF($Y7<TODAY(),"Chase Overdue","Scheduled"),IF(AND($Q7<>"",N($R7)>='안내 Guide'!$D$4,OR($X7="",N($X7)>='안내 Guide'!$D$4)),"Chase Needed",""))) -> Chase Needed | AC7: OMH 개발 대기 사유·일정 IT 확인 후 Live 전환 | AD7: Check with IT the reason for and timeline of the OMH development hold, then switch to Live | AF7: 2026-10-01 | AG7: Tracker | AO7: 46235 | AP7: 46296 | AQ7: 46296
A8: =IF($G8="","",ROW()-4) -> 4 | B8: =IF($G8="","",IF($C8<>"",$C8,IF($Q8="","Contact",IF($P8>=1,"Live",IF($P8>=0.8,"Pending Live",IF($P8>=0.7,"Testing",IF($P8>=0.45,"In Development",IF($P8>=0.2,"NDA/Contract","Pipeline")))))))) -> Testing | E8: 중화권 · Greater China | F8: China | G8: Fangcang | H8: 공급 · OMH → Partner | I8: 직접 · Direct | J8: Channel API | K8: High | L8: API 연동 중 · Integrating | M8: Grace | N8: Partner (client-side) | O8: GSM | P8: =IF($G8="","",IFERROR(LOOKUP(2,1/($AH8:$AU8<>""),$AH$2:$AU$2),0)) -> 0.7 | Q8: =IF(COUNT($AH8:$AU8)=0,"",MAX($AH8:$AU8)) -> 46289 | R8: =IF($Q8="","",TODAY()-$Q8) -> 36 | S8: =IF($G8="","",IF($Q8="","No Record",IF(OR($P8>=1,$C8="Live"),"Live",IF($R8>=90,"Stalled 90d+",IF($R8>=60,"Stalled 60d+",IF($R8>=30,"Stalled 30d+","In Progress")))))) -> Stalled 30d+ | T8: =IF(COUNT($AH8:$AU8)=0,"",LOOKUP(2,1/($AH8:$AU8<>""),{"① 파이프라인 시작 · Pipeline Start","② 제안·소개 발송 · Proposal Sent","③ NDA 발송 · NDA Sent","④ NDA 체결 · NDA Signed","⑤ 계약 체결 · Contract Signed","⑥ SLA 확정 · SLA Finalized","⑦ 개발 착수 예정 · Kickoff Planned","⑧ 개발 착수 · SPEC/DEV 키 · 크리덴셜 · Kickoff / Credential","⑨ 인증 · Certification","⑩ 라이브 테스트 · Live Test","⑪ 개발 완료 예정 · Dev Complete Planned","⑫ 라이브 키 오픈 (OMH 측) · Live Key Open","⑬ 첫 예약 · First Booking","⑭ 고객 라이브 확정 (고객 통보) · Customer Live"})) -> ⑩ 라이브 테스트 · Live Test | U8: =IF(COUNT($AH8:$AU8)=0,"",IF(N($P8)>=1,MAX($AH8:$AU8),TODAY())-MIN($AH8:$AU8)) -> 83 | V8: =IF($G8="","",COUNTIF('Chase Log'!$B$4:$B$2000,$G8)) -> 1 | W8: =IF(N($V8)=0,"",_xlfn.MAXIFS('Chase Log'!$E$4:$E$2000,'Chase Log'!$B$4:$B$2000,$G8)) -> 46300 | X8: =IF($W8="","",TODAY()-$W8) -> 25 | Y8: =IF($W8="","",IF(OR(AND($Q8<>"",N($Q8)>N($W8)),COUNTIFS('Chase Log'!$B$4:$B$2000,$G8,'Chase Log'!$E$4:$E$2000,$W8,'Chase Log'!$I$4:$I$2000,"Y")>0),"",IF(_xlfn.MAXIFS('Chase Log'!$J$4:$J$2000,'Chase Log'!$B$4:$B$2000,$G8,'Chase Log'!$E$4:$E$2000,$W8)=0,"",_xlfn.MAXIFS('Chase Log'!$J$4:$J$2000,'Chase Log'!$B$4:$B$2000,$G8,'Chase Log'!$E$4:$E$2000,$W8)))) | Z8: =IF(OR($G8="",N($P8)>=1,$C8="Live",$D8<>""),"",IF(AND($Y8<>"",N($Y8)>0),IF($Y8<TODAY(),"Chase Overdue","Scheduled"),IF(AND($Q8<>"",N($R8)>='안내 Guide'!$D$4,OR($X8="",N($X8)>='안내 Guide'!$D$4)),"Chase Needed",""))) -> Chase Needed | AC8: OMH 개발 대기 사유·일정 IT 확인 → Live Key 일정 확정 + Z-trip 결제용 Fangcang(AMT) 연동 가능성 확인·재보고 | AD8: Check with IT the reason for and timeline of the OMH development hold → confirm Live Key date + check feasibility of Fangcang (AMT) integration for Z-trip payments and re-report | AF8: 2026-10-05 | AG8: Tracker | AK8: 46242 | AL8: 46243 | AM8: 46244 | AN8: 46245 | AO8: 46246 | AP8: 46256 | AQ8: 46289
A9: =IF($G9="","",ROW()-4) -> 5 | B9: =IF($G9="","",IF($C9<>"",$C9,IF($Q9="","Contact",IF($P9>=1,"Live",IF($P9>=0.8,"Pending Live",IF($P9>=0.7,"Testing",IF($P9>=0.45,"In Development",IF($P9>=0.2,"NDA/Contract","Pipeline")))))))) -> Live | C9: Live | E9: 중화권 · Greater China | F9: China | G9: JL Tour | H9: 공급 · OMH → Partner | I9: 직접 · Direct | J9: Channel API | K9: High | L9: API 연동 중 · Integrating | M9: Grace | N9: Partner (client-side) | O9: GSM | P9: {=IF($G9="","",IFERROR(LOOKUP(2,1/($AH9:$AU9<>""),$AH$2:$AU$2),0))} -> 0.9 | Q9: =IF(COUNT($AH9:$AU9)=0,"",MAX($AH9:$AU9)) -> 46316 | R9: =IF($Q9="","",TODAY()-$Q9) -> 9 | S9: =IF($G9="","",IF($Q9="","No Record",IF(OR($P9>=1,$C9="Live"),"Live",IF($R9>=90,"Stalled 90d+",IF($R9>=60,"Stalled 60d+",IF($R9>=30,"Stalled 30d+","In Progress")))))) -> Live | T9: =IF(COUNT($AH9:$AU9)=0,"",LOOKUP(2,1/($AH9:$AU9<>""),{"① 파이프라인 시작 · Pipeline Start","② 제안·소개 발송 · Proposal Sent","③ NDA 발송 · NDA Sent","④ NDA 체결 · NDA Signed","⑤ 계약 체결 · Contract Signed","⑥ SLA 확정 · SLA Finalized","⑦ 개발 착수 예정 · Kickoff Planned","⑧ 개발 착수 · SPEC/DEV 키 · 크리덴셜 · Kickoff / Credential","⑨ 인증 · Certification","⑩ 라이브 테스트 · Live Test","⑪ 개발 완료 예정 · Dev Complete Planned","⑫ 라이브 키 오픈 (OMH 측) · Live Key Open","⑬ 첫 예약 · First Booking","⑭ 고객 라이브 확정 (고객 통보) · Customer Live"})) -> ⑬ 첫 예약 · First Booking | U9: =IF(COUNT($AH9:$AU9)=0,"",IF(N($P9)>=1,MAX($AH9:$AU9),TODAY())-MIN($AH9:$AU9)) -> 354 | V9: =IF($G9="","",COUNTIF('Chase Log'!$B$4:$B$2000,$G9)) -> 1 | W9: =IF(N($V9)=0,"",_xlfn.MAXIFS('Chase Log'!$E$4:$E$2000,'Chase Log'!$B$4:$B$2000,$G9)) -> 46300 | X9: =IF($W9="","",TODAY()-$W9) -> 25 | Y9: =IF($W9="","",IF(OR(AND($Q9<>"",N($Q9)>N($W9)),COUNTIFS('Chase Log'!$B$4:$B$2000,$G9,'Chase Log'!$E$4:$E$2000,$W9,'Chase Log'!$I$4:$I$2000,"Y")>0),"",IF(_xlfn.MAXIFS('Chase Log'!$J$4:$J$2000,'Chase Log'!$B$4:$B$2000,$G9,'Chase Log'!$E$4:$E$2000,$W9)=0,"",_xlfn.MAXIFS('Chase Log'!$J$4:$J$2000,'Chase Log'!$B$4:$B$2000,$G9,'Chase Log'!$E$4:$E$2000,$W9)))) | Z9: =IF(OR($G9="",N($P9)>=1,$C9="Live",$D9<>""),"",IF(AND($Y9<>"",N($Y9)>0),IF($Y9<TODAY(),"Chase Overdue","Scheduled"),IF(AND($Q9<>"",N($R9)>='안내 Guide'!$D$4,OR($X9="",N($X9)>='안내 Guide'!$D$4)),"Chase Needed",""))) | AA9: 46310 | AC9: OMH 개발 대기 사유·일정 IT 확인 후 Live 전환 | AD9: Check with IT the reason for and timeline of the OMH development hold, then switch to Live | AF9: 2026-10-05 | AG9: Tracker | AK9: 45971 | AL9: 45971 | AM9: 45971 | AN9: 45971 | AO9: 45971 | AP9: 46275 | AQ9: 46280 | AR9: 46295 | AS9: 46296 | AT9: 46316
A10: =IF($G10="","",ROW()-4) -> 6 | B10: =IF($G10="","",IF($C10<>"",$C10,IF($Q10="","Contact",IF($P10>=1,"Live",IF($P10>=0.8,"Pending Live",IF($P10>=0.7,"Testing",IF($P10>=0.45,"In Development",IF($P10>=0.2,"NDA/Contract","Pipeline")))))))) -> In Development | E10: 한국 · Korea | F10: Korea | G10: Jejupay | H10: 공급 · OMH → Partner | I10: 직접 · Direct | J10: Channel API | K10: Mid | L10: API 연동 중 · Integrating | M10: Jane | N10: Partner (client-side) | O10: GSM | P10: =IF($G10="","",IFERROR(LOOKUP(2,1/($AH10:$AU10<>""),$AH$2:$AU$2),0)) -> 0.5 | Q10: =IF(COUNT($AH10:$AU10)=0,"",MAX($AH10:$AU10)) -> 46255 | R10: =IF($Q10="","",TODAY()-$Q10) -> 70 | S10: =IF($G10="","",IF($Q10="","No Record",IF(OR($P10>=1,$C10="Live"),"Live",IF($R10>=90,"Stalled 90d+",IF($R10>=60,"Stalled 60d+",IF($R10>=30,"Stalled 30d+","In Progress")))))) -> Stalled 60d+ | T10: =IF(COUNT($AH10:$AU10)=0,"",LOOKUP(2,1/($AH10:$AU10<>""),{"① 파이프라인 시작 · Pipeline Start","② 제안·소개 발송 · Proposal Sent","③ NDA 발송 · NDA Sent","④ NDA 체결 · NDA Signed","⑤ 계약 체결 · Contract Signed","⑥ SLA 확정 · SLA Finalized","⑦ 개발 착수 예정 · Kickoff Planned","⑧ 개발 착수 · SPEC/DEV 키 · 크리덴셜 · Kickoff / Credential","⑨ 인증 · Certification","⑩ 라이브 테스트 · Live Test","⑪ 개발 완료 예정 · Dev Complete Planned","⑫ 라이브 키 오픈 (OMH 측) · Live Key Open","⑬ 첫 예약 · First Booking","⑭ 고객 라이브 확정 (고객 통보) · Customer Live"})) -> ⑧ 개발 착수 · SPEC/DEV 키 · 크리덴셜 · Kickoff / Credential | U10: =IF(COUNT($AH10:$AU10)=0,"",IF(N($P10)>=1,MAX($AH10:$AU10),TODAY())-MIN($AH10:$AU10)) -> 108 | V10: =IF($G10="","",COUNTIF('Chase Log'!$B$4:$B$2000,$G10)) -> 1 | W10: =IF(N($V10)=0,"",_xlfn.MAXIFS('Chase Log'!$E$4:$E$2000,'Chase Log'!$B$4:$B$2000,$G10)) -> 46300 | X10: =IF($W10="","",TODAY()-$W10) -> 25 | Y10: =IF($W10="","",IF(OR(AND($Q10<>"",N($Q10)>N($W10)),COUNTIFS('Chase Log'!$B$4:$B$2000,$G10,'Chase Log'!$E$4:$E$2000,$W10,'Chase Log'!$I$4:$I$2000,"Y")>0),"",IF(_xlfn.MAXIFS('Chase Log'!$J$4:$J$2000,'Chase Log'!$B$4:$B$2000,$G10,'Chase Log'!$E$4:$E$2000,$W10)=0,"",_xlfn.MAXIFS('Chase Log'!$J$4:$J$2000,'Chase Log'!$B$4:$B$2000,$G10,'Chase Log'!$E$4:$E$2000,$W10)))) | Z10: =IF(OR($G10="",N($P10)>=1,$C10="Live",$D10<>""),"",IF(AND($Y10<>"",N($Y10)>0),IF($Y10<TODAY(),"Chase Overdue","Scheduled"),IF(AND($Q10<>"",N($R10)>='안내 Guide'!$D$4,OR($X10="",N($X10)>='안내 Guide'!$D$4)),"Chase Needed",""))) -> Chase Needed | AC10: 상대 설계 진행 상황·연동 착수 예정일 체이스 | AD10: Chase partner's design progress and planned integration start date | AF10: 2026-10-05 | AG10: Tracker | AK10: 46217 | AL10: 46238 | AO10: 46255
A11: =IF($G11="","",ROW()-4) -> 7 | B11: =IF($G11="","",IF($C11<>"",$C11,IF($Q11="","Contact",IF($P11>=1,"Live",IF($P11>=0.8,"Pending Live",IF($P11>=0.7,"Testing",IF($P11>=0.45,"In Development",IF($P11>=0.2,"NDA/Contract","Pipeline")))))))) -> In Development | E11: 중화권 · Greater China | F11: China | G11: Huamao | H11: 공급 · OMH → Partner | I11: 직접 · Direct | J11: Channel API | K11: Mid | L11: API 연동 중 · Integrating | M11: Grace | N11: Partner (client-side) | O11: GSM | P11: =IF($G11="","",IFERROR(LOOKUP(2,1/($AH11:$AU11<>""),$AH$2:$AU$2),0)) -> 0.5 | Q11: =IF(COUNT($AH11:$AU11)=0,"",MAX($AH11:$AU11)) -> 46248 | R11: =IF($Q11="","",TODAY()-$Q11) -> 77 | S11: =IF($G11="","",IF($Q11="","No Record",IF(OR($P11>=1,$C11="Live"),"Live",IF($R11>=90,"Stalled 90d+",IF($R11>=60,"Stalled 60d+",IF($R11>=30,"Stalled 30d+","In Progress")))))) -> Stalled 60d+ | T11: =IF(COUNT($AH11:$AU11)=0,"",LOOKUP(2,1/($AH11:$AU11<>""),{"① 파이프라인 시작 · Pipeline Start","② 제안·소개 발송 · Proposal Sent","③ NDA 발송 · NDA Sent","④ NDA 체결 · NDA Signed","⑤ 계약 체결 · Contract Signed","⑥ SLA 확정 · SLA Finalized","⑦ 개발 착수 예정 · Kickoff Planned","⑧ 개발 착수 · SPEC/DEV 키 · 크리덴셜 · Kickoff / Credential","⑨ 인증 · Certification","⑩ 라이브 테스트 · Live Test","⑪ 개발 완료 예정 · Dev Complete Planned","⑫ 라이브 키 오픈 (OMH 측) · Live Key Open","⑬ 첫 예약 · First Booking","⑭ 고객 라이브 확정 (고객 통보) · Customer Live"})) -> ⑧ 개발 착수 · SPEC/DEV 키 · 크리덴셜 · Kickoff / Credential | U11: =IF(COUNT($AH11:$AU11)=0,"",IF(N($P11)>=1,MAX($AH11:$AU11),TODAY())-MIN($AH11:$AU11)) -> 81 | V11: =IF($G11="","",COUNTIF('Chase Log'!$B$4:$B$2000,$G11)) -> 1 | W11: =IF(N($V11)=0,"",_xlfn.MAXIFS('Chase Log'!$E$4:$E$2000,'Chase Log'!$B$4:$B$2000,$G11)) -> 46300 | X11: =IF($W11="","",TODAY()-$W11) -> 25 | Y11: =IF($W11="","",IF(OR(AND($Q11<>"",N($Q11)>N($W11)),COUNTIFS('Chase Log'!$B$4:$B$2000,$G11,'Chase Log'!$E$4:$E$2000,$W11,'Chase Log'!$I$4:$I$2000,"Y")>0),"",IF(_xlfn.MAXIFS('Chase Log'!$J$4:$J$2000,'Chase Log'!$B$4:$B$2000,$G11,'Chase Log'!$E$4:$E$2000,$W11)=0,"",_xlfn.MAXIFS('Chase Log'!$J$4:$J$2000,'Chase Log'!$B$4:$B$2000,$G11,'Chase Log'!$E$4:$E$2000,$W11)))) | Z11: =IF(OR($G11="",N($P11)>=1,$C11="Live",$D11<>""),"",IF(AND($Y11<>"",N($Y11)>0),IF($Y11<TODAY(),"Chase Overdue","Scheduled"),IF(AND($Q11<>"",N($R11)>='안내 Guide'!$D$4,OR($X11="",N($X11)>='안내 Guide'!$D$4)),"Chase Needed",""))) -> Chase Needed | AC11: 개발 재개 확인 — 8/3 API 오류 해결 여부·인증 일정 | AD11: Confirm development has resumed — whether the 3 Aug API error is resolved and certification schedule | AF11: 2026-10-05 | AG11: Tracker | AK11: 46244 | AL11: 46245 | AM11: 46246 | AN11: 46247 | AO11: 46248
A12: =IF($G12="","",ROW()-4) -> 8 | B12: =IF($G12="","",IF($C12<>"",$C12,IF($Q12="","Contact",IF($P12>=1,"Live",IF($P12>=0.8,"Pending Live",IF($P12>=0.7,"Testing",IF($P12>=0.45,"In Development",IF($P12>=0.2,"NDA/Contract","Pipeline")))))))) -> In Development | E12: 중화권 · Greater China | F12: Taiwan | G12: Star Travel | H12: 공급 · OMH → Partner | I12: 직접 · Direct | J12: Channel API | K12: High | L12: — | M12: Grace | N12: Partner (client-side) | O12: GSM | P12: =IF($G12="","",IFERROR(LOOKUP(2,1/($AH12:$AU12<>""),$AH$2:$AU$2),0)) -> 0.5 | Q12: =IF(COUNT($AH12:$AU12)=0,"",MAX($AH12:$AU12)) -> 45993 | R12: =IF($Q12="","",TODAY()-$Q12) -> 332 | S12: =IF($G12="","",IF($Q12="","No Record",IF(OR($P12>=1,$C12="Live"),"Live",IF($R12>=90,"Stalled 90d+",IF($R12>=60,"Stalled 60d+",IF($R12>=30,"Stalled 30d+","In Progress")))))) -> Stalled 90d+ | T12: =IF(COUNT($AH12:$AU12)=0,"",LOOKUP(2,1/($AH12:$AU12<>""),{"① 파이프라인 시작 · Pipeline Start","② 제안·소개 발송 · Proposal Sent","③ NDA 발송 · NDA Sent","④ NDA 체결 · NDA Signed","⑤ 계약 체결 · Contract Signed","⑥ SLA 확정 · SLA Finalized","⑦ 개발 착수 예정 · Kickoff Planned","⑧ 개발 착수 · SPEC/DEV 키 · 크리덴셜 · Kickoff / Credential","⑨ 인증 · Certification","⑩ 라이브 테스트 · Live Test","⑪ 개발 완료 예정 · Dev Complete Planned","⑫ 라이브 키 오픈 (OMH 측) · Live Key Open","⑬ 첫 예약 · First Booking","⑭ 고객 라이브 확정 (고객 통보) · Customer Live"})) -> ⑧ 개발 착수 · SPEC/DEV 키 · 크리덴셜 · Kickoff / Credential | U12: =IF(COUNT($AH12:$AU12)=0,"",IF(N($P12)>=1,MAX($AH12:$AU12),TODAY())-MIN($AH12:$AU12)) -> 379 | V12: =IF($G12="","",COUNTIF('Chase Log'!$B$4:$B$2000,$G12)) -> 1 | W12: =IF(N($V12)=0,"",_xlfn.MAXIFS('Chase Log'!$E$4:$E$2000,'Chase Log'!$B$4:$B$2000,$G12)) -> 46300 | X12: =IF($W12="","",TODAY()-$W12) -> 25 | Y12: =IF($W12="","",IF(OR(AND($Q12<>"",N($Q12)>N($W12)),COUNTIFS('Chase Log'!$B$4:$B$2000,$G12,'Chase Log'!$E$4:$E$2000,$W12,'Chase Log'!$I$4:$I$2000,"Y")>0),"",IF(_xlfn.MAXIFS('Chase Log'!$J$4:$J$2000,'Chase Log'!$B$4:$B$2000,$G12,'Chase Log'!$E$4:$E$2000,$W12)=0,"",_xlfn.MAXIFS('Chase Log'!$J$4:$J$2000,'Chase Log'!$B$4:$B$2000,$G12,'Chase Log'!$E$4:$E$2000,$W12)))) | Z12: =IF(OR($G12="",N($P12)>=1,$C12="Live",$D12<>""),"",IF(AND($Y12<>"",N($Y12)>0),IF($Y12<TODAY(),"Chase Overdue","Scheduled"),IF(AND($Q12<>"",N($R12)>='안내 Guide'!$D$4,OR($X12="",N($X12)>='안내 Guide'!$D$4)),"Chase Needed",""))) -> Chase Needed | AG12: Tracker | AL12: 45946 | AN12: 45992 | AO12: 45993
A13: =IF($G13="","",ROW()-4) -> 9 | B13: =IF($G13="","",IF($C13<>"",$C13,IF($Q13="","Contact",IF($P13>=1,"Live",IF($P13>=0.8,"Pending Live",IF($P13>=0.7,"Testing",IF($P13>=0.45,"In Development",IF($P13>=0.2,"NDA/Contract","Pipeline")))))))) -> In Development | E13: 중화권 · Greater China | F13: China | G13: Ziru (TMC) | H13: 공급 · OMH → Partner | I13: 직접 · Direct | J13: Channel API | K13: Mid | L13: — | M13: Grace | N13: Partner (client-side) | O13: GSM | P13: =IF($G13="","",IFERROR(LOOKUP(2,1/($AH13:$AU13<>""),$AH$2:$AU$2),0)) -> 0.5 | Q13: =IF(COUNT($AH13:$AU13)=0,"",MAX($AH13:$AU13)) -> 46248 | R13: =IF($Q13="","",TODAY()-$Q13) -> 77 | S13: =IF($G13="","",IF($Q13="","No Record",IF(OR($P13>=1,$C13="Live"),"Live",IF($R13>=90,"Stalled 90d+",IF($R13>=60,"Stalled 60d+",IF($R13>=30,"Stalled 30d+","In Progress")))))) -> Stalled 60d+ | T13: =IF(COUNT($AH13:$AU13)=0,"",LOOKUP(2,1/($AH13:$AU13<>""),{"① 파이프라인 시작 · Pipeline Start","② 제안·소개 발송 · Proposal Sent","③ NDA 발송 · NDA Sent","④ NDA 체결 · NDA Signed","⑤ 계약 체결 · Contract Signed","⑥ SLA 확정 · SLA Finalized","⑦ 개발 착수 예정 · Kickoff Planned","⑧ 개발 착수 · SPEC/DEV 키 · 크리덴셜 · Kickoff / Credential","⑨ 인증 · Certification","⑩ 라이브 테스트 · Live Test","⑪ 개발 완료 예정 · Dev Complete Planned","⑫ 라이브 키 오픈 (OMH 측) · Live Key Open","⑬ 첫 예약 · First Booking","⑭ 고객 라이브 확정 (고객 통보) · Customer Live"})) -> ⑧ 개발 착수 · SPEC/DEV 키 · 크리덴셜 · Kickoff / Credential | U13: =IF(COUNT($AH13:$AU13)=0,"",IF(N($P13)>=1,MAX($AH13:$AU13),TODAY())-MIN($AH13:$AU13)) -> 81 | V13: =IF($G13="","",COUNTIF('Chase Log'!$B$4:$B$2000,$G13)) -> 1 | W13: =IF(N($V13)=0,"",_xlfn.MAXIFS('Chase Log'!$E$4:$E$2000,'Chase Log'!$B$4:$B$2000,$G13)) -> 46300 | X13: =IF($W13="","",TODAY()-$W13) -> 25 | Y13: =IF($W13="","",IF(OR(AND($Q13<>"",N($Q13)>N($W13)),COUNTIFS('Chase Log'!$B$4:$B$2000,$G13,'Chase Log'!$E$4:$E$2000,$W13,'Chase Log'!$I$4:$I$2000,"Y")>0),"",IF(_xlfn.MAXIFS('Chase Log'!$J$4:$J$2000,'Chase Log'!$B$4:$B$2000,$G13,'Chase Log'!$E$4:$E$2000,$W13)=0,"",_xlfn.MAXIFS('Chase Log'!$J$4:$J$2000,'Chase Log'!$B$4:$B$2000,$G13,'Chase Log'!$E$4:$E$2000,$W13)))) | Z13: =IF(OR($G13="",N($P13)>=1,$C13="Live",$D13<>""),"",IF(AND($Y13<>"",N($Y13)>0),IF($Y13<TODAY(),"Chase Overdue","Scheduled"),IF(AND($Q13<>"",N($R13)>='안내 Guide'!$D$4,OR($X13="",N($X13)>='안내 Guide'!$D$4)),"Chase Needed",""))) -> Chase Needed | AG13: Tracker | AK13: 46244 | AL13: 46245 | AM13: 46246 | AN13: 46247 | AO13: 46248
A14: =IF($G14="","",ROW()-4) -> 10 | B14: =IF($G14="","",IF($C14<>"",$C14,IF($Q14="","Contact",IF($P14>=1,"Live",IF($P14>=0.8,"Pending Live",IF($P14>=0.7,"Testing",IF($P14>=0.45,"In Development",IF($P14>=0.2,"NDA/Contract","Pipeline")))))))) -> In Development | E14: 중동·러시아 · ME & Russia | F14: Russia | G14: Travelata(Vivatech) | H14: 공급 · OMH → Partner | I14: 직접 · Direct | J14: Channel API | K14: High | L14: API 연동 중 · Integrating | M14: Aiden (지역 공백 · interim) | N14: Partner (client-side) | O14: GSM | P14: =IF($G14="","",IFERROR(LOOKUP(2,1/($AH14:$AU14<>""),$AH$2:$AU$2),0)) -> 0.5 | Q14: =IF(COUNT($AH14:$AU14)=0,"",MAX($AH14:$AU14)) -> 46253 | R14: =IF($Q14="","",TODAY()-$Q14) -> 72 | S14: =IF($G14="","",IF($Q14="","No Record",IF(OR($P14>=1,$C14="Live"),"Live",IF($R14>=90,"Stalled 90d+",IF($R14>=60,"Stalled 60d+",IF($R14>=30,"Stalled 30d+","In Progress")))))) -> Stalled 60d+ | T14: =IF(COUNT($AH14:$AU14)=0,"",LOOKUP(2,1/($AH14:$AU14<>""),{"① 파이프라인 시작 · Pipeline Start","② 제안·소개 발송 · Proposal Sent","③ NDA 발송 · NDA Sent","④ NDA 체결 · NDA Signed","⑤ 계약 체결 · Contract Signed","⑥ SLA 확정 · SLA Finalized","⑦ 개발 착수 예정 · Kickoff Planned","⑧ 개발 착수 · SPEC/DEV 키 · 크리덴셜 · Kickoff / Credential","⑨ 인증 · Certification","⑩ 라이브 테스트 · Live Test","⑪ 개발 완료 예정 · Dev Complete Planned","⑫ 라이브 키 오픈 (OMH 측) · Live Key Open","⑬ 첫 예약 · First Booking","⑭ 고객 라이브 확정 (고객 통보) · Customer Live"})) -> ⑧ 개발 착수 · SPEC/DEV 키 · 크리덴셜 · Kickoff / Credential | U14: =IF(COUNT($AH14:$AU14)=0,"",IF(N($P14)>=1,MAX($AH14:$AU14),TODAY())-MIN($AH14:$AU14)) -> 73 | V14: =IF($G14="","",COUNTIF('Chase Log'!$B$4:$B$2000,$G14)) -> 1 | W14: =IF(N($V14)=0,"",_xlfn.MAXIFS('Chase Log'!$E$4:$E$2000,'Chase Log'!$B$4:$B$2000,$G14)) -> 46300 | X14: =IF($W14="","",TODAY()-$W14) -> 25 | Y14: =IF($W14="","",IF(OR(AND($Q14<>"",N($Q14)>N($W14)),COUNTIFS('Chase Log'!$B$4:$B$2000,$G14,'Chase Log'!$E$4:$E$2000,$W14,'Chase Log'!$I$4:$I$2000,"Y")>0),"",IF(_xlfn.MAXIFS('Chase Log'!$J$4:$J$2000,'Chase Log'!$B$4:$B$2000,$G14,'Chase Log'!$E$4:$E$2000,$W14)=0,"",_xlfn.MAXIFS('Chase Log'!$J$4:$J$2000,'Chase Log'!$B$4:$B$2000,$G14,'Chase Log'!$E$4:$E$2000,$W14)))) | Z14: =IF(OR($G14="",N($P14)>=1,$C14="Live",$D14<>""),"",IF(AND($Y14<>"",N($Y14)>0),IF($Y14<TODAY(),"Chase Overdue","Scheduled"),IF(AND($Q14<>"",N($R14)>='안내 Guide'!$D$4,OR($X14="",N($X14)>='안내 Guide'!$D$4)),"Chase Needed",""))) -> Chase Needed | AC14: API 연동 진행(DEV·개발 일정·담당자·IP) 체이스 + 보증금 USD 20,000 입금 확인 | AD14: Chase API integration progress (DEV, development schedule, contact person, IP) + confirm deposit of USD 20,000 received | AF14: 2026-09-29 | AG14: Tracker | AK14: 46252 | AL14: 46253 | AN14: 46253 | AO14: 46253
A15: =IF($G15="","",ROW()-4) -> 11 | B15: =IF($G15="","",IF($C15<>"",$C15,IF($Q15="","Contact",IF($P15>=1,"Live",IF($P15>=0.8,"Pending Live",IF($P15>=0.7,"Testing",IF($P15>=0.45,"In Development",IF($P15>=0.2,"NDA/Contract","Pipeline")))))))) -> In Development | E15: 중화권 · Greater China | F15: China | G15: Hibeds | H15: 공급 · OMH → Partner | I15: 직접 · Direct | J15: Channel API | K15: High | L15: API 연동 중 · Integrating | M15: Grace | N15: Partner (client-side) | O15: GSM | P15: =IF($G15="","",IFERROR(LOOKUP(2,1/($AH15:$AU15<>""),$AH$2:$AU$2),0)) -> 0.5 | Q15: =IF(COUNT($AH15:$AU15)=0,"",MAX($AH15:$AU15)) -> 46305 | R15: =IF($Q15="","",TODAY()-$Q15) -> 20 | S15: =IF($G15="","",IF($Q15="","No Record",IF(OR($P15>=1,$C15="Live"),"Live",IF($R15>=90,"Stalled 90d+",IF($R15>=60,"Stalled 60d+",IF($R15>=30,"Stalled 30d+","In Progress")))))) -> In Progress | T15: =IF(COUNT($AH15:$AU15)=0,"",LOOKUP(2,1/($AH15:$AU15<>""),{"① 파이프라인 시작 · Pipeline Start","② 제안·소개 발송 · Proposal Sent","③ NDA 발송 · NDA Sent","④ NDA 체결 · NDA Signed","⑤ 계약 체결 · Contract Signed","⑥ SLA 확정 · SLA Finalized","⑦ 개발 착수 예정 · Kickoff Planned","⑧ 개발 착수 · SPEC/DEV 키 · 크리덴셜 · Kickoff / Credential","⑨ 인증 · Certification","⑩ 라이브 테스트 · Live Test","⑪ 개발 완료 예정 · Dev Complete Planned","⑫ 라이브 키 오픈 (OMH 측) · Live Key Open","⑬ 첫 예약 · First Booking","⑭ 고객 라이브 확정 (고객 통보) · Customer Live"})) -> ⑧ 개발 착수 · SPEC/DEV 키 · 크리덴셜 · Kickoff / Credential | U15: =IF(COUNT($AH15:$AU15)=0,"",IF(N($P15)>=1,MAX($AH15:$AU15),TODAY())-MIN($AH15:$AU15)) -> 50 | V15: =IF($G15="","",COUNTIF('Chase Log'!$B$4:$B$2000,$G15)) -> 0 | W15: =IF(N($V15)=0,"",_xlfn.MAXIFS('Chase Log'!$E$4:$E$2000,'Chase Log'!$B$4:$B$2000,$G15)) | X15: =IF($W15="","",TODAY()-$W15) | Y15: =IF($W15="","",IF(OR(AND($Q15<>"",N($Q15)>N($W15)),COUNTIFS('Chase Log'!$B$4:$B$2000,$G15,'Chase Log'!$E$4:$E$2000,$W15,'Chase Log'!$I$4:$I$2000,"Y")>0),"",IF(_xlfn.MAXIFS('Chase Log'!$J$4:$J$2000,'Chase Log'!$B$4:$B$2000,$G15,'Chase Log'!$E$4:$E$2000,$W15)=0,"",_xlfn.MAXIFS('Chase Log'!$J$4:$J$2000,'Chase Log'!$B$4:$B$2000,$G15,'Chase Log'!$E$4:$E$2000,$W15)))) | Z15: =IF(OR($G15="",N($P15)>=1,$C15="Live",$D15<>""),"",IF(AND($Y15<>"",N($Y15)>0),IF($Y15<TODAY(),"Chase Overdue","Scheduled"),IF(AND($Q15<>"",N($R15)>='안내 Guide'!$D$4,OR($X15="",N($X15)>='안내 Guide'!$D$4)),"Chase Needed",""))) -> Chase Needed | AC15: OMH 개발 대기 항목 IT 확인 + 상대 착수·완료 일정 재확인(10/10 목표 경과) | AD15: Check pending OMH development items with IT + reconfirm partner's start and completion dates (10 Oct target passed) | AF15: 2026-08-12 | AG15: Tracker | AK15: 46275 | AL15: 46275 | AM15: 46275 | AN15: 46305 | AO15: 46305
A16: =IF($G16="","",ROW()-4) -> 12 | B16: =IF($G16="","",IF($C16<>"",$C16,IF($Q16="","Contact",IF($P16>=1,"Live",IF($P16>=0.8,"Pending Live",IF($P16>=0.7,"Testing",IF($P16>=0.45,"In Development",IF($P16>=0.2,"NDA/Contract","Pipeline")))))))) -> NDA/Contract | E16: 동남아 · SE Asia | F16: Vietnam | G16: Gotadi - HN Branch | H16: 공급 · OMH → Partner | I16: 직접 · Direct | J16: Channel API | K16: Mid | L16: 휴면·재활성화 · Dormant · re-engage | M16: Aiden (지역 공백 · interim) | N16: Partner (client-side) | O16: GSM | P16: =IF($G16="","",IFERROR(LOOKUP(2,1/($AH16:$AU16<>""),$AH$2:$AU$2),0)) -> 0.4 | Q16: =IF(COUNT($AH16:$AU16)=0,"",MAX($AH16:$AU16)) -> 46212 | R16: =IF($Q16="","",TODAY()-$Q16) -> 113 | S16: =IF($G16="","",IF($Q16="","No Record",IF(OR($P16>=1,$C16="Live"),"Live",IF($R16>=90,"Stalled 90d+",IF($R16>=60,"Stalled 60d+",IF($R16>=30,"Stalled 30d+","In Progress")))))) -> Stalled 90d+ | T16: =IF(COUNT($AH16:$AU16)=0,"",LOOKUP(2,1/($AH16:$AU16<>""),{"① 파이프라인 시작 · Pipeline Start","② 제안·소개 발송 · Proposal Sent","③ NDA 발송 · NDA Sent","④ NDA 체결 · NDA Signed","⑤ 계약 체결 · Contract Signed","⑥ SLA 확정 · SLA Finalized","⑦ 개발 착수 예정 · Kickoff Planned","⑧ 개발 착수 · SPEC/DEV 키 · 크리덴셜 · Kickoff / Credential","⑨ 인증 · Certification","⑩ 라이브 테스트 · Live Test","⑪ 개발 완료 예정 · Dev Complete Planned","⑫ 라이브 키 오픈 (OMH 측) · Live Key Open","⑬ 첫 예약 · First Booking","⑭ 고객 라이브 확정 (고객 통보) · Customer Live"})) -> ⑥ SLA 확정 · SLA Finalized | U16: =IF(COUNT($AH16:$AU16)=0,"",IF(N($P16)>=1,MAX($AH16:$AU16),TODAY())-MIN($AH16:$AU16)) -> 113 | V16: =IF($G16="","",COUNTIF('Chase Log'!$B$4:$B$2000,$G16)) -> 1 | W16: =IF(N($V16)=0,"",_xlfn.MAXIFS('Chase Log'!$E$4:$E$2000,'Chase Log'!$B$4:$B$2000,$G16)) -> 46300 | X16: =IF($W16="","",TODAY()-$W16) -> 25 | Y16: =IF($W16="","",IF(OR(AND($Q16<>"",N($Q16)>N($W16)),COUNTIFS('Chase Log'!$B$4:$B$2000,$G16,'Chase Log'!$E$4:$E$2000,$W16,'Chase Log'!$I$4:$I$2000,"Y")>0),"",IF(_xlfn.MAXIFS('Chase Log'!$J$4:$J$2000,'Chase Log'!$B$4:$B$2000,$G16,'Chase Log'!$E$4:$E$2000,$W16)=0,"",_xlfn.MAXIFS('Chase Log'!$J$4:$J$2000,'Chase Log'!$B$4:$B$2000,$G16,'Chase Log'!$E$4:$E$2000,$W16)))) | Z16: =IF(OR($G16="",N($P16)>=1,$C16="Live",$D16<>""),"",IF(AND($Y16<>"",N($Y16)>0),IF($Y16<TODAY(),"Chase Overdue","Scheduled"),IF(AND($Q16<>"",N($R16)>='안내 Guide'!$D$4,OR($X16="",N($X16)>='안내 Guide'!$D$4)),"Chase Needed",""))) -> Chase Needed | AC16: 재가동 회신 2차 체이스 + OMH 측 개발 deliverable·ETA 확정 | AD16: Second chase for re-engagement reply + confirm OMH-side development deliverables and ETA | AF16: 2026-10-05 | AG16: Tracker | AK16: 46212 | AL16: 46212 | AM16: 46212
A17: =IF($G17="","",ROW()-4) -> 13 | B17: =IF($G17="","",IF($C17<>"",$C17,IF($Q17="","Contact",IF($P17>=1,"Live",IF($P17>=0.8,"Pending Live",IF($P17>=0.7,"Testing",IF($P17>=0.45,"In Development",IF($P17>=0.2,"NDA/Contract","Pipeline")))))))) -> NDA/Contract | E17: 중화권 · Greater China | F17: China | G17: Amerilink | H17: 공급 · OMH → Partner | I17: 직접 · Direct | J17: Channel API | K17: Low | L17: — | M17: Grace | N17: Partner (client-side) | O17: GSM | P17: =IF($G17="","",IFERROR(LOOKUP(2,1/($AH17:$AU17<>""),$AH$2:$AU$2),0)) -> 0.2 | Q17: =IF(COUNT($AH17:$AU17)=0,"",MAX($AH17:$AU17)) -> 45957 | R17: =IF($Q17="","",TODAY()-$Q17) -> 368 | S17: =IF($G17="","",IF($Q17="","No Record",IF(OR($P17>=1,$C17="Live"),"Live",IF($R17>=90,"Stalled 90d+",IF($R17>=60,"Stalled 60d+",IF($R17>=30,"Stalled 30d+","In Progress")))))) -> Stalled 90d+ | T17: =IF(COUNT($AH17:$AU17)=0,"",LOOKUP(2,1/($AH17:$AU17<>""),{"① 파이프라인 시작 · Pipeline Start","② 제안·소개 발송 · Proposal Sent","③ NDA 발송 · NDA Sent","④ NDA 체결 · NDA Signed","⑤ 계약 체결 · Contract Signed","⑥ SLA 확정 · SLA Finalized","⑦ 개발 착수 예정 · Kickoff Planned","⑧ 개발 착수 · SPEC/DEV 키 · 크리덴셜 · Kickoff / Credential","⑨ 인증 · Certification","⑩ 라이브 테스트 · Live Test","⑪ 개발 완료 예정 · Dev Complete Planned","⑫ 라이브 키 오픈 (OMH 측) · Live Key Open","⑬ 첫 예약 · First Booking","⑭ 고객 라이브 확정 (고객 통보) · Customer Live"})) -> ④ NDA 체결 · NDA Signed | U17: =IF(COUNT($AH17:$AU17)=0,"",IF(N($P17)>=1,MAX($AH17:$AU17),TODAY())-MIN($AH17:$AU17)) -> 368 | V17: =IF($G17="","",COUNTIF('Chase Log'!$B$4:$B$2000,$G17)) -> 1 | W17: =IF(N($V17)=0,"",_xlfn.MAXIFS('Chase Log'!$E$4:$E$2000,'Chase Log'!$B$4:$B$2000,$G17)) -> 46300 | X17: =IF($W17="","",TODAY()-$W17) -> 25 | Y17: =IF($W17="","",IF(OR(AND($Q17<>"",N($Q17)>N($W17)),COUNTIFS('Chase Log'!$B$4:$B$2000,$G17,'Chase Log'!$E$4:$E$2000,$W17,'Chase Log'!$I$4:$I$2000,"Y")>0),"",IF(_xlfn.MAXIFS('Chase Log'!$J$4:$J$2000,'Chase Log'!$B$4:$B$2000,$G17,'Chase Log'!$E$4:$E$2000,$W17)=0,"",_xlfn.MAXIFS('Chase Log'!$J$4:$J$2000,'Chase Log'!$B$4:$B$2000,$G17,'Chase Log'!$E$4:$E$2000,$W17)))) | Z17: =IF(OR($G17="",N($P17)>=1,$C17="Live",$D17<>""),"",IF(AND($Y17<>"",N($Y17)>0),IF($Y17<TODAY(),"Chase Overdue","Scheduled"),IF(AND($Q17<>"",N($R17)>='안내 Guide'!$D$4,OR($X17="",N($X17)>='안내 Guide'!$D$4)),"Chase Needed",""))) -> Chase Needed | AG17: Tracker | AK17: 45957
A18: =IF($G18="","",ROW()-4) -> 14 | B18: =IF($G18="","",IF($C18<>"",$C18,IF($Q18="","Contact",IF($P18>=1,"Live",IF($P18>=0.8,"Pending Live",IF($P18>=0.7,"Testing",IF($P18>=0.45,"In Development",IF($P18>=0.2,"NDA/Contract","Pipeline")))))))) -> NDA/Contract | E18: 중화권 · Greater China | F18: China | G18: Justgotrip | H18: 공급 · OMH → Partner | I18: 직접 · Direct | J18: Channel API | K18: Low | L18: — | M18: Grace | N18: Partner (client-side) | O18: GSM | P18: =IF($G18="","",IFERROR(LOOKUP(2,1/($AH18:$AU18<>""),$AH$2:$AU$2),0)) -> 0.2 | Q18: =IF(COUNT($AH18:$AU18)=0,"",MAX($AH18:$AU18)) -> 46027 | R18: =IF($Q18="","",TODAY()-$Q18) -> 298 | S18: =IF($G18="","",IF($Q18="","No Record",IF(OR($P18>=1,$C18="Live"),"Live",IF($R18>=90,"Stalled 90d+",IF($R18>=60,"Stalled 60d+",IF($R18>=30,"Stalled 30d+","In Progress")))))) -> Stalled 90d+ | T18: =IF(COUNT($AH18:$AU18)=0,"",LOOKUP(2,1/($AH18:$AU18<>""),{"① 파이프라인 시작 · Pipeline Start","② 제안·소개 발송 · Proposal Sent","③ NDA 발송 · NDA Sent","④ NDA 체결 · NDA Signed","⑤ 계약 체결 · Contract Signed","⑥ SLA 확정 · SLA Finalized","⑦ 개발 착수 예정 · Kickoff Planned","⑧ 개발 착수 · SPEC/DEV 키 · 크리덴셜 · Kickoff / Credential","⑨ 인증 · Certification","⑩ 라이브 테스트 · Live Test","⑪ 개발 완료 예정 · Dev Complete Planned","⑫ 라이브 키 오픈 (OMH 측) · Live Key Open","⑬ 첫 예약 · First Booking","⑭ 고객 라이브 확정 (고객 통보) · Customer Live"})) -> ④ NDA 체결 · NDA Signed | U18: =IF(COUNT($AH18:$AU18)=0,"",IF(N($P18)>=1,MAX($AH18:$AU18),TODAY())-MIN($AH18:$AU18)) -> 298 | V18: =IF($G18="","",COUNTIF('Chase Log'!$B$4:$B$2000,$G18)) -> 1 | W18: =IF(N($V18)=0,"",_xlfn.MAXIFS('Chase Log'!$E$4:$E$2000,'Chase Log'!$B$4:$B$2000,$G18)) -> 46300 | X18: =IF($W18="","",TODAY()-$W18) -> 25 | Y18: =IF($W18="","",IF(OR(AND($Q18<>"",N($Q18)>N($W18)),COUNTIFS('Chase Log'!$B$4:$B$2000,$G18,'Chase Log'!$E$4:$E$2000,$W18,'Chase Log'!$I$4:$I$2000,"Y")>0),"",IF(_xlfn.MAXIFS('Chase Log'!$J$4:$J$2000,'Chase Log'!$B$4:$B$2000,$G18,'Chase Log'!$E$4:$E$2000,$W18)=0,"",_xlfn.MAXIFS('Chase Log'!$J$4:$J$2000,'Chase Log'!$B$4:$B$2000,$G18,'Chase Log'!$E$4:$E$2000,$W18)))) | Z18: =IF(OR($G18="",N($P18)>=1,$C18="Live",$D18<>""),"",IF(AND($Y18<>"",N($Y18)>0),IF($Y18<TODAY(),"Chase Overdue","Scheduled"),IF(AND($Q18<>"",N($R18)>='안내 Guide'!$D$4,OR($X18="",N($X18)>='안내 Guide'!$D$4)),"Chase Needed",""))) -> Chase Needed | AG18: Tracker | AK18: 46027
A19: =IF($G19="","",ROW()-4) -> 15 | B19: =IF($G19="","",IF($C19<>"",$C19,IF($Q19="","Contact",IF($P19>=1,"Live",IF($P19>=0.8,"Pending Live",IF($P19>=0.7,"Testing",IF($P19>=0.45,"In Development",IF($P19>=0.2,"NDA/Contract","Pipeline")))))))) -> NDA/Contract | E19: 중화권 · Greater China | F19: China | G19: Uone | H19: 공급 · OMH → Partner | I19: 직접 · Direct | J19: Channel API | K19: Low | L19: — | M19: Grace | N19: Partner (client-side) | O19: GSM | P19: =IF($G19="","",IFERROR(LOOKUP(2,1/($AH19:$AU19<>""),$AH$2:$AU$2),0)) -> 0.2 | Q19: =IF(COUNT($AH19:$AU19)=0,"",MAX($AH19:$AU19)) -> 45908 | R19: =IF($Q19="","",TODAY()-$Q19) -> 417 | S19: =IF($G19="","",IF($Q19="","No Record",IF(OR($P19>=1,$C19="Live"),"Live",IF($R19>=90,"Stalled 90d+",IF($R19>=60,"Stalled 60d+",IF($R19>=30,"Stalled 30d+","In Progress")))))) -> Stalled 90d+ | T19: =IF(COUNT($AH19:$AU19)=0,"",LOOKUP(2,1/($AH19:$AU19<>""),{"① 파이프라인 시작 · Pipeline Start","② 제안·소개 발송 · Proposal Sent","③ NDA 발송 · NDA Sent","④ NDA 체결 · NDA Signed","⑤ 계약 체결 · Contract Signed","⑥ SLA 확정 · SLA Finalized","⑦ 개발 착수 예정 · Kickoff Planned","⑧ 개발 착수 · SPEC/DEV 키 · 크리덴셜 · Kickoff / Credential","⑨ 인증 · Certification","⑩ 라이브 테스트 · Live Test","⑪ 개발 완료 예정 · Dev Complete Planned","⑫ 라이브 키 오픈 (OMH 측) · Live Key Open","⑬ 첫 예약 · First Booking","⑭ 고객 라이브 확정 (고객 통보) · Customer Live"})) -> ④ NDA 체결 · NDA Signed | U19: =IF(COUNT($AH19:$AU19)=0,"",IF(N($P19)>=1,MAX($AH19:$AU19),TODAY())-MIN($AH19:$AU19)) -> 417 | V19: =IF($G19="","",COUNTIF('Chase Log'!$B$4:$B$2000,$G19)) -> 1 | W19: =IF(N($V19)=0,"",_xlfn.MAXIFS('Chase Log'!$E$4:$E$2000,'Chase Log'!$B$4:$B$2000,$G19)) -> 46300 | X19: =IF($W19="","",TODAY()-$W19) -> 25 | Y19: =IF($W19="","",IF(OR(AND($Q19<>"",N($Q19)>N($W19)),COUNTIFS('Chase Log'!$B$4:$B$2000,$G19,'Chase Log'!$E$4:$E$2000,$W19,'Chase Log'!$I$4:$I$2000,"Y")>0),"",IF(_xlfn.MAXIFS('Chase Log'!$J$4:$J$2000,'Chase Log'!$B$4:$B$2000,$G19,'Chase Log'!$E$4:$E$2000,$W19)=0,"",_xlfn.MAXIFS('Chase Log'!$J$4:$J$2000,'Chase Log'!$B$4:$B$2000,$G19,'Chase Log'!$E$4:$E$2000,$W19)))) | Z19: =IF(OR($G19="",N($P19)>=1,$C19="Live",$D19<>""),"",IF(AND($Y19<>"",N($Y19)>0),IF($Y19<TODAY(),"Chase Overdue","Scheduled"),IF(AND($Q19<>"",N($R19)>='안내 Guide'!$D$4,OR($X19="",N($X19)>='안내 Guide'!$D$4)),"Chase Needed",""))) -> Chase Needed | AG19: Tracker | AK19: 45908
A20: =IF($G20="","",ROW()-4) -> 16 | B20: =IF($G20="","",IF($C20<>"",$C20,IF($Q20="","Contact",IF($P20>=1,"Live",IF($P20>=0.8,"Pending Live",IF($P20>=0.7,"Testing",IF($P20>=0.45,"In Development",IF($P20>=0.2,"NDA/Contract","Pipeline")))))))) -> Pipeline | E20: 중화권 · Greater China | F20: China | G20: U Tour | H20: 공급 · OMH → Partner | I20: 직접 · Direct | J20: Channel API | K20: Mid | L20: 신규 개발 · New lead | M20: Grace | N20: OHMY | O20: GSM | P20: =IF($G20="","",IFERROR(LOOKUP(2,1/($AH20:$AU20<>""),$AH$2:$AU$2),0)) -> 0.1 | Q20: =IF(COUNT($AH20:$AU20)=0,"",MAX($AH20:$AU20)) -> 46308 | R20: =IF($Q20="","",TODAY()-$Q20) -> 17 | S20: =IF($G20="","",IF($Q20="","No Record",IF(OR($P20>=1,$C20="Live"),"Live",IF($R20>=90,"Stalled 90d+",IF($R20>=60,"Stalled 60d+",IF($R20>=30,"Stalled 30d+","In Progress")))))) -> In Progress | T20: =IF(COUNT($AH20:$AU20)=0,"",LOOKUP(2,1/($AH20:$AU20<>""),{"① 파이프라인 시작 · Pipeline Start","② 제안·소개 발송 · Proposal Sent","③ NDA 발송 · NDA Sent","④ NDA 체결 · NDA Signed","⑤ 계약 체결 · Contract Signed","⑥ SLA 확정 · SLA Finalized","⑦ 개발 착수 예정 · Kickoff Planned","⑧ 개발 착수 · SPEC/DEV 키 · 크리덴셜 · Kickoff / Credential","⑨ 인증 · Certification","⑩ 라이브 테스트 · Live Test","⑪ 개발 완료 예정 · Dev Complete Planned","⑫ 라이브 키 오픈 (OMH 측) · Live Key Open","⑬ 첫 예약 · First Booking","⑭ 고객 라이브 확정 (고객 통보) · Customer Live"})) -> ② 제안·소개 발송 · Proposal Sent | U20: =IF(COUNT($AH20:$AU20)=0,"",IF(N($P20)>=1,MAX($AH20:$AU20),TODAY())-MIN($AH20:$AU20)) -> 18 | V20: =IF($G20="","",COUNTIF('Chase Log'!$B$4:$B$2000,$G20)) -> 0 | W20: =IF(N($V20)=0,"",_xlfn.MAXIFS('Chase Log'!$E$4:$E$2000,'Chase Log'!$B$4:$B$2000,$G20)) | X20: =IF($W20="","",TODAY()-$W20) | Y20: =IF($W20="","",IF(OR(AND($Q20<>"",N($Q20)>N($W20)),COUNTIFS('Chase Log'!$B$4:$B$2000,$G20,'Chase Log'!$E$4:$E$2000,$W20,'Chase Log'!$I$4:$I$2000,"Y")>0),"",IF(_xlfn.MAXIFS('Chase Log'!$J$4:$J$2000,'Chase Log'!$B$4:$B$2000,$G20,'Chase Log'!$E$4:$E$2000,$W20)=0,"",_xlfn.MAXIFS('Chase Log'!$J$4:$J$2000,'Chase Log'!$B$4:$B$2000,$G20,'Chase Log'!$E$4:$E$2000,$W20)))) | Z20: =IF(OR($G20="",N($P20)>=1,$C20="Live",$D20<>""),"",IF(AND($Y20<>"",N($Y20)>0),IF($Y20<TODAY(),"Chase Overdue","Scheduled"),IF(AND($Q20<>"",N($R20)>='안내 Guide'!$D$4,OR($X20="",N($X20)>='안내 Guide'!$D$4)),"Chase Needed",""))) -> Chase Needed | AB20: Partner | AC20: 호텔 리스트 송부 + Open API 개발 요청(Aiden) + CNY 정산 가능 여부 확인(T54) | AD20: Send hotel list + request Open API development (Aiden) + confirm whether CNY settlement is possible (T54) | AF20: 2026-10-12 | AG20: Tracker | AH20: 46307 | AI20: 46308
A21: =IF($G21="","",ROW()-4) -> 17 | B21: =IF($G21="","",IF($C21<>"",$C21,IF($Q21="","Contact",IF($P21>=1,"Live",IF($P21>=0.8,"Pending Live",IF($P21>=0.7,"Testing",IF($P21>=0.45,"In Development",IF($P21>=0.2,"NDA/Contract","Pipeline")))))))) -> Pipeline | E21: 인도 · India | F21: India | G21: MakeMyTrip | H21: 공급 · OMH → Partner | I21: 직접 · Direct | J21: Channel API | K21: High | L21: 계약 협상 중 · Contract talks | M21: Aiden (지역 공백 · interim) | N21: OHMY | O21: GSM | P21: =IF($G21="","",IFERROR(LOOKUP(2,1/($AH21:$AU21<>""),$AH$2:$AU$2),0)) -> 0.1 | Q21: =IF(COUNT($AH21:$AU21)=0,"",MAX($AH21:$AU21)) -> 46268 | R21: =IF($Q21="","",TODAY()-$Q21) -> 57 | S21: =IF($G21="","",IF($Q21="","No Record",IF(OR($P21>=1,$C21="Live"),"Live",IF($R21>=90,"Stalled 90d+",IF($R21>=60,"Stalled 60d+",IF($R21>=30,"Stalled 30d+","In Progress")))))) -> Stalled 30d+ | T21: =IF(COUNT($AH21:$AU21)=0,"",LOOKUP(2,1/($AH21:$AU21<>""),{"① 파이프라인 시작 · Pipeline Start","② 제안·소개 발송 · Proposal Sent","③ NDA 발송 · NDA Sent","④ NDA 체결 · NDA Signed","⑤ 계약 체결 · Contract Signed","⑥ SLA 확정 · SLA Finalized","⑦ 개발 착수 예정 · Kickoff Planned","⑧ 개발 착수 · SPEC/DEV 키 · 크리덴셜 · Kickoff / Credential","⑨ 인증 · Certification","⑩ 라이브 테스트 · Live Test","⑪ 개발 완료 예정 · Dev Complete Planned","⑫ 라이브 키 오픈 (OMH 측) · Live Key Open","⑬ 첫 예약 · First Booking","⑭ 고객 라이브 확정 (고객 통보) · Customer Live"})) -> ② 제안·소개 발송 · Proposal Sent | U21: =IF(COUNT($AH21:$AU21)=0,"",IF(N($P21)>=1,MAX($AH21:$AU21),TODAY())-MIN($AH21:$AU21)) -> 60 | V21: =IF($G21="","",COUNTIF('Chase Log'!$B$4:$B$2000,$G21)) -> 3 | W21: =IF(N($V21)=0,"",_xlfn.MAXIFS('Chase Log'!$E$4:$E$2000,'Chase Log'!$B$4:$B$2000,$G21)) -> 46318 | X21: =IF($W21="","",TODAY()-$W21) -> 7 | Y21: =IF($W21="","",IF(OR(AND($Q21<>"",N($Q21)>N($W21)),COUNTIFS('Chase Log'!$B$4:$B$2000,$G21,'Chase Log'!$E$4:$E$2000,$W21,'Chase Log'!$I$4:$I$2000,"Y")>0),"",IF(_xlfn.MAXIFS('Chase Log'!$J$4:$J$2000,'Chase Log'!$B$4:$B$2000,$G21,'Chase Log'!$E$4:$E$2000,$W21)=0,"",_xlfn.MAXIFS('Chase Log'!$J$4:$J$2000,'Chase Log'!$B$4:$B$2000,$G21,'Chase Log'!$E$4:$E$2000,$W21)))) -> 46325 | Z21: =IF(OR($G21="",N($P21)>=1,$C21="Live",$D21<>""),"",IF(AND($Y21<>"",N($Y21)>0),IF($Y21<TODAY(),"Chase Overdue","Scheduled"),IF(AND($Q21<>"",N($R21)>='안내 Guide'!$D$4,OR($X21="",N($X21)>='안내 Guide'!$D$4)),"Chase Needed",""))) -> Scheduled | AA21: 46491 | AC21: MMT 법무 검토 회신 체이스(10/18 수정 표시본)·Bank Transfer 합의, 요금 경쟁력 회신 체이스, ITB Asia(10/23 13:00) Vivek kumar 미팅 | AD21: Chase MMT legal review reply (18 Oct redline) and agree Bank Transfer; chase reply on rate competitiveness; ITB Asia meeting with Vivek kumar (23 Oct 13:00) | AE21: Develop OPEN API | AF21: 2026-10-18 | AG21: Tracker | AH21: 46265 | AI21: 46268
A22: =IF($G22="","",ROW()-4) -> 18 | B22: =IF($G22="","",IF($C22<>"",$C22,IF($Q22="","Contact",IF($P22>=1,"Live",IF($P22>=0.8,"Pending Live",IF($P22>=0.7,"Testing",IF($P22>=0.45,"In Development",IF($P22>=0.2,"NDA/Contract","Pipeline")))))))) -> Contact | E22: 중화권 · Greater China | F22: China | G22: Chai Yi Lc -Yihao | H22: 공급 · OMH → Partner | I22: 직접 · Direct | J22: Channel API | K22: High | L22: — | M22: Grace | N22: Partner (client-side) | O22: GSM | P22: =IF($G22="","",IFERROR(LOOKUP(2,1/($AH22:$AU22<>""),$AH$2:$AU$2),0)) -> 0 | Q22: =IF(COUNT($AH22:$AU22)=0,"",MAX($AH22:$AU22)) | R22: =IF($Q22="","",TODAY()-$Q22) | S22: =IF($G22="","",IF($Q22="","No Record",IF(OR($P22>=1,$C22="Live"),"Live",IF($R22>=90,"Stalled 90d+",IF($R22>=60,"Stalled 60d+",IF($R22>=30,"Stalled 30d+","In Progress")))))) -> No Record | T22: =IF(COUNT($AH22:$AU22)=0,"",LOOKUP(2,1/($AH22:$AU22<>""),{"① 파이프라인 시작 · Pipeline Start","② 제안·소개 발송 · Proposal Sent","③ NDA 발송 · NDA Sent","④ NDA 체결 · NDA Signed","⑤ 계약 체결 · Contract Signed","⑥ SLA 확정 · SLA Finalized","⑦ 개발 착수 예정 · Kickoff Planned","⑧ 개발 착수 · SPEC/DEV 키 · 크리덴셜 · Kickoff / Credential","⑨ 인증 · Certification","⑩ 라이브 테스트 · Live Test","⑪ 개발 완료 예정 · Dev Complete Planned","⑫ 라이브 키 오픈 (OMH 측) · Live Key Open","⑬ 첫 예약 · First Booking","⑭ 고객 라이브 확정 (고객 통보) · Customer Live"})) | U22: =IF(COUNT($AH22:$AU22)=0,"",IF(N($P22)>=1,MAX($AH22:$AU22),TODAY())-MIN($AH22:$AU22)) | V22: =IF($G22="","",COUNTIF('Chase Log'!$B$4:$B$2000,$G22)) -> 0 | W22: =IF(N($V22)=0,"",_xlfn.MAXIFS('Chase Log'!$E$4:$E$2000,'Chase Log'!$B$4:$B$2000,$G22)) | X22: =IF($W22="","",TODAY()-$W22) | Y22: =IF($W22="","",IF(OR(AND($Q22<>"",N($Q22)>N($W22)),COUNTIFS('Chase Log'!$B$4:$B$2000,$G22,'Chase Log'!$E$4:$E$2000,$W22,'Chase Log'!$I$4:$I$2000,"Y")>0),"",IF(_xlfn.MAXIFS('Chase Log'!$J$4:$J$2000,'Chase Log'!$B$4:$B$2000,$G22,'Chase Log'!$E$4:$E$2000,$W22)=0,"",_xlfn.MAXIFS('Chase Log'!$J$4:$J$2000,'Chase Log'!$B$4:$B$2000,$G22,'Chase Log'!$E$4:$E$2000,$W22)))) | Z22: =IF(OR($G22="",N($P22)>=1,$C22="Live",$D22<>""),"",IF(AND($Y22<>"",N($Y22)>0),IF($Y22<TODAY(),"Chase Overdue","Scheduled"),IF(AND($Q22<>"",N($R22)>='안내 Guide'!$D$4,OR($X22="",N($X22)>='안내 Guide'!$D$4)),"Chase Needed",""))) | AG22: Tracker
A23: =IF($G23="","",ROW()-4) -> 19 | B23: =IF($G23="","",IF($C23<>"",$C23,IF($Q23="","Contact",IF($P23>=1,"Live",IF($P23>=0.8,"Pending Live",IF($P23>=0.7,"Testing",IF($P23>=0.45,"In Development",IF($P23>=0.2,"NDA/Contract","Pipeline")))))))) -> Contact | E23: 중화권 · Greater China | F23: China | G23: CN Booking | H23: 공급 · OMH → Partner | I23: 직접 · Direct | J23: Channel API | K23: Mid | L23: — | M23: Grace | N23: Partner (client-side) | O23: GSM | P23: =IF($G23="","",IFERROR(LOOKUP(2,1/($AH23:$AU23<>""),$AH$2:$AU$2),0)) -> 0 | Q23: =IF(COUNT($AH23:$AU23)=0,"",MAX($AH23:$AU23)) | R23: =IF($Q23="","",TODAY()-$Q23) | S23: =IF($G23="","",IF($Q23="","No Record",IF(OR($P23>=1,$C23="Live"),"Live",IF($R23>=90,"Stalled 90d+",IF($R23>=60,"Stalled 60d+",IF($R23>=30,"Stalled 30d+","In Progress")))))) -> No Record | T23: =IF(COUNT($AH23:$AU23)=0,"",LOOKUP(2,1/($AH23:$AU23<>""),{"① 파이프라인 시작 · Pipeline Start","② 제안·소개 발송 · Proposal Sent","③ NDA 발송 · NDA Sent","④ NDA 체결 · NDA Signed","⑤ 계약 체결 · Contract Signed","⑥ SLA 확정 · SLA Finalized","⑦ 개발 착수 예정 · Kickoff Planned","⑧ 개발 착수 · SPEC/DEV 키 · 크리덴셜 · Kickoff / Credential","⑨ 인증 · Certification","⑩ 라이브 테스트 · Live Test","⑪ 개발 완료 예정 · Dev Complete Planned","⑫ 라이브 키 오픈 (OMH 측) · Live Key Open","⑬ 첫 예약 · First Booking","⑭ 고객 라이브 확정 (고객 통보) · Customer Live"})) | U23: =IF(COUNT($AH23:$AU23)=0,"",IF(N($P23)>=1,MAX($AH23:$AU23),TODAY())-MIN($AH23:$AU23)) | V23: =IF($G23="","",COUNTIF('Chase Log'!$B$4:$B$2000,$G23)) -> 0 | W23: =IF(N($V23)=0,"",_xlfn.MAXIFS('Chase Log'!$E$4:$E$2000,'Chase Log'!$B$4:$B$2000,$G23)) | X23: =IF($W23="","",TODAY()-$W23) | Y23: =IF($W23="","",IF(OR(AND($Q23<>"",N($Q23)>N($W23)),COUNTIFS('Chase Log'!$B$4:$B$2000,$G23,'Chase Log'!$E$4:$E$2000,$W23,'Chase Log'!$I$4:$I$2000,"Y")>0),"",IF(_xlfn.MAXIFS('Chase Log'!$J$4:$J$2000,'Chase Log'!$B$4:$B$2000,$G23,'Chase Log'!$E$4:$E$2000,$W23)=0,"",_xlfn.MAXIFS('Chase Log'!$J$4:$J$2000,'Chase Log'!$B$4:$B$2000,$G23,'Chase Log'!$E$4:$E$2000,$W23)))) | Z23: =IF(OR($G23="",N($P23)>=1,$C23="Live",$D23<>""),"",IF(AND($Y23<>"",N($Y23)>0),IF($Y23<TODAY(),"Chase Overdue","Scheduled"),IF(AND($Q23<>"",N($R23)>='안내 Guide'!$D$4,OR($X23="",N($X23)>='안내 Guide'!$D$4)),"Chase Needed",""))) | AG23: Tracker
A24: =IF($G24="","",ROW()-4) -> 20 | B24: =IF($G24="","",IF($C24<>"",$C24,IF($Q24="","Contact",IF($P24>=1,"Live",IF($P24>=0.8,"Pending Live",IF($P24>=0.7,"Testing",IF($P24>=0.45,"In Development",IF($P24>=0.2,"NDA/Contract","Pipeline")))))))) -> NDA/Contract | C24: NDA/Contract | E24: 중화권 · Greater China | F24: China | G24: Didi TMC | H24: 공급 · OMH → Partner | I24: 직접 · Direct | J24: Channel API | K24: High | L24: 신규 개발 · New lead | M24: Grace | N24: Partner (client-side) | O24: GSM | P24: =IF($G24="","",IFERROR(LOOKUP(2,1/($AH24:$AU24<>""),$AH$2:$AU$2),0)) -> 0 | Q24: =IF(COUNT($AH24:$AU24)=0,"",MAX($AH24:$AU24)) | R24: =IF($Q24="","",TODAY()-$Q24) | S24: =IF($G24="","",IF($Q24="","No Record",IF(OR($P24>=1,$C24="Live"),"Live",IF($R24>=90,"Stalled 90d+",IF($R24>=60,"Stalled 60d+",IF($R24>=30,"Stalled 30d+","In Progress")))))) -> No Record | T24: =IF(COUNT($AH24:$AU24)=0,"",LOOKUP(2,1/($AH24:$AU24<>""),{"① 파이프라인 시작 · Pipeline Start","② 제안·소개 발송 · Proposal Sent","③ NDA 발송 · NDA Sent","④ NDA 체결 · NDA Signed","⑤ 계약 체결 · Contract Signed","⑥ SLA 확정 · SLA Finalized","⑦ 개발 착수 예정 · Kickoff Planned","⑧ 개발 착수 · SPEC/DEV 키 · 크리덴셜 · Kickoff / Credential","⑨ 인증 · Certification","⑩ 라이브 테스트 · Live Test","⑪ 개발 완료 예정 · Dev Complete Planned","⑫ 라이브 키 오픈 (OMH 측) · Live Key Open","⑬ 첫 예약 · First Booking","⑭ 고객 라이브 확정 (고객 통보) · Customer Live"})) | U24: =IF(COUNT($AH24:$AU24)=0,"",IF(N($P24)>=1,MAX($AH24:$AU24),TODAY())-MIN($AH24:$AU24)) | V24: =IF($G24="","",COUNTIF('Chase Log'!$B$4:$B$2000,$G24)) -> 0 | W24: =IF(N($V24)=0,"",_xlfn.MAXIFS('Chase Log'!$E$4:$E$2000,'Chase Log'!$B$4:$B$2000,$G24)) | X24: =IF($W24="","",TODAY()-$W24) | Y24: =IF($W24="","",IF(OR(AND($Q24<>"",N($Q24)>N($W24)),COUNTIFS('Chase Log'!$B$4:$B$2000,$G24,'Chase Log'!$E$4:$E$2000,$W24,'Chase Log'!$I$4:$I$2000,"Y")>0),"",IF(_xlfn.MAXIFS('Chase Log'!$J$4:$J$2000,'Chase Log'!$B$4:$B$2000,$G24,'Chase Log'!$E$4:$E$2000,$W24)=0,"",_xlfn.MAXIFS('Chase Log'!$J$4:$J$2000,'Chase Log'!$B$4:$B$2000,$G24,'Chase Log'!$E$4:$E$2000,$W24)))) | Z24: =IF(OR($G24="",N($P24)>=1,$C24="Live",$D24<>""),"",IF(AND($Y24<>"",N($Y24)>0),IF($Y24<TODAY(),"Chase Overdue","Scheduled"),IF(AND($Q24<>"",N($R24)>='안내 Guide'!$D$4,OR($X24="",N($X24)>='안내 Guide'!$D$4)),"Chase Needed",""))) | AC24: ITB Asia 10/22 15:00 DiDi Enterprise Solutions 미팅 — 동일 회사 여부 확인·결과 기록 | AD24: ITB Asia meeting with DiDi Enterprise Solutions 22 Oct 15:00 — confirm whether it is the same company and record outcome | AF24: 미확인 | AG24: Tracker
A25: =IF($G25="","",ROW()-4) -> 21 | B25: =IF($G25="","",IF($C25<>"",$C25,IF($Q25="","Contact",IF($P25>=1,"Live",IF($P25>=0.8,"Pending Live",IF($P25>=0.7,"Testing",IF($P25>=0.45,"In Development",IF($P25>=0.2,"NDA/Contract","Pipeline")))))))) -> Contact | E25: 중화권 · Greater China | F25: China | G25: Fenbeitong | H25: 공급 · OMH → Partner | I25: 직접 · Direct | J25: Channel API | K25: High | L25: 신규 개발 · New lead | M25: Grace | N25: Partner (client-side) | O25: GSM | P25: =IF($G25="","",IFERROR(LOOKUP(2,1/($AH25:$AU25<>""),$AH$2:$AU$2),0)) -> 0 | Q25: =IF(COUNT($AH25:$AU25)=0,"",MAX($AH25:$AU25)) | R25: =IF($Q25="","",TODAY()-$Q25) | S25: =IF($G25="","",IF($Q25="","No Record",IF(OR($P25>=1,$C25="Live"),"Live",IF($R25>=90,"Stalled 90d+",IF($R25>=60,"Stalled 60d+",IF($R25>=30,"Stalled 30d+","In Progress")))))) -> No Record | T25: =IF(COUNT($AH25:$AU25)=0,"",LOOKUP(2,1/($AH25:$AU25<>""),{"① 파이프라인 시작 · Pipeline Start","② 제안·소개 발송 · Proposal Sent","③ NDA 발송 · NDA Sent","④ NDA 체결 · NDA Signed","⑤ 계약 체결 · Contract Signed","⑥ SLA 확정 · SLA Finalized","⑦ 개발 착수 예정 · Kickoff Planned","⑧ 개발 착수 · SPEC/DEV 키 · 크리덴셜 · Kickoff / Credential","⑨ 인증 · Certification","⑩ 라이브 테스트 · Live Test","⑪ 개발 완료 예정 · Dev Complete Planned","⑫ 라이브 키 오픈 (OMH 측) · Live Key Open","⑬ 첫 예약 · First Booking","⑭ 고객 라이브 확정 (고객 통보) · Customer Live"})) | U25: =IF(COUNT($AH25:$AU25)=0,"",IF(N($P25)>=1,MAX($AH25:$AU25),TODAY())-MIN($AH25:$AU25)) | V25: =IF($G25="","",COUNTIF('Chase Log'!$B$4:$B$2000,$G25)) -> 0 | W25: =IF(N($V25)=0,"",_xlfn.MAXIFS('Chase Log'!$E$4:$E$2000,'Chase Log'!$B$4:$B$2000,$G25)) | X25: =IF($W25="","",TODAY()-$W25) | Y25: =IF($W25="","",IF(OR(AND($Q25<>"",N($Q25)>N($W25)),COUNTIFS('Chase Log'!$B$4:$B$2000,$G25,'Chase Log'!$E$4:$E$2000,$W25,'Chase Log'!$I$4:$I$2000,"Y")>0),"",IF(_xlfn.MAXIFS('Chase Log'!$J$4:$J$2000,'Chase Log'!$B$4:$B$2000,$G25,'Chase Log'!$E$4:$E$2000,$W25)=0,"",_xlfn.MAXIFS('Chase Log'!$J$4:$J$2000,'Chase Log'!$B$4:$B$2000,$G25,'Chase Log'!$E$4:$E$2000,$W25)))) | Z25: =IF(OR($G25="",N($P25)>=1,$C25="Live",$D25<>""),"",IF(AND($Y25<>"",N($Y25)>0),IF($Y25<TODAY(),"Chase Overdue","Scheduled"),IF(AND($Q25<>"",N($R25)>='안내 Guide'!$D$4,OR($X25="",N($X25)>='안내 Guide'!$D$4)),"Chase Needed",""))) | AC25: VN SCM(DK) 소싱 결과 받아 FBT에 박닌·박장 산업단지 호텔 제안 + 위안화 정산 경로 확인(T54) | AD25: Get sourcing results from VN SCM (DK) and propose hotels in Bac Ninh/Bac Giang industrial parks to FBT + confirm CNY settlement route (T54) | AF25: 2026-10-12 | AG25: Tracker
A26: =IF($G26="","",ROW()-4) -> 22 | B26: =IF($G26="","",IF($C26<>"",$C26,IF($Q26="","Contact",IF($P26>=1,"Live",IF($P26>=0.8,"Pending Live",IF($P26>=0.7,"Testing",IF($P26>=0.45,"In Development",IF($P26>=0.2,"NDA/Contract","Pipeline")))))))) -> Contact | E26: 중화권 · Greater China | F26: China | G26: Joy Travel | H26: 공급 · OMH → Partner | I26: 직접 · Direct | J26: Channel API | K26: Low | L26: — | M26: Grace | N26: Partner (client-side) | O26: GSM | P26: =IF($G26="","",IFERROR(LOOKUP(2,1/($AH26:$AU26<>""),$AH$2:$AU$2),0)) -> 0 | Q26: =IF(COUNT($AH26:$AU26)=0,"",MAX($AH26:$AU26)) | R26: =IF($Q26="","",TODAY()-$Q26) | S26: =IF($G26="","",IF($Q26="","No Record",IF(OR($P26>=1,$C26="Live"),"Live",IF($R26>=90,"Stalled 90d+",IF($R26>=60,"Stalled 60d+",IF($R26>=30,"Stalled 30d+","In Progress")))))) -> No Record | T26: =IF(COUNT($AH26:$AU26)=0,"",LOOKUP(2,1/($AH26:$AU26<>""),{"① 파이프라인 시작 · Pipeline Start","② 제안·소개 발송 · Proposal Sent","③ NDA 발송 · NDA Sent","④ NDA 체결 · NDA Signed","⑤ 계약 체결 · Contract Signed","⑥ SLA 확정 · SLA Finalized","⑦ 개발 착수 예정 · Kickoff Planned","⑧ 개발 착수 · SPEC/DEV 키 · 크리덴셜 · Kickoff / Credential","⑨ 인증 · Certification","⑩ 라이브 테스트 · Live Test","⑪ 개발 완료 예정 · Dev Complete Planned","⑫ 라이브 키 오픈 (OMH 측) · Live Key Open","⑬ 첫 예약 · First Booking","⑭ 고객 라이브 확정 (고객 통보) · Customer Live"})) | U26: =IF(COUNT($AH26:$AU26)=0,"",IF(N($P26)>=1,MAX($AH26:$AU26),TODAY())-MIN($AH26:$AU26)) | V26: =IF($G26="","",COUNTIF('Chase Log'!$B$4:$B$2000,$G26)) -> 0 | W26: =IF(N($V26)=0,"",_xlfn.MAXIFS('Chase Log'!$E$4:$E$2000,'Chase Log'!$B$4:$B$2000,$G26)) | X26: =IF($W26="","",TODAY()-$W26) | Y26: =IF($W26="","",IF(OR(AND($Q26<>"",N($Q26)>N($W26)),COUNTIFS('Chase Log'!$B$4:$B$2000,$G26,'Chase Log'!$E$4:$E$2000,$W26,'Chase Log'!$I$4:$I$2000,"Y")>0),"",IF(_xlfn.MAXIFS('Chase Log'!$J$4:$J$2000,'Chase Log'!$B$4:$B$2000,$G26,'Chase Log'!$E$4:$E$2000,$W26)=0,"",_xlfn.MAXIFS('Chase Log'!$J$4:$J$2000,'Chase Log'!$B$4:$B$2000,$G26,'Chase Log'!$E$4:$E$2000,$W26)))) | Z26: =IF(OR($G26="",N($P26)>=1,$C26="Live",$D26<>""),"",IF(AND($Y26<>"",N($Y26)>0),IF($Y26<TODAY(),"Chase Overdue","Scheduled"),IF(AND($Q26<>"",N($R26)>='안내 Guide'!$D$4,OR($X26="",N($X26)>='안내 Guide'!$D$4)),"Chase Needed",""))) | AG26: Tracker
A27: =IF($G27="","",ROW()-4) -> 23 | B27: =IF($G27="","",IF($C27<>"",$C27,IF($Q27="","Contact",IF($P27>=1,"Live",IF($P27>=0.8,"Pending Live",IF($P27>=0.7,"Testing",IF($P27>=0.45,"In Development",IF($P27>=0.2,"NDA/Contract","Pipeline")))))))) -> Contact | E27: 중화권 · Greater China | F27: China | G27: Linkall travel | H27: 공급 · OMH → Partner | I27: 직접 · Direct | J27: Channel API | K27: Mid | L27: — | M27: Grace | N27: Partner (client-side) | O27: GSM | P27: =IF($G27="","",IFERROR(LOOKUP(2,1/($AH27:$AU27<>""),$AH$2:$AU$2),0)) -> 0 | Q27: =IF(COUNT($AH27:$AU27)=0,"",MAX($AH27:$AU27)) | R27: =IF($Q27="","",TODAY()-$Q27) | S27: =IF($G27="","",IF($Q27="","No Record",IF(OR($P27>=1,$C27="Live"),"Live",IF($R27>=90,"Stalled 90d+",IF($R27>=60,"Stalled 60d+",IF($R27>=30,"Stalled 30d+","In Progress")))))) -> No Record | T27: =IF(COUNT($AH27:$AU27)=0,"",LOOKUP(2,1/($AH27:$AU27<>""),{"① 파이프라인 시작 · Pipeline Start","② 제안·소개 발송 · Proposal Sent","③ NDA 발송 · NDA Sent","④ NDA 체결 · NDA Signed","⑤ 계약 체결 · Contract Signed","⑥ SLA 확정 · SLA Finalized","⑦ 개발 착수 예정 · Kickoff Planned","⑧ 개발 착수 · SPEC/DEV 키 · 크리덴셜 · Kickoff / Credential","⑨ 인증 · Certification","⑩ 라이브 테스트 · Live Test","⑪ 개발 완료 예정 · Dev Complete Planned","⑫ 라이브 키 오픈 (OMH 측) · Live Key Open","⑬ 첫 예약 · First Booking","⑭ 고객 라이브 확정 (고객 통보) · Customer Live"})) | U27: =IF(COUNT($AH27:$AU27)=0,"",IF(N($P27)>=1,MAX($AH27:$AU27),TODAY())-MIN($AH27:$AU27)) | V27: =IF($G27="","",COUNTIF('Chase Log'!$B$4:$B$2000,$G27)) -> 0 | W27: =IF(N($V27)=0,"",_xlfn.MAXIFS('Chase Log'!$E$4:$E$2000,'Chase Log'!$B$4:$B$2000,$G27)) | X27: =IF($W27="","",TODAY()-$W27) | Y27: =IF($W27="","",IF(OR(AND($Q27<>"",N($Q27)>N($W27)),COUNTIFS('Chase Log'!$B$4:$B$2000,$G27,'Chase Log'!$E$4:$E$2000,$W27,'Chase Log'!$I$4:$I$2000,"Y")>0),"",IF(_xlfn.MAXIFS('Chase Log'!$J$4:$J$2000,'Chase Log'!$B$4:$B$2000,$G27,'Chase Log'!$E$4:$E$2000,$W27)=0,"",_xlfn.MAXIFS('Chase Log'!$J$4:$J$2000,'Chase Log'!$B$4:$B$2000,$G27,'Chase Log'!$E$4:$E$2000,$W27)))) | Z27: =IF(OR($G27="",N($P27)>=1,$C27="Live",$D27<>""),"",IF(AND($Y27<>"",N($Y27)>0),IF($Y27<TODAY(),"Chase Overdue","Scheduled"),IF(AND($Q27<>"",N($R27)>='안내 Guide'!$D$4,OR($X27="",N($X27)>='안내 Guide'!$D$4)),"Chase Needed",""))) | AG27: Tracker
A28: =IF($G28="","",ROW()-4) -> 24 | B28: =IF($G28="","",IF($C28<>"",$C28,IF($Q28="","Contact",IF($P28>=1,"Live",IF($P28>=0.8,"Pending Live",IF($P28>=0.7,"Testing",IF($P28>=0.45,"In Development",IF($P28>=0.2,"NDA/Contract","Pipeline")))))))) -> Contact | E28: 중화권 · Greater China | F28: China | G28: Mafengwo | H28: 공급 · OMH → Partner | I28: 직접 · Direct | J28: Channel API | K28: Mid | L28: — | M28: Grace | N28: Partner (client-side) | O28: GSM | P28: =IF($G28="","",IFERROR(LOOKUP(2,1/($AH28:$AU28<>""),$AH$2:$AU$2),0)) -> 0 | Q28: =IF(COUNT($AH28:$AU28)=0,"",MAX($AH28:$AU28)) | R28: =IF($Q28="","",TODAY()-$Q28) | S28: =IF($G28="","",IF($Q28="","No Record",IF(OR($P28>=1,$C28="Live"),"Live",IF($R28>=90,"Stalled 90d+",IF($R28>=60,"Stalled 60d+",IF($R28>=30,"Stalled 30d+","In Progress")))))) -> No Record | T28: =IF(COUNT($AH28:$AU28)=0,"",LOOKUP(2,1/($AH28:$AU28<>""),{"① 파이프라인 시작 · Pipeline Start","② 제안·소개 발송 · Proposal Sent","③ NDA 발송 · NDA Sent","④ NDA 체결 · NDA Signed","⑤ 계약 체결 · Contract Signed","⑥ SLA 확정 · SLA Finalized","⑦ 개발 착수 예정 · Kickoff Planned","⑧ 개발 착수 · SPEC/DEV 키 · 크리덴셜 · Kickoff / Credential","⑨ 인증 · Certification","⑩ 라이브 테스트 · Live Test","⑪ 개발 완료 예정 · Dev Complete Planned","⑫ 라이브 키 오픈 (OMH 측) · Live Key Open","⑬ 첫 예약 · First Booking","⑭ 고객 라이브 확정 (고객 통보) · Customer Live"})) | U28: =IF(COUNT($AH28:$AU28)=0,"",IF(N($P28)>=1,MAX($AH28:$AU28),TODAY())-MIN($AH28:$AU28)) | V28: =IF($G28="","",COUNTIF('Chase Log'!$B$4:$B$2000,$G28)) -> 0 | W28: =IF(N($V28)=0,"",_xlfn.MAXIFS('Chase Log'!$E$4:$E$2000,'Chase Log'!$B$4:$B$2000,$G28)) | X28: =IF($W28="","",TODAY()-$W28) | Y28: =IF($W28="","",IF(OR(AND($Q28<>"",N($Q28)>N($W28)),COUNTIFS('Chase Log'!$B$4:$B$2000,$G28,'Chase Log'!$E$4:$E$2000,$W28,'Chase Log'!$I$4:$I$2000,"Y")>0),"",IF(_xlfn.MAXIFS('Chase Log'!$J$4:$J$2000,'Chase Log'!$B$4:$B$2000,$G28,'Chase Log'!$E$4:$E$2000,$W28)=0,"",_xlfn.MAXIFS('Chase Log'!$J$4:$J$2000,'Chase Log'!$B$4:$B$2000,$G28,'Chase Log'!$E$4:$E$2000,$W28)))) | Z28: =IF(OR($G28="",N($P28)>=1,$C28="Live",$D28<>""),"",IF(AND($Y28<>"",N($Y28)>0),IF($Y28<TODAY(),"Chase Overdue","Scheduled"),IF(AND($Q28<>"",N($R28)>='안내 Guide'!$D$4,OR($X28="",N($X28)>='안내 Guide'!$D$4)),"Chase Needed",""))) | AG28: Tracker
A29: =IF($G29="","",ROW()-4) -> 25 | B29: =IF($G29="","",IF($C29<>"",$C29,IF($Q29="","Contact",IF($P29>=1,"Live",IF($P29>=0.8,"Pending Live",IF($P29>=0.7,"Testing",IF($P29>=0.45,"In Development",IF($P29>=0.2,"NDA/Contract","Pipeline")))))))) -> Contact | E29: 중화권 · Greater China | F29: China | G29: Meiya | H29: 공급 · OMH → Partner | I29: 직접 · Direct | J29: Channel API | K29: High | L29: — | M29: Grace | N29: Partner (client-side) | O29: GSM | P29: =IF($G29="","",IFERROR(LOOKUP(2,1/($AH29:$AU29<>""),$AH$2:$AU$2),0)) -> 0 | Q29: =IF(COUNT($AH29:$AU29)=0,"",MAX($AH29:$AU29)) | R29: =IF($Q29="","",TODAY()-$Q29) | S29: =IF($G29="","",IF($Q29="","No Record",IF(OR($P29>=1,$C29="Live"),"Live",IF($R29>=90,"Stalled 90d+",IF($R29>=60,"Stalled 60d+",IF($R29>=30,"Stalled 30d+","In Progress")))))) -> No Record | T29: =IF(COUNT($AH29:$AU29)=0,"",LOOKUP(2,1/($AH29:$AU29<>""),{"① 파이프라인 시작 · Pipeline Start","② 제안·소개 발송 · Proposal Sent","③ NDA 발송 · NDA Sent","④ NDA 체결 · NDA Signed","⑤ 계약 체결 · Contract Signed","⑥ SLA 확정 · SLA Finalized","⑦ 개발 착수 예정 · Kickoff Planned","⑧ 개발 착수 · SPEC/DEV 키 · 크리덴셜 · Kickoff / Credential","⑨ 인증 · Certification","⑩ 라이브 테스트 · Live Test","⑪ 개발 완료 예정 · Dev Complete Planned","⑫ 라이브 키 오픈 (OMH 측) · Live Key Open","⑬ 첫 예약 · First Booking","⑭ 고객 라이브 확정 (고객 통보) · Customer Live"})) | U29: =IF(COUNT($AH29:$AU29)=0,"",IF(N($P29)>=1,MAX($AH29:$AU29),TODAY())-MIN($AH29:$AU29)) | V29: =IF($G29="","",COUNTIF('Chase Log'!$B$4:$B$2000,$G29)) -> 0 | W29: =IF(N($V29)=0,"",_xlfn.MAXIFS('Chase Log'!$E$4:$E$2000,'Chase Log'!$B$4:$B$2000,$G29)) | X29: =IF($W29="","",TODAY()-$W29) | Y29: =IF($W29="","",IF(OR(AND($Q29<>"",N($Q29)>N($W29)),COUNTIFS('Chase Log'!$B$4:$B$2000,$G29,'Chase Log'!$E$4:$E$2000,$W29,'Chase Log'!$I$4:$I$2000,"Y")>0),"",IF(_xlfn.MAXIFS('Chase Log'!$J$4:$J$2000,'Chase Log'!$B$4:$B$2000,$G29,'Chase Log'!$E$4:$E$2000,$W29)=0,"",_xlfn.MAXIFS('Chase Log'!$J$4:$J$2000,'Chase Log'!$B$4:$B$2000,$G29,'Chase Log'!$E$4:$E$2000,$W29)))) | Z29: =IF(OR($G29="",N($P29)>=1,$C29="Live",$D29<>""),"",IF(AND($Y29<>"",N($Y29)>0),IF($Y29<TODAY(),"Chase Overdue","Scheduled"),IF(AND($Q29<>"",N($R29)>='안내 Guide'!$D$4,OR($X29="",N($X29)>='안내 Guide'!$D$4)),"Chase Needed",""))) | AG29: Tracker
A30: =IF($G30="","",ROW()-4) -> 26 | B30: =IF($G30="","",IF($C30<>"",$C30,IF($Q30="","Contact",IF($P30>=1,"Live",IF($P30>=0.8,"Pending Live",IF($P30>=0.7,"Testing",IF($P30>=0.45,"In Development",IF($P30>=0.2,"NDA/Contract","Pipeline")))))))) -> Contact | E30: 중화권 · Greater China | F30: China | G30: Qian Tao | H30: 공급 · OMH → Partner | I30: 직접 · Direct | J30: Channel API | K30: Mid | L30: — | M30: Grace | N30: Partner (client-side) | O30: GSM | P30: =IF($G30="","",IFERROR(LOOKUP(2,1/($AH30:$AU30<>""),$AH$2:$AU$2),0)) -> 0 | Q30: =IF(COUNT($AH30:$AU30)=0,"",MAX($AH30:$AU30)) | R30: =IF($Q30="","",TODAY()-$Q30) | S30: =IF($G30="","",IF($Q30="","No Record",IF(OR($P30>=1,$C30="Live"),"Live",IF($R30>=90,"Stalled 90d+",IF($R30>=60,"Stalled 60d+",IF($R30>=30,"Stalled 30d+","In Progress")))))) -> No Record | T30: =IF(COUNT($AH30:$AU30)=0,"",LOOKUP(2,1/($AH30:$AU30<>""),{"① 파이프라인 시작 · Pipeline Start","② 제안·소개 발송 · Proposal Sent","③ NDA 발송 · NDA Sent","④ NDA 체결 · NDA Signed","⑤ 계약 체결 · Contract Signed","⑥ SLA 확정 · SLA Finalized","⑦ 개발 착수 예정 · Kickoff Planned","⑧ 개발 착수 · SPEC/DEV 키 · 크리덴셜 · Kickoff / Credential","⑨ 인증 · Certification","⑩ 라이브 테스트 · Live Test","⑪ 개발 완료 예정 · Dev Complete Planned","⑫ 라이브 키 오픈 (OMH 측) · Live Key Open","⑬ 첫 예약 · First Booking","⑭ 고객 라이브 확정 (고객 통보) · Customer Live"})) | U30: =IF(COUNT($AH30:$AU30)=0,"",IF(N($P30)>=1,MAX($AH30:$AU30),TODAY())-MIN($AH30:$AU30)) | V30: =IF($G30="","",COUNTIF('Chase Log'!$B$4:$B$2000,$G30)) -> 0 | W30: =IF(N($V30)=0,"",_xlfn.MAXIFS('Chase Log'!$E$4:$E$2000,'Chase Log'!$B$4:$B$2000,$G30)) | X30: =IF($W30="","",TODAY()-$W30) | Y30: =IF($W30="","",IF(OR(AND($Q30<>"",N($Q30)>N($W30)),COUNTIFS('Chase Log'!$B$4:$B$2000,$G30,'Chase Log'!$E$4:$E$2000,$W30,'Chase Log'!$I$4:$I$2000,"Y")>0),"",IF(_xlfn.MAXIFS('Chase Log'!$J$4:$J$2000,'Chase Log'!$B$4:$B$2000,$G30,'Chase Log'!$E$4:$E$2000,$W30)=0,"",_xlfn.MAXIFS('Chase Log'!$J$4:$J$2000,'Chase Log'!$B$4:$B$2000,$G30,'Chase Log'!$E$4:$E$2000,$W30)))) | Z30: =IF(OR($G30="",N($P30)>=1,$C30="Live",$D30<>""),"",IF(AND($Y30<>"",N($Y30)>0),IF($Y30<TODAY(),"Chase Overdue","Scheduled"),IF(AND($Q30<>"",N($R30)>='안내 Guide'!$D$4,OR($X30="",N($X30)>='안내 Guide'!$D$4)),"Chase Needed",""))) | AG30: Tracker
A31: =IF($G31="","",ROW()-4) -> 27 | B31: =IF($G31="","",IF($C31<>"",$C31,IF($Q31="","Contact",IF($P31>=1,"Live",IF($P31>=0.8,"Pending Live",IF($P31>=0.7,"Testing",IF($P31>=0.45,"In Development",IF($P31>=0.2,"NDA/Contract","Pipeline")))))))) -> In Development | C31: In Development | E31: 중화권 · Greater China | F31: China | G31: Wingspulse | H31: 공급 · OMH → Partner | I31: 직접 · Direct | J31: Channel API | K31: Mid | L31: — | M31: Grace | N31: Partner (client-side) | O31: GSM | P31: =IF($G31="","",IFERROR(LOOKUP(2,1/($AH31:$AU31<>""),$AH$2:$AU$2),0)) -> 0 | Q31: =IF(COUNT($AH31:$AU31)=0,"",MAX($AH31:$AU31)) | R31: =IF($Q31="","",TODAY()-$Q31) | S31: =IF($G31="","",IF($Q31="","No Record",IF(OR($P31>=1,$C31="Live"),"Live",IF($R31>=90,"Stalled 90d+",IF($R31>=60,"Stalled 60d+",IF($R31>=30,"Stalled 30d+","In Progress")))))) -> No Record | T31: =IF(COUNT($AH31:$AU31)=0,"",LOOKUP(2,1/($AH31:$AU31<>""),{"① 파이프라인 시작 · Pipeline Start","② 제안·소개 발송 · Proposal Sent","③ NDA 발송 · NDA Sent","④ NDA 체결 · NDA Signed","⑤ 계약 체결 · Contract Signed","⑥ SLA 확정 · SLA Finalized","⑦ 개발 착수 예정 · Kickoff Planned","⑧ 개발 착수 · SPEC/DEV 키 · 크리덴셜 · Kickoff / Credential","⑨ 인증 · Certification","⑩ 라이브 테스트 · Live Test","⑪ 개발 완료 예정 · Dev Complete Planned","⑫ 라이브 키 오픈 (OMH 측) · Live Key Open","⑬ 첫 예약 · First Booking","⑭ 고객 라이브 확정 (고객 통보) · Customer Live"})) | U31: =IF(COUNT($AH31:$AU31)=0,"",IF(N($P31)>=1,MAX($AH31:$AU31),TODAY())-MIN($AH31:$AU31)) | V31: =IF($G31="","",COUNTIF('Chase Log'!$B$4:$B$2000,$G31)) -> 0 | W31: =IF(N($V31)=0,"",_xlfn.MAXIFS('Chase Log'!$E$4:$E$2000,'Chase Log'!$B$4:$B$2000,$G31)) | X31: =IF($W31="","",TODAY()-$W31) | Y31: =IF($W31="","",IF(OR(AND($Q31<>"",N($Q31)>N($W31)),COUNTIFS('Chase Log'!$B$4:$B$2000,$G31,'Chase Log'!$E$4:$E$2000,$W31,'Chase Log'!$I$4:$I$2000,"Y")>0),"",IF(_xlfn.MAXIFS('Chase Log'!$J$4:$J$2000,'Chase Log'!$B$4:$B$2000,$G31,'Chase Log'!$E$4:$E$2000,$W31)=0,"",_xlfn.MAXIFS('Chase Log'!$J$4:$J$2000,'Chase Log'!$B$4:$B$2000,$G31,'Chase Log'!$E$4:$E$2000,$W31)))) | Z31: =IF(OR($G31="",N($P31)>=1,$C31="Live",$D31<>""),"",IF(AND($Y31<>"",N($Y31)>0),IF($Y31<TODAY(),"Chase Overdue","Scheduled"),IF(AND($Q31<>"",N($R31)>='안내 Guide'!$D$4,OR($X31="",N($X31)>='안내 Guide'!$D$4)),"Chase Needed",""))) | AG31: Tracker
A32: =IF($G32="","",ROW()-4) -> 28 | B32: =IF($G32="","",IF($C32<>"",$C32,IF($Q32="","Contact",IF($P32>=1,"Live",IF($P32>=0.8,"Pending Live",IF($P32>=0.7,"Testing",IF($P32>=0.45,"In Development",IF($P32>=0.2,"NDA/Contract","Pipeline")))))))) -> Contact | E32: 동남아 · SE Asia | F32: Vietnam | G32: Gotadi - HCM Branch | H32: 공급 · OMH → Partner | I32: 직접 · Direct | J32: Channel API | K32: Mid | L32: 휴면·재활성화 · Dormant · re-engage | M32: Aiden (지역 공백 · interim) | N32: Partner (client-side) | O32: GSM | P32: =IF($G32="","",IFERROR(LOOKUP(2,1/($AH32:$AU32<>""),$AH$2:$AU$2),0)) -> 0 | Q32: =IF(COUNT($AH32:$AU32)=0,"",MAX($AH32:$AU32)) | R32: =IF($Q32="","",TODAY()-$Q32) | S32: =IF($G32="","",IF($Q32="","No Record",IF(OR($P32>=1,$C32="Live"),"Live",IF($R32>=90,"Stalled 90d+",IF($R32>=60,"Stalled 60d+",IF($R32>=30,"Stalled 30d+","In Progress")))))) -> No Record | T32: =IF(COUNT($AH32:$AU32)=0,"",LOOKUP(2,1/($AH32:$AU32<>""),{"① 파이프라인 시작 · Pipeline Start","② 제안·소개 발송 · Proposal Sent","③ NDA 발송 · NDA Sent","④ NDA 체결 · NDA Signed","⑤ 계약 체결 · Contract Signed","⑥ SLA 확정 · SLA Finalized","⑦ 개발 착수 예정 · Kickoff Planned","⑧ 개발 착수 · SPEC/DEV 키 · 크리덴셜 · Kickoff / Credential","⑨ 인증 · Certification","⑩ 라이브 테스트 · Live Test","⑪ 개발 완료 예정 · Dev Complete Planned","⑫ 라이브 키 오픈 (OMH 측) · Live Key Open","⑬ 첫 예약 · First Booking","⑭ 고객 라이브 확정 (고객 통보) · Customer Live"})) | U32: =IF(COUNT($AH32:$AU32)=0,"",IF(N($P32)>=1,MAX($AH32:$AU32),TODAY())-MIN($AH32:$AU32)) | V32: =IF($G32="","",COUNTIF('Chase Log'!$B$4:$B$2000,$G32)) -> 0 | W32: =IF(N($V32)=0,"",_xlfn.MAXIFS('Chase Log'!$E$4:$E$2000,'Chase Log'!$B$4:$B$2000,$G32)) | X32: =IF($W32="","",TODAY()-$W32) | Y32: =IF($W32="","",IF(OR(AND($Q32<>"",N($Q32)>N($W32)),COUNTIFS('Chase Log'!$B$4:$B$2000,$G32,'Chase Log'!$E$4:$E$2000,$W32,'Chase Log'!$I$4:$I$2000,"Y")>0),"",IF(_xlfn.MAXIFS('Chase Log'!$J$4:$J$2000,'Chase Log'!$B$4:$B$2000,$G32,'Chase Log'!$E$4:$E$2000,$W32)=0,"",_xlfn.MAXIFS('Chase Log'!$J$4:$J$2000,'Chase Log'!$B$4:$B$2000,$G32,'Chase Log'!$E$4:$E$2000,$W32)))) | Z32: =IF(OR($G32="",N($P32)>=1,$C32="Live",$D32<>""),"",IF(AND($Y32<>"",N($Y32)>0),IF($Y32<TODAY(),"Chase Overdue","Scheduled"),IF(AND($Q32<>"",N($R32)>='안내 Guide'!$D$4,OR($X32="",N($X32)>='안내 Guide'!$D$4)),"Chase Needed",""))) | AC32: 재가동 회신 2차 체이스 + OMH 측 개발 deliverable·ETA 확정 | AD32: Second chase for re-engagement reply + confirm OMH-side development deliverables and ETA | AF32: 2026-10-05 | AG32: Tracker
A33: =IF($G33="","",ROW()-4) -> 29 | B33: =IF($G33="","",IF($C33<>"",$C33,IF($Q33="","Contact",IF($P33>=1,"Live",IF($P33>=0.8,"Pending Live",IF($P33>=0.7,"Testing",IF($P33>=0.45,"In Development",IF($P33>=0.2,"NDA/Contract","Pipeline")))))))) -> Contact | E33: 동남아 · SE Asia | F33: Vietnam | G33: Vietravel | H33: 공급 · OMH → Partner | I33: 직접 · Direct | J33: Channel API | K33: High | L33: 계약 협상 중 · Contract talks | M33: Aiden (지역 공백 · interim) | N33: Partner (client-side) | O33: GSM | P33: =IF($G33="","",IFERROR(LOOKUP(2,1/($AH33:$AU33<>""),$AH$2:$AU$2),0)) -> 0 | Q33: =IF(COUNT($AH33:$AU33)=0,"",MAX($AH33:$AU33)) | R33: =IF($Q33="","",TODAY()-$Q33) | S33: =IF($G33="","",IF($Q33="","No Record",IF(OR($P33>=1,$C33="Live"),"Live",IF($R33>=90,"Stalled 90d+",IF($R33>=60,"Stalled 60d+",IF($R33>=30,"Stalled 30d+","In Progress")))))) -> No Record | T33: =IF(COUNT($AH33:$AU33)=0,"",LOOKUP(2,1/($AH33:$AU33<>""),{"① 파이프라인 시작 · Pipeline Start","② 제안·소개 발송 · Proposal Sent","③ NDA 발송 · NDA Sent","④ NDA 체결 · NDA Signed","⑤ 계약 체결 · Contract Signed","⑥ SLA 확정 · SLA Finalized","⑦ 개발 착수 예정 · Kickoff Planned","⑧ 개발 착수 · SPEC/DEV 키 · 크리덴셜 · Kickoff / Credential","⑨ 인증 · Certification","⑩ 라이브 테스트 · Live Test","⑪ 개발 완료 예정 · Dev Complete Planned","⑫ 라이브 키 오픈 (OMH 측) · Live Key Open","⑬ 첫 예약 · First Booking","⑭ 고객 라이브 확정 (고객 통보) · Customer Live"})) | U33: =IF(COUNT($AH33:$AU33)=0,"",IF(N($P33)>=1,MAX($AH33:$AU33),TODAY())-MIN($AH33:$AU33)) | V33: =IF($G33="","",COUNTIF('Chase Log'!$B$4:$B$2000,$G33)) -> 1 | W33: =IF(N($V33)=0,"",_xlfn.MAXIFS('Chase Log'!$E$4:$E$2000,'Chase Log'!$B$4:$B$2000,$G33)) -> 46300 | X33: =IF($W33="","",TODAY()-$W33) -> 25 | Y33: =IF($W33="","",IF(OR(AND($Q33<>"",N($Q33)>N($W33)),COUNTIFS('Chase Log'!$B$4:$B$2000,$G33,'Chase Log'!$E$4:$E$2000,$W33,'Chase Log'!$I$4:$I$2000,"Y")>0),"",IF(_xlfn.MAXIFS('Chase Log'!$J$4:$J$2000,'Chase Log'!$B$4:$B$2000,$G33,'Chase Log'!$E$4:$E$2000,$W33)=0,"",_xlfn.MAXIFS('Chase Log'!$J$4:$J$2000,'Chase Log'!$B$4:$B$2000,$G33,'Chase Log'!$E$4:$E$2000,$W33)))) -> 46307 | Z33: =IF(OR($G33="",N($P33)>=1,$C33="Live",$D33<>""),"",IF(AND($Y33<>"",N($Y33)>0),IF($Y33<TODAY(),"Chase Overdue","Scheduled"),IF(AND($Q33<>"",N($R33)>='안내 Guide'!$D$4,OR($X33="",N($X33)>='안내 Guide'!$D$4)),"Chase Needed",""))) -> Chase Overdue | AA33: 46400 | AB33: Partner | AC33: 계약서 2건 서명 2차 체이스(전화 병행) | AD33: Second chase for signature of 2 contracts (with phone follow-up) | AF33: 2026-10-05 | AG33: Tracker
A34: =IF($G34="","",ROW()-4) -> 30 | B34: =IF($G34="","",IF($C34<>"",$C34,IF($Q34="","Contact",IF($P34>=1,"Live",IF($P34>=0.8,"Pending Live",IF($P34>=0.7,"Testing",IF($P34>=0.45,"In Development",IF($P34>=0.2,"NDA/Contract","Pipeline")))))))) -> Contact | E34: 중동·러시아 · ME & Russia | F34: UAE | G34: Happy Travel | H34: 공급 · OMH → Partner | I34: 직접 · Direct | J34: Channel API | K34: Mid | L34: 계약 협상 중 · Contract talks | M34: Aiden (지역 공백 · interim) | N34: Partner (client-side) | O34: GSM | P34: =IF($G34="","",IFERROR(LOOKUP(2,1/($AH34:$AU34<>""),$AH$2:$AU$2),0)) -> 0 | Q34: =IF(COUNT($AH34:$AU34)=0,"",MAX($AH34:$AU34)) | R34: =IF($Q34="","",TODAY()-$Q34) | S34: =IF($G34="","",IF($Q34="","No Record",IF(OR($P34>=1,$C34="Live"),"Live",IF($R34>=90,"Stalled 90d+",IF($R34>=60,"Stalled 60d+",IF($R34>=30,"Stalled 30d+","In Progress")))))) -> No Record | T34: =IF(COUNT($AH34:$AU34)=0,"",LOOKUP(2,1/($AH34:$AU34<>""),{"① 파이프라인 시작 · Pipeline Start","② 제안·소개 발송 · Proposal Sent","③ NDA 발송 · NDA Sent","④ NDA 체결 · NDA Signed","⑤ 계약 체결 · Contract Signed","⑥ SLA 확정 · SLA Finalized","⑦ 개발 착수 예정 · Kickoff Planned","⑧ 개발 착수 · SPEC/DEV 키 · 크리덴셜 · Kickoff / Credential","⑨ 인증 · Certification","⑩ 라이브 테스트 · Live Test","⑪ 개발 완료 예정 · Dev Complete Planned","⑫ 라이브 키 오픈 (OMH 측) · Live Key Open","⑬ 첫 예약 · First Booking","⑭ 고객 라이브 확정 (고객 통보) · Customer Live"})) | U34: =IF(COUNT($AH34:$AU34)=0,"",IF(N($P34)>=1,MAX($AH34:$AU34),TODAY())-MIN($AH34:$AU34)) | V34: =IF($G34="","",COUNTIF('Chase Log'!$B$4:$B$2000,$G34)) -> 1 | W34: =IF(N($V34)=0,"",_xlfn.MAXIFS('Chase Log'!$E$4:$E$2000,'Chase Log'!$B$4:$B$2000,$G34)) -> 46301 | X34: =IF($W34="","",TODAY()-$W34) -> 24 | Y34: =IF($W34="","",IF(OR(AND($Q34<>"",N($Q34)>N($W34)),COUNTIFS('Chase Log'!$B$4:$B$2000,$G34,'Chase Log'!$E$4:$E$2000,$W34,'Chase Log'!$I$4:$I$2000,"Y")>0),"",IF(_xlfn.MAXIFS('Chase Log'!$J$4:$J$2000,'Chase Log'!$B$4:$B$2000,$G34,'Chase Log'!$E$4:$E$2000,$W34)=0,"",_xlfn.MAXIFS('Chase Log'!$J$4:$J$2000,'Chase Log'!$B$4:$B$2000,$G34,'Chase Log'!$E$4:$E$2000,$W34)))) -> 46308 | Z34: =IF(OR($G34="",N($P34)>=1,$C34="Live",$D34<>""),"",IF(AND($Y34<>"",N($Y34)>0),IF($Y34<TODAY(),"Chase Overdue","Scheduled"),IF(AND($Q34<>"",N($R34)>='안내 Guide'!$D$4,OR($X34="",N($X34)>='안내 Guide'!$D$4)),"Chase Needed",""))) -> Chase Overdue | AC34: ~10/20 체이스, 무응답 시 우선순위 하향/종결 결정 | AD34: Chase by 20 Oct; if no response, decide to lower priority or close | AF34: 2026-10-06 | AG34: Tracker
A35: =IF($G35="","",ROW()-4) -> 31 | B35: =IF($G35="","",IF($C35<>"",$C35,IF($Q35="","Contact",IF($P35>=1,"Live",IF($P35>=0.8,"Pending Live",IF($P35>=0.7,"Testing",IF($P35>=0.45,"In Development",IF($P35>=0.2,"NDA/Contract","Pipeline")))))))) -> Contact | E35: 중동·러시아 · ME & Russia | F35: UAE | G35: Webbeds | H35: 공급 · OMH → Partner | I35: 직접 · Direct | J35: Channel API | K35: High | L35: 휴면·재활성화 · Dormant · re-engage | M35: Aiden (지역 공백 · interim) | N35: OHMY | O35: GSM | P35: =IF($G35="","",IFERROR(LOOKUP(2,1/($AH35:$AU35<>""),$AH$2:$AU$2),0)) -> 0 | Q35: =IF(COUNT($AH35:$AU35)=0,"",MAX($AH35:$AU35)) | R35: =IF($Q35="","",TODAY()-$Q35) | S35: =IF($G35="","",IF($Q35="","No Record",IF(OR($P35>=1,$C35="Live"),"Live",IF($R35>=90,"Stalled 90d+",IF($R35>=60,"Stalled 60d+",IF($R35>=30,"Stalled 30d+","In Progress")))))) -> No Record | T35: =IF(COUNT($AH35:$AU35)=0,"",LOOKUP(2,1/($AH35:$AU35<>""),{"① 파이프라인 시작 · Pipeline Start","② 제안·소개 발송 · Proposal Sent","③ NDA 발송 · NDA Sent","④ NDA 체결 · NDA Signed","⑤ 계약 체결 · Contract Signed","⑥ SLA 확정 · SLA Finalized","⑦ 개발 착수 예정 · Kickoff Planned","⑧ 개발 착수 · SPEC/DEV 키 · 크리덴셜 · Kickoff / Credential","⑨ 인증 · Certification","⑩ 라이브 테스트 · Live Test","⑪ 개발 완료 예정 · Dev Complete Planned","⑫ 라이브 키 오픈 (OMH 측) · Live Key Open","⑬ 첫 예약 · First Booking","⑭ 고객 라이브 확정 (고객 통보) · Customer Live"})) | U35: =IF(COUNT($AH35:$AU35)=0,"",IF(N($P35)>=1,MAX($AH35:$AU35),TODAY())-MIN($AH35:$AU35)) | V35: =IF($G35="","",COUNTIF('Chase Log'!$B$4:$B$2000,$G35)) -> 0 | W35: =IF(N($V35)=0,"",_xlfn.MAXIFS('Chase Log'!$E$4:$E$2000,'Chase Log'!$B$4:$B$2000,$G35)) | X35: =IF($W35="","",TODAY()-$W35) | Y35: =IF($W35="","",IF(OR(AND($Q35<>"",N($Q35)>N($W35)),COUNTIFS('Chase Log'!$B$4:$B$2000,$G35,'Chase Log'!$E$4:$E$2000,$W35,'Chase Log'!$I$4:$I$2000,"Y")>0),"",IF(_xlfn.MAXIFS('Chase Log'!$J$4:$J$2000,'Chase Log'!$B$4:$B$2000,$G35,'Chase Log'!$E$4:$E$2000,$W35)=0,"",_xlfn.MAXIFS('Chase Log'!$J$4:$J$2000,'Chase Log'!$B$4:$B$2000,$G35,'Chase Log'!$E$4:$E$2000,$W35)))) | Z35: =IF(OR($G35="",N($P35)>=1,$C35="Live",$D35<>""),"",IF(AND($Y35<>"",N($Y35)>0),IF($Y35<TODAY(),"Chase Overdue","Scheduled"),IF(AND($Q35<>"",N($R35)>='안내 Guide'!$D$4,OR($X35="",N($X35)>='안내 Guide'!$D$4)),"Chase Needed",""))) | AC35: 'Webbeds DMC' 미수금 JPY 203,300(10/16 신규) 계정 식별·회수 확인 + T17 3rd-party(WebBeds) 판매 확대 진척 점검 + 일·한 성과 호텔 리스트 수령 확인 | AD35: Identify the 'Webbeds DMC' account for receivable JPY 203,300 (new 16 Oct) and confirm collection + check progress on T17 3rd-party (WebBeds) sales expansion + confirm receipt of Japan/Korea top-performing hotel list | AF35: 2026-07-01 | AG35: Tracker
